Workbook

Sheet README
A1: FPGA / AI Hardware Product Research Workbook (Template)
A3: How to use:
A5: 1) Go to 'Inputs_Assumptions' and update USD→INR FX, default duty/GST and Amazon fee assumptions.
A6: 2) Go to 'Products_Master' and fill the site prices (Amazon India, India e-commerce, Alibaba/LCSC/Mouser/DigiKey).
A7: 3) For imported items, enter 'Chosen_Import_Price_USD' and select the source you plan to use; the sheet computes landed cost and recommended selling price.
A8: 4) Review 'Inventory_Plans' tabs (5L/10L/20L) — adjust quantities and ensure totals fit your budget.
A9: 5) Use 'FPGA_Board_BOM' to estimate your own branded Artix-7 board manufacturing cost.
A12: Last generated: | B12: 2025-12-20

Sheet Inputs_Assumptions
A1: Assumptions (edit blue cells)
A3: Parameter | B3: Value | C3: Notes
A4: USD→INR FX rate | B4: 83 | C4: Update daily/weekly.
A5: Default Import Duty % | B5: 0.1 | C5: Edit per product/HSN.
A6: Default GST % | B6: 0.18 | C6: Most electronics 18% in India (verify).
A7: Default Ship/Handling per unit (INR) | B7: 150 | C7: Avg shipping+packing; adjust.
A8: Amazon fees % (referral+closing+FBA avg) | B8: 0.18 | C8: Approx; depends category & weight.
A9: Target Gross Margin % (default) | B9: 0.35 | C9: Used for recommended sell price.
A10: IndiaMart lead cost per month (INR) | B10: 40000 | C10: Optional paid subscription.

Sheet Products_Master
A1: SKU | B1: Category | C1: Product_Type | D1: Product_Name | E1: Brand/Manufacturer | F1: Model/Part_Number | G1: Variant | H1: Key_Specs | I1: Use_Case | J1: Target_Customers | K1: Sourcing_Mode | L1: Primary_Supplier_Planned | M1: Planned_Buy_Price_INR | N1: Planned_Sell_Price_INR | O1: Planned_Gross_Margin_% | P1: AmazonIN_Price_INR | Q1: AmazonIN_URL | R1: IndiaEcom_Price_INR | S1: IndiaEcom_URL | T1: Alibaba_Price_USD | U1: Alibaba_URL | V1: LCSC_Price_USD | W1: LCSC_URL | X1: Mouser_Price_USD | Y1: Mouser_URL | Z1: DigiKey_Price_USD | AA1: DigiKey_URL | AB1: MOQ | AC1: Lead_Time_Days | AD1: Ship/Handling_INR | AE1: Import_Duty_% | AF1: GST_% | AG1: FX_USD_INR | AH1: Chosen_Import_Price_USD | AI1: Chosen_Source | AJ1: Landed_Cost_INR | AK1: Target_Gross_Margin_% | AL1: Recommended_Sell_Price_INR | AM1: Amazon_Fees_% | AN1: Net_Margin_Amazon_% | AO1: Priority | AP1: Qty_5L | AQ1: Qty_10L | AR1: Qty_20L | AS1: Expected_Monthly_Units | AT1: Notes | AU1: Last_Checked_Date | AV1: Source_Notes | AX1: AmazonIN_Price_Checked_Date | AY1: AmazonIN_Seller_Name | AZ1: AmazonIN_Seller_URL | BA1: AmazonIN_Seller_Address | BB1: AmazonIN_Seller_Contact | BC1: IndiaEcom_Price_Checked_Date | BD1: IndiaEcom_Vendor_Name | BE1: IndiaEcom_Vendor_URL | BF1: IndiaEcom_Vendor_Address | BG1: IndiaEcom_Vendor_Contact | BH1: Alibaba_Price_Checked_Date | BI1: Alibaba_Supplier_Name | BJ1: Alibaba_Supplier_URL | BK1: Alibaba_Supplier_Address | BL1: Alibaba_Supplier_Contact | BM1: Best_Price_INR | BN1: Best_Price_Source | BO1: Best_Price_URL | BP1: Best_Vendor_Name | BQ1: Best_Vendor_URL | BR1: Best_Vendor_Address | BS1: Best_Vendor_Contact | BT1: Best_Price_Checked_Date | BU1: Price_Notes | BV1: Price_Workability_Notes | BW1: Best_Channels | BX1: Bundle_Idea_To_Raise_ASP | BY1: Amazon_Listing_Copy | BZ1: Listing_Keywords | CA1: Simple_Launch_Plan | CB1: Supplier_Verification_Status | CC1: Supplier_Type_(Authorized/Reseller/OEM) | CD1: Seller_Supplier_Profile_URL | CE1: Verified_Badges | CF1: Alibaba_SellerCentral_Profile | CG1: Evidence_File_Link_(Screenshot/PDF) | CH1: Payment_Method_Safe_(Y/N) | CI1: Sample_Tested_(Y/N) | CJ1: DOA_Terms_(Days) | CK1: Return_Terms | CL1: Incoterms | CM1: Warranty | CN1: Replacement_Timeline | CO1: Approved_Supplier_(Y/N) | CP1: Best_Price_Vendor_(Auto) | CQ1: Best_Price_Site_URL | CR1: Next_Recheck_Date | CS1: Bottom_Line | CT1: Priority_Label | CU1: Priority_Score | CV1: Priority_Score_Breakdown
A2: FPGA-A7-35T | B2: FPGA Board | C2: Board | D2: Artix-7 FPGA Dev Board | E2: AMD/Xilinx | F2: XC7A35T | G2: A35T dev board | H2: Artix-7, ~33k LUT, DDR3, USB-JTAG | I2: FPGA prototyping, DSP, AI accel | J2: Students, Startups | K2: Both | L2: Rynex/Import | M2: 6500 | N2: 8500 | O2: =IF(AND(M2<>"",N2<>""),(N2-M2)/N2,"") -> 0.23529412 | P2: 3371 | Q2: https://www.amazon.in/Arty-A7-Artix-7-Development-Hobbyists/dp/B07D1DVRG6 | S2: =HYPERLINK("https://robu.in/?s="&SUBSTITUTE($D2," ","+")&"&post_type=product","Robu search") -> Robu search | T2: 282.8 | U2: https://www.alibaba.com/showroom/xilinx-fpga-kit.html | W2: =HYPERLINK("https://www.lcsc.com/search?q="&SUBSTITUTE($D2," ","+"),"LCSC search") -> LCSC search | Y2: =HYPERLINK("https://www.mouser.in/c/?q="&SUBSTITUTE($D2," ","+"),"Mouser search") -> Mouser search | AA2: =HYPERLINK("https://www.digikey.in/en/products/filter?keywords="&SUBSTITUTE($D2," ","+"),"DigiKey search") -> DigiKey search | AC2: =Inputs_Assumptions!$B$7 -> 150 | AD2: =Inputs_Assumptions!$B$7 -> 150 | AE2: =Inputs_Assumptions!$B$5 -> 0.1 | AF2: =Inputs_Assumptions!$B$6 -> 0.18 | AG2: =Inputs_Assumptions!$B$4 -> 83 | AJ2: =IF(AH2<>"",(AH2*AG2+AD2)*(1+AE2)*(1+AF2),(M2+AD2)*(1+AF2)) -> 7847 | AK2: =Inputs_Assumptions!$B$9 -> 0.35 | AL2: =IF(AJ2<>"",AJ2/(1-AK2),"") -> 12072.308 | AM2: =Inputs_Assumptions!$B$8 -> 0.18 | AN2: =IF(AND(P2<>"",AJ2<>"",AM2<>""),(P2-AJ2-P2*AM2)/P2,"") -> -1.5077959 | AO2: A | AP2: 4 | AQ2: 8 | AR2: 16 | AS2: 2 | AW2: 2025-12-20 | AX2: 2025-12-21 | BH2: 2025-12-21 | BV2: Risky at planned sell (needs bundle or cheaper sourcing). Gross≈15%. Est Amazon net≈-3% after ~18% fees. | BW2: Direct (B2B) + IndiaMART RFQs; avoid Amazon unless bundled/priced higher; also local resellers. | BX2: Bundle: correct power adapter + USB cable + JTAG cable option + PMOD starter pack + demo bitstream + quick‑start + onboarding call. | BY2: Title: Artix-7 FPGA Dev Board | Verified/QA Tested | Quick‑Start + Support | GST Invoice Bullets: - Key specs: Artix-7, ~33k LUT, DDR3, USB-JTAG - Use case: FPGA prototyping, DSP, AI accel - Pre‑tested unit with packaging QC sticker + photo proof before dispatch. - Support: setup guide (QR) + WhatsApp troubleshooting; replacement DOA policy. - Ideal for startups/labs/training centers; bulk pricing available. | BZ2: fpga development board, zynq board, artix board, cyclone board, vivado board, quartus board, fpga starter kit, pmod | CA2: Day1–2 sample+QC | Day3 assets+pack insert QR | Day4 IndiaMART+WhatsApp catalog | Week1 Amazon (kit) | Week1–2 LinkedIn/B2B outreach | Week2 small ads + optimize | Bi‑weekly price recheck | CB2: Pending (missing seller profile) | CC2: Reseller (needs confirmation) | CE2: Unknown | CH2: N | CI2: N | CJ2: 7 | CK2: 7 days DOA replacement; unopened returns as per channel policy. | CL2: Domestic shipment (GST invoice preferred) | CM2: 3 months (board functional; no over-voltage/ESD damage). | CN2: 7–14 days (confirm with supplier) | CO2: N | CR2: 2026-01-06 | CS2: Risky at planned sell (needs bundle or cheaper sourcing). Gross≈15%. Est Amazon net≈-3% after ~18% fees. | Channels: Direct (B2B) + IndiaMART RFQs; avoid Amazon unless bundled/priced higher; also local resellers. | Bundle: Bundle: correct power adapter + USB cable + JTAG cable option + PMOD starter pack + demo bitstream + quick‑start + onboarding call. | CT2: High | CU2: 30.2 | CV2: Demand 4.0/40 (units=2.0); Margin 0.0/30 (GM%=-2614260161.3); Channel 0.0/10 (AmazonNet%=NA); Sourcing 6.2/10 (mode=Both); Lead 10.0/10 (days=7.0); Fit 10.0/10; Penalty 0.0/10.
A3: FPGA-A7-100T | B3: FPGA Board | C3: Board | D3: Artix-7 FPGA Dev Board | E3: AMD/Xilinx | F3: XC7A100T | G3: A100T dev board | H3: Artix-7, ~101k LUT, DDR3, USB-JTAG | I3: Higher logic prototypes | J3: Startups, Labs | K3: Import | L3: Import | M3: 10500 | N3: 14500 | O3: =IF(AND(M3<>"",N3<>""),(N3-M3)/N3,"") -> 0.27586207 | P3: 66118 | Q3: https://www.amazon.in/Digilent-Arty-A7-100T-Development/dp/B07V2ZC7R2 | S3: =HYPERLINK("https://robu.in/?s="&SUBSTITUTE($D3," ","+")&"&post_type=product","Robu search") -> Robu search | U3: https://www.alibaba.com/trade/search?SearchText=Artix-7+FPGA+Dev+Board+XC7A100T | W3: =HYPERLINK("https://www.lcsc.com/search?q="&SUBSTITUTE($D3," ","+"),"LCSC search") -> LCSC search | Y3: =HYPERLINK("https://www.mouser.in/c/?q="&SUBSTITUTE($D3," ","+"),"Mouser search") -> Mouser search | AA3: =HYPERLINK("https://www.digikey.in/en/products/filter?keywords="&SUBSTITUTE($D3," ","+"),"DigiKey search") -> DigiKey search | AC3: =Inputs_Assumptions!$B$7 -> 150 | AD3: =Inputs_Assumptions!$B$7 -> 150 | AE3: =Inputs_Assumptions!$B$5 -> 0.1 | AF3: =Inputs_Assumptions!$B$6 -> 0.18 | AG3: =Inputs_Assumptions!$B$4 -> 83 | AJ3: =IF(AH3<>"",(AH3*AG3+AD3)*(1+AE3)*(1+AF3),(M3+AD3)*(1+AF3)) -> 12567 | AK3: =Inputs_Assumptions!$B$9 -> 0.35 | AL3: =IF(AJ3<>"",AJ3/(1-AK3),"") -> 19333.846 | AM3: =Inputs_Assumptions!$B$8 -> 0.18 | AN3: =IF(AND(P3<>"",AJ3<>"",AM3<>""),(P3-AJ3-P3*AM3)/P3,"") -> 0.62993073 | AO3: B | AW3: 2025-12-20 | AX3: 2025-12-21 | BH3: 2025-12-21 | BV3: Works for Direct/B2B; marketplaces need bundle/price-up. Gross≈19%. Est Amazon net≈1% after ~18% fees. | BW3: Direct (B2B) + IndiaMART; Amazon only if bundled/priced higher. | BX3: Bundle: correct power adapter + USB cable + JTAG cable option + PMOD starter pack + demo bitstream + quick‑start + onboarding call. | BY3: Title: Artix-7 FPGA Dev Board | Verified/QA Tested | Quick‑Start + Support | GST Invoice Bullets: - Key specs: Artix-7, ~101k LUT, DDR3, USB-JTAG - Use case: Higher logic prototypes - Pre‑tested unit with packaging QC sticker + photo proof before dispatch. - Support: setup guide (QR) + WhatsApp troubleshooting; replacement DOA policy. - Ideal for startups/labs/training centers; bulk pricing available. | BZ3: fpga development board, zynq board, artix board, cyclone board, vivado board, quartus board, fpga starter kit, pmod | CA3: Day1–2 sample+QC | Day3 assets+pack insert QR | Day4 IndiaMART+WhatsApp catalog | Week1 Amazon (kit) | Week1–2 LinkedIn/B2B outreach | Week2 small ads + optimize | Bi‑weekly price recheck | CB3: Pending (missing seller profile) | CC3: Reseller (needs confirmation) | CE3: Unknown | CH3: N | CI3: N | CJ3: 7 | CK3: 7 days DOA replacement; unopened returns as per channel policy. | CL3: Domestic shipment (GST invoice preferred) | CM3: 3 months (board functional; no over-voltage/ESD damage). | CN3: 7–14 days (confirm with supplier) | CO3: N | CR3: 2026-01-06 | CS3: Works for Direct/B2B; marketplaces need bundle/price-up. Gross≈19%. Est Amazon net≈1% after ~18% fees. | Channels: Direct (B2B) + IndiaMART; Amazon only if bundled/priced higher. | Bundle: Bundle: correct power adapter + USB cable + JTAG cable option + PMOD starter pack + demo bitstream + quick‑start + onboarding call. | CT3: Medium | CU3: 25 | CV3: Demand 0.0/40 (units=0.0); Margin 0.0/30 (GM%=-2298711164.2); Channel 5.0/10 (AmazonNet%=NA); Sourcing 0.0/10 (mode=Import); Lead 10.0/10 (days=7.0); Fit 10.0/10; Penalty 0.0/10.
A4: FPGA-ZYNQ-7020 | B4: FPGA Board | C4: Board | D4: Zynq-7000 Dev Board | E4: AMD/Xilinx | F4: XC7Z020 | G4: Z-7020 board | H4: Dual ARM A9 + FPGA fabric, DDR3 | I4: Embedded + HW accel | J4: Startups, Labs | K4: Both | L4: Rynex/Import | M4: 12500 | N4: 15500 | O4: =IF(AND(M4<>"",N4<>""),(N4-M4)/N4,"") -> 0.19354839 | P4: 50750.1 | Q4: https://www.amazon.in/Digilent-Zybo-Z7-Zynq-7000-Development/dp/B0797G4485 | S4: =HYPERLINK("https://robu.in/?s="&SUBSTITUTE($D4," ","+")&"&post_type=product","Robu search") -> Robu search | T4: 85.5 | U4: https://www.alibaba.com/showroom/zynq-7020-development-board.html | W4: =HYPERLINK("https://www.lcsc.com/search?q="&SUBSTITUTE($D4," ","+"),"LCSC search") -> LCSC search | Y4: =HYPERLINK("https://www.mouser.in/c/?q="&SUBSTITUTE($D4," ","+"),"Mouser search") -> Mouser search | AA4: =HYPERLINK("https://www.digikey.in/en/products/filter?keywords="&SUBSTITUTE($D4," ","+"),"DigiKey search") -> DigiKey search | AC4: =Inputs_Assumptions!$B$7 -> 150 | AD4: =Inputs_Assumptions!$B$7 -> 150 | AE4: =Inputs_Assumptions!$B$5 -> 0.1 | AF4: =Inputs_Assumptions!$B$6 -> 0.18 | AG4: =Inputs_Assumptions!$B$4 -> 83 | AJ4: =IF(AH4<>"",(AH4*AG4+AD4)*(1+AE4)*(1+AF4),(M4+AD4)*(1+AF4)) -> 14927 | AK4: =Inputs_Assumptions!$B$9 -> 0.35 | AL4: =IF(AJ4<>"",AJ4/(1-AK4),"") -> 22964.615 | AM4: =Inputs_Assumptions!$B$8 -> 0.18 | AN4: =IF(AND(P4<>"",AJ4<>"",AM4<>""),(P4-AJ4-P4*AM4)/P4,"") -> 0.5258725 | AO4: A | AP4: 2 | AQ4: 4 | AR4: 8 | AS4: 1 | AW4: 2025-12-20 | AX4: 2025-12-21 | BH4: 2025-12-21 | BV4: Risky at planned sell (needs bundle or cheaper sourcing). Gross≈10%. Est Amazon net≈-8% after ~18% fees. | BW4: Direct (B2B) + IndiaMART RFQs; avoid Amazon unless bundled/priced higher; also local resellers. | BX4: Bundle: correct power adapter + USB cable + JTAG cable option + PMOD starter pack + demo bitstream + quick‑start + onboarding call. | BY4: Title: Zynq-7000 Dev Board | Verified/QA Tested | Quick‑Start + Support | GST Invoice Bullets: - Key specs: Dual ARM A9 + FPGA fabric, DDR3 - Use case: Embedded + HW accel - Pre‑tested unit with packaging QC sticker + photo proof before dispatch. - Support: setup guide (QR) + WhatsApp troubleshooting; replacement DOA policy. - Ideal for startups/labs/training centers; bulk pricing available. | BZ4: fpga development board, zynq board, artix board, cyclone board, vivado board, quartus board, fpga starter kit, pmod | CA4: Day1–2 sample+QC | Day3 assets+pack insert QR | Day4 IndiaMART+WhatsApp catalog | Week1 Amazon (kit) | Week1–2 LinkedIn/B2B outreach | Week2 small ads + optimize | Bi‑weekly price recheck | CB4: Pending (missing seller profile) | CC4: Reseller (needs confirmation) | CE4: Unknown | CH4: N | CI4: N | CJ4: 7 | CK4: 7 days DOA replacement; unopened returns as per channel policy. | CL4: Domestic shipment (GST invoice preferred) | CM4: 3 months (board functional; no over-voltage/ESD damage). | CN4: 7–14 days (confirm with supplier) | CO4: N | CR4: 2026-01-06 | CS4: Risky at planned sell (needs bundle or cheaper sourcing). Gross≈10%. Est Amazon net≈-8% after ~18% fees. | Channels: Direct (B2B) + IndiaMART RFQs; avoid Amazon unless bundled/priced higher; also local resellers. | Bundle: Bundle: correct power adapter + USB cable + JTAG cable option + PMOD starter pack + demo bitstream + quick‑start + onboarding call. | CT4: High | CU4: 28.2 | CV4: Demand 2.0/40 (units=1.0); Margin 0.0/30 (GM%=-2867187928.5); Channel 0.0/10 (AmazonNet%=NA); Sourcing 6.2/10 (mode=Both); Lead 10.0/10 (days=7.0); Fit 10.0/10; Penalty 0.0/10.
A5: FPGA-SPARTAN6 | B5: FPGA Board | C5: Board | D5: Spartan-6 Dev Board | E5: AMD/Xilinx | F5: XC6SLX9/16 | G5: Spartan-6 board | H5: Low cost FPGA, basic IO | I5: Education, legacy designs | J5: Students, Colleges | K5: Local | L5: Local | M5: 4200 | N5: 5800 | O5: =IF(AND(M5<>"",N5<>""),(N5-M5)/N5,"") -> 0.27586207 | P5: 4097 | Q5: https://www.amazon.in/Numato-Lab-Spartan-Development-Board/dp/B00JA2FAVS | S5: =HYPERLINK("https://robu.in/?s="&SUBSTITUTE($D5," ","+")&"&post_type=product","Robu search") -> Robu search | T5: 15.06 | U5: https://www.alibaba.com/showroom/spartan-fpga-development-board.html | W5: =HYPERLINK("https://www.lcsc.com/search?q="&SUBSTITUTE($D5," ","+"),"LCSC search") -> LCSC search | Y5: =HYPERLINK("https://www.mouser.in/c/?q="&SUBSTITUTE($D5," ","+"),"Mouser search") -> Mouser search | AA5: =HYPERLINK("https://www.digikey.in/en/products/filter?keywords="&SUBSTITUTE($D5," ","+"),"DigiKey search") -> DigiKey search | AC5: =Inputs_Assumptions!$B$7 -> 150 | AD5: =Inputs_Assumptions!$B$7 -> 150 | AE5: =Inputs_Assumptions!$B$5 -> 0.1 | AF5: =Inputs_Assumptions!$B$6 -> 0.18 | AG5: =Inputs_Assumptions!$B$4 -> 83 | AJ5: =IF(AH5<>"",(AH5*AG5+AD5)*(1+AE5)*(1+AF5),(M5+AD5)*(1+AF5)) -> 5133 | AK5: =Inputs_Assumptions!$B$9 -> 0.35 | AL5: =IF(AJ5<>"",AJ5/(1-AK5),"") -> 7896.9231 | AM5: =Inputs_Assumptions!$B$8 -> 0.18 | AN5: =IF(AND(P5<>"",AJ5<>"",AM5<>""),(P5-AJ5-P5*AM5)/P5,"") -> -0.43286795 | AO5: A | AW5: 2025-12-20 | AX5: 2025-12-21 | BH5: 2025-12-21 | BV5: Works for Direct/B2B; marketplaces need bundle/price-up. Gross≈19%. Est Amazon net≈1% after ~18% fees. | BW5: Direct (B2B) + IndiaMART; Amazon only if bundled/priced higher. | BX5: Bundle: correct power adapter + USB cable + JTAG cable option + PMOD starter pack + demo bitstream + quick‑start + onboarding call. | BY5: Title: Spartan-6 Dev Board | Verified/QA Tested | Quick‑Start + Support | GST Invoice Bullets: - Key specs: Low cost FPGA, basic IO - Use case: Education, legacy designs - Pre‑tested unit with packaging QC sticker + photo proof before dispatch. - Support: setup guide (QR) + WhatsApp troubleshooting; replacement DOA policy. - Ideal for startups/labs/training centers; bulk pricing available. | BZ5: fpga development board, zynq board, artix board, cyclone board, vivado board, quartus board, fpga starter kit, pmod | CA5: Day1–2 sample+QC | Day3 assets+pack insert QR | Day4 IndiaMART+WhatsApp catalog | Week1 Amazon (kit) | Week1–2 LinkedIn/B2B outreach | Week2 small ads + optimize | Bi‑weekly price recheck | CB5: Pending (missing seller profile) | CC5: Reseller (needs confirmation) | CE5: Unknown | CH5: N | CI5: N | CJ5: 7 | CK5: 7 days DOA replacement; unopened returns as per channel policy. | CL5: Domestic shipment (GST invoice preferred) | CM5: 3 months (board functional; no over-voltage/ESD damage). | CN5: 7–14 days (confirm with supplier) | CO5: N | CR5: 2026-01-06 | CS5: Works for Direct/B2B; marketplaces need bundle/price-up. Gross≈19%. Est Amazon net≈1% after ~18% fees. | Channels: Direct (B2B) + IndiaMART; Amazon only if bundled/priced higher. | Bundle: Bundle: correct power adapter + USB cable + JTAG cable option + PMOD starter pack + demo bitstream + quick‑start + onboarding call. | CT5: High | CU5: 31.2 | CV5: Demand 0.0/40 (units=0.0); Margin 0.0/30 (GM%=-9577847408.9); Channel 5.0/10 (AmazonNet%=NA); Sourcing 6.2/10 (mode=Local); Lead 10.0/10 (days=7.0); Fit 10.0/10; Penalty 0.0/10.
A6: FPGA-ICE40UP5K | B6: FPGA Board | C6: Board | D6: iCE40 UltraPlus Dev Board | E6: Lattice | F6: iCE40UP5K | G6: UP5K board | H6: Low-power FPGA, DSP blocks | I6: Ultra-low power edge, learning | J6: Makers, Startups | K6: Both | L6: Import | M6: 2200 | N6: 3500 | O6: =IF(AND(M6<>"",N6<>""),(N6-M6)/N6,"") -> 0.37142857 | Q6: https://www.amazon.in/s?k=iCE40+UltraPlus+Dev+Board+iCE40UP5K | S6: =HYPERLINK("https://robu.in/?s="&SUBSTITUTE($D6," ","+")&"&post_type=product","Robu search") -> Robu search | U6: https://www.alibaba.com/trade/search?SearchText=iCE40+UltraPlus+Dev+Board+iCE40UP5K | W6: =HYPERLINK("https://www.lcsc.com/search?q="&SUBSTITUTE($D6," ","+"),"LCSC search") -> LCSC search | Y6: =HYPERLINK("https://www.mouser.in/c/?q="&SUBSTITUTE($D6," ","+"),"Mouser search") -> Mouser search | AA6: =HYPERLINK("https://www.digikey.in/en/products/filter?keywords="&SUBSTITUTE($D6," ","+"),"DigiKey search") -> DigiKey search | AC6: =Inputs_Assumptions!$B$7 -> 150 | AD6: =Inputs_Assumptions!$B$7 -> 150 | AE6: =Inputs_Assumptions!$B$5 -> 0.1 | AF6: =Inputs_Assumptions!$B$6 -> 0.18 | AG6: =Inputs_Assumptions!$B$4 -> 83 | AJ6: =IF(AH6<>"",(AH6*AG6+AD6)*(1+AE6)*(1+AF6),(M6+AD6)*(1+AF6)) -> 2773 | AK6: =Inputs_Assumptions!$B$9 -> 0.35 | AL6: =IF(AJ6<>"",AJ6/(1-AK6),"") -> 4266.1538 | AM6: =Inputs_Assumptions!$B$8 -> 0.18 | AN6: =IF(AND(P6<>"",AJ6<>"",AM6<>""),(P6-AJ6-P6*AM6)/P6,"") | AO6: A | AP6: 6 | AQ6: 6 | AR6: 12 | AS6: 2 | AW6: 2025-12-20 | AX6: 2025-12-21 | BH6: 2025-12-21 | BV6: Works (healthy margin). Gross≈30%. Est Amazon net≈12% after ~18% fees. | BW6: Amazon (as verified kit) + Direct (B2B) + IndiaMART; also Website/WhatsApp + LinkedIn outreach. | BX6: Bundle: correct power adapter + USB cable + JTAG cable option + PMOD starter pack + demo bitstream + quick‑start + onboarding call. | BY6: Title: iCE40 UltraPlus Dev Board | Verified/QA Tested | Quick‑Start + Support | GST Invoice Bullets: - Key specs: Low-power FPGA, DSP blocks - Use case: Ultra-low power edge, learning - Pre‑tested unit with packaging QC sticker + photo proof before dispatch. - Support: setup guide (QR) + WhatsApp troubleshooting; replacement DOA policy. - Ideal for startups/labs/training centers; bulk pricing available. | BZ6: fpga development board, zynq board, artix board, cyclone board, vivado board, quartus board, fpga starter kit, pmod | CA6: Day1–2 sample+QC | Day3 assets+pack insert QR | Day4 IndiaMART+WhatsApp catalog | Week1 Amazon (kit) | Week1–2 LinkedIn/B2B outreach | Week2 small ads + optimize | Bi‑weekly price recheck | CB6: Pending (missing seller profile) | CC6: Reseller (needs confirmation) | CE6: Unknown | CH6: N | CI6: N | CJ6: 7 | CK6: 7 days DOA replacement; unopened returns as per channel policy. | CL6: Domestic shipment (GST invoice preferred) | CM6: 3 months (board functional; no over-voltage/ESD damage). | CN6: 7–14 days (confirm with supplier) | CO6: N | CR6: 2026-01-06 | CS6: Works (healthy margin). Gross≈30%. Est Amazon net≈12% after ~18% fees. | Channels: Amazon (as verified kit) + Direct (B2B) + IndiaMART; also Website/WhatsApp + LinkedIn outreach. | Bundle: Bundle: correct power adapter + USB cable + JTAG cable option + PMOD starter pack + demo bitstream + quick‑start + onboarding call. | CT6: High | CU6: 35.2 | CV6: Demand 4.0/40 (units=2.0); Margin 0.0/30 (GM%=-19046176089.0); Channel 5.0/10 (AmazonNet%=NA); Sourcing 6.2/10 (mode=Both); Lead 10.0/10 (days=7.0); Fit 10.0/10; Penalty 0.0/10.
A7: FPGA-ECP5-25F | B7: FPGA Board | C7: Board | D7: ECP5 Dev Board | E7: Lattice | F7: LFE5U-25F | G7: 25F board | H7: ECP5 FPGA, SerDes, DDR3 optional | I7: Edge video, custom accel | J7: Startups, Labs | K7: Import | L7: Import | M7: 5800 | N7: 8000 | O7: =IF(AND(M7<>"",N7<>""),(N7-M7)/N7,"") -> 0.275 | P7: 10156.4 | Q7: https://www.amazon.in/Lattice-ECP5-FPGA-RISC-V-Development/dp/B0BKF9NDGZ | S7: =HYPERLINK("https://robu.in/?s="&SUBSTITUTE($D7," ","+")&"&post_type=product","Robu search") -> Robu search | T7: 21.28 | U7: https://m.alibaba.com/showroom/ecp5-fpga.html | W7: =HYPERLINK("https://www.lcsc.com/search?q="&SUBSTITUTE($D7," ","+"),"LCSC search") -> LCSC search | Y7: =HYPERLINK("https://www.mouser.in/c/?q="&SUBSTITUTE($D7," ","+"),"Mouser search") -> Mouser search | AA7: =HYPERLINK("https://www.digikey.in/en/products/filter?keywords="&SUBSTITUTE($D7," ","+"),"DigiKey search") -> DigiKey search | AC7: =Inputs_Assumptions!$B$7 -> 150 | AD7: =Inputs_Assumptions!$B$7 -> 150 | AE7: =Inputs_Assumptions!$B$5 -> 0.1 | AF7: =Inputs_Assumptions!$B$6 -> 0.18 | AG7: =Inputs_Assumptions!$B$4 -> 83 | AJ7: =IF(AH7<>"",(AH7*AG7+AD7)*(1+AE7)*(1+AF7),(M7+AD7)*(1+AF7)) -> 7021 | AK7: =Inputs_Assumptions!$B$9 -> 0.35 | AL7: =IF(AJ7<>"",AJ7/(1-AK7),"") -> 10801.538 | AM7: =Inputs_Assumptions!$B$8 -> 0.18 | AN7: =IF(AND(P7<>"",AJ7<>"",AM7<>""),(P7-AJ7-P7*AM7)/P7,"") -> 0.12871175 | AO7: A | AP7: 3 | AQ7: 6 | AR7: 12 | AS7: 2 | AW7: 2025-12-20 | AX7: 2025-12-21 | BH7: 2025-12-21 | BV7: Works for Direct/B2B; marketplaces need bundle/price-up. Gross≈19%. Est Amazon net≈1% after ~18% fees. | BW7: Direct (B2B) + IndiaMART; Amazon only if bundled/priced higher. | BX7: Bundle: correct power adapter + USB cable + JTAG cable option + PMOD starter pack + demo bitstream + quick‑start + onboarding call. | BY7: Title: ECP5 Dev Board | Verified/QA Tested | Quick‑Start + Support | GST Invoice Bullets: - Key specs: ECP5 FPGA, SerDes, DDR3 optional - Use case: Edge video, custom accel - Pre‑tested unit with packaging QC sticker + photo proof before dispatch. - Support: setup guide (QR) + WhatsApp troubleshooting; replacement DOA policy. - Ideal for startups/labs/training centers; bulk pricing available. | BZ7: fpga development board, zynq board, artix board, cyclone board, vivado board, quartus board, fpga starter kit, pmod | CA7: Day1–2 sample+QC | Day3 assets+pack insert QR | Day4 IndiaMART+WhatsApp catalog | Week1 Amazon (kit) | Week1–2 LinkedIn/B2B outreach | Week2 small ads + optimize | Bi‑weekly price recheck | CB7: Pending (missing seller profile) | CC7: Reseller (needs confirmation) | CE7: Unknown | CH7: N | CI7: N | CJ7: 7 | CK7: 7 days DOA replacement; unopened returns as per channel policy. | CL7: Domestic shipment (GST invoice preferred) | CM7: 3 months (board functional; no over-voltage/ESD damage). | CN7: 7–14 days (confirm with supplier) | CO7: N | CR7: 2026-01-06 | CS7: Works for Direct/B2B; marketplaces need bundle/price-up. Gross≈19%. Est Amazon net≈1% after ~18% fees. | Channels: Direct (B2B) + IndiaMART; Amazon only if bundled/priced higher. | Bundle: Bundle: correct power adapter + USB cable + JTAG cable option + PMOD starter pack + demo bitstream + quick‑start + onboarding call. | CT7: High | CU7: 29 | CV7: Demand 4.0/40 (units=2.0); Margin 0.0/30 (GM%=-9721464621.5); Channel 5.0/10 (AmazonNet%=NA); Sourcing 0.0/10 (mode=Import); Lead 10.0/10 (days=7.0); Fit 10.0/10; Penalty 0.0/10.
A8: FPGA-ECP5-45F | B8: FPGA Board | C8: Board | D8: ECP5 Dev Board | E8: Lattice | F8: LFE5U-45F | G8: 45F board | H8: Mid-range ECP5, better fabric | I8: Edge compute, camera pipelines | J8: Startups, Labs | K8: Import | L8: Import | M8: 7500 | N8: 10200 | O8: =IF(AND(M8<>"",N8<>""),(N8-M8)/N8,"") -> 0.26470588 | Q8: https://www.amazon.in/s?k=ECP5+Dev+Board+LFE5U-45F | S8: =HYPERLINK("https://robu.in/?s="&SUBSTITUTE($D8," ","+")&"&post_type=product","Robu search") -> Robu search | U8: https://www.alibaba.com/trade/search?SearchText=ECP5+Dev+Board+LFE5U-45F | W8: =HYPERLINK("https://www.lcsc.com/search?q="&SUBSTITUTE($D8," ","+"),"LCSC search") -> LCSC search | Y8: =HYPERLINK("https://www.mouser.in/c/?q="&SUBSTITUTE($D8," ","+"),"Mouser search") -> Mouser search | AA8: =HYPERLINK("https://www.digikey.in/en/products/filter?keywords="&SUBSTITUTE($D8," ","+"),"DigiKey search") -> DigiKey search | AC8: =Inputs_Assumptions!$B$7 -> 150 | AD8: =Inputs_Assumptions!$B$7 -> 150 | AE8: =Inputs_Assumptions!$B$5 -> 0.1 | AF8: =Inputs_Assumptions!$B$6 -> 0.18 | AG8: =Inputs_Assumptions!$B$4 -> 83 | AJ8: =IF(AH8<>"",(AH8*AG8+AD8)*(1+AE8)*(1+AF8),(M8+AD8)*(1+AF8)) -> 9027 | AK8: =Inputs_Assumptions!$B$9 -> 0.35 | AL8: =IF(AJ8<>"",AJ8/(1-AK8),"") -> 13887.692 | AM8: =Inputs_Assumptions!$B$8 -> 0.18 | AN8: =IF(AND(P8<>"",AJ8<>"",AM8<>""),(P8-AJ8-P8*AM8)/P8,"") | AO8: B | AR8: 6 | AW8: 2025-12-20 | AX8: 2025-12-21 | BH8: 2025-12-21 | BV8: Works for Direct/B2B; marketplaces need bundle/price-up. Gross≈18%. Est Amazon net≈0% after ~18% fees. | BW8: Direct (B2B) + IndiaMART; Amazon only if bundled/priced higher. | BX8: Bundle: correct power adapter + USB cable + JTAG cable option + PMOD starter pack + demo bitstream + quick‑start + onboarding call. | BY8: Title: ECP5 Dev Board | Verified/QA Tested | Quick‑Start + Support | GST Invoice Bullets: - Key specs: Mid-range ECP5, better fabric - Use case: Edge compute, camera pipelines - Pre‑tested unit with packaging QC sticker + photo proof before dispatch. - Support: setup guide (QR) + WhatsApp troubleshooting; replacement DOA policy. - Ideal for startups/labs/training centers; bulk pricing available. | BZ8: fpga development board, zynq board, artix board, cyclone board, vivado board, quartus board, fpga starter kit, pmod | CA8: Day1–2 sample+QC | Day3 assets+pack insert QR | Day4 IndiaMART+WhatsApp catalog | Week1 Amazon (kit) | Week1–2 LinkedIn/B2B outreach | Week2 small ads + optimize | Bi‑weekly price recheck | CB8: Pending (missing seller profile) | CC8: Reseller (needs confirmation) | CE8: Unknown | CH8: N | CI8: N | CJ8: 7 | CK8: 7 days DOA replacement; unopened returns as per channel policy. | CL8: Domestic shipment (GST invoice preferred) | CM8: 3 months (board functional; no over-voltage/ESD damage). | CN8: 7–14 days (confirm with supplier) | CO8: N | CR8: 2026-01-06 | CS8: Works for Direct/B2B; marketplaces need bundle/price-up. Gross≈18%. Est Amazon net≈0% after ~18% fees. | Channels: Direct (B2B) + IndiaMART; Amazon only if bundled/priced higher. | Bundle: Bundle: correct power adapter + USB cable + JTAG cable option + PMOD starter pack + demo bitstream + quick‑start + onboarding call. | CT8: Medium | CU8: 25 | CV8: Demand 0.0/40 (units=0.0); Margin 0.0/30 (GM%=-8713903711.9); Channel 5.0/10 (AmazonNet%=NA); Sourcing 0.0/10 (mode=Import); Lead 10.0/10 (days=7.0); Fit 10.0/10; Penalty 0.0/10.
A9: FPGA-ECP5-85F | B9: FPGA Board | C9: Board | D9: ECP5 Dev Board | E9: Lattice | F9: LFE5U-85F | G9: 85F board | H9: High-density ECP5 | I9: Advanced edge accel | J9: Startups | K9: Import | L9: Import | M9: 9800 | N9: 13500 | O9: =IF(AND(M9<>"",N9<>""),(N9-M9)/N9,"") -> 0.27407407 | Q9: https://www.amazon.in/s?k=ECP5+Dev+Board+LFE5U-85F | S9: =HYPERLINK("https://robu.in/?s="&SUBSTITUTE($D9," ","+")&"&post_type=product","Robu search") -> Robu search | U9: https://www.alibaba.com/trade/search?SearchText=ECP5+Dev+Board+LFE5U-85F | W9: =HYPERLINK("https://www.lcsc.com/search?q="&SUBSTITUTE($D9," ","+"),"LCSC search") -> LCSC search | Y9: =HYPERLINK("https://www.mouser.in/c/?q="&SUBSTITUTE($D9," ","+"),"Mouser search") -> Mouser search | AA9: =HYPERLINK("https://www.digikey.in/en/products/filter?keywords="&SUBSTITUTE($D9," ","+"),"DigiKey search") -> DigiKey search | AC9: =Inputs_Assumptions!$B$7 -> 150 | AD9: =Inputs_Assumptions!$B$7 -> 150 | AE9: =Inputs_Assumptions!$B$5 -> 0.1 | AF9: =Inputs_Assumptions!$B$6 -> 0.18 | AG9: =Inputs_Assumptions!$B$4 -> 83 | AJ9: =IF(AH9<>"",(AH9*AG9+AD9)*(1+AE9)*(1+AF9),(M9+AD9)*(1+AF9)) -> 11741 | AK9: =Inputs_Assumptions!$B$9 -> 0.35 | AL9: =IF(AJ9<>"",AJ9/(1-AK9),"") -> 18063.077 | AM9: =Inputs_Assumptions!$B$8 -> 0.18 | AN9: =IF(AND(P9<>"",AJ9<>"",AM9<>""),(P9-AJ9-P9*AM9)/P9,"") | AO9: B | AW9: 2025-12-20 | AX9: 2025-12-21 | BH9: 2025-12-21 | BV9: Works for Direct/B2B; marketplaces need bundle/price-up. Gross≈19%. Est Amazon net≈1% after ~18% fees. | BW9: Direct (B2B) + IndiaMART; Amazon only if bundled/priced higher. | BX9: Bundle: correct power adapter + USB cable + JTAG cable option + PMOD starter pack + demo bitstream + quick‑start + onboarding call. | BY9: Title: ECP5 Dev Board | Verified/QA Tested | Quick‑Start + Support | GST Invoice Bullets: - Key specs: High-density ECP5 - Use case: Advanced edge accel - Pre‑tested unit with packaging QC sticker + photo proof before dispatch. - Support: setup guide (QR) + WhatsApp troubleshooting; replacement DOA policy. - Ideal for startups/labs/training centers; bulk pricing available. | BZ9: fpga development board, zynq board, artix board, cyclone board, vivado board, quartus board, fpga starter kit, pmod | CA9: Day1–2 sample+QC | Day3 assets+pack insert QR | Day4 IndiaMART+WhatsApp catalog | Week1 Amazon (kit) | Week1–2 LinkedIn/B2B outreach | Week2 small ads + optimize | Bi‑weekly price recheck | CB9: Pending (missing seller profile) | CC9: Reseller (needs confirmation) | CE9: Unknown | CH9: N | CI9: N | CJ9: 7 | CK9: 7 days DOA replacement; unopened returns as per channel policy. | CL9: Domestic shipment (GST invoice preferred) | CM9: 3 months (board functional; no over-voltage/ESD damage). | CN9: 7–14 days (confirm with supplier) | CO9: N | CR9: 2026-01-06 | CS9: Works for Direct/B2B; marketplaces need bundle/price-up. Gross≈19%. Est Amazon net≈1% after ~18% fees. | Channels: Direct (B2B) + IndiaMART; Amazon only if bundled/priced higher. | Bundle: Bundle: correct power adapter + USB cable + JTAG cable option + PMOD starter pack + demo bitstream + quick‑start + onboarding call. | CT9: Medium | CU9: 25 | CV9: Demand 0.0/40 (units=0.0); Margin 0.0/30 (GM%=-7406808788.3); Channel 5.0/10 (AmazonNet%=NA); Sourcing 0.0/10 (mode=Import); Lead 10.0/10 (days=7.0); Fit 10.0/10; Penalty 0.0/10.
A10: FPGA-MAX10 | B10: FPGA Board | C10: Board | D10: MAX10 Dev Board | E10: Intel/Altera | F10: MAX10 | G10: MAX10 kit | H10: Low-power FPGA + ADC | I10: Industrial control | J10: Colleges, Industry | K10: Both | L10: Import | M10: 6500 | N10: 8800 | O10: =IF(AND(M10<>"",N10<>""),(N10-M10)/N10,"") -> 0.26136364 | P10: 16098 | Q10: https://www.amazon.in/Altera-MAX10-FPGA-Development-Board/dp/B07B4WPKGS | S10: =HYPERLINK("https://robu.in/?s="&SUBSTITUTE($D10," ","+")&"&post_type=product","Robu search") -> Robu search | T10: 81.5 | U10: https://www.alibaba.com/product-detail/DK-DEV-10M50F484-B-MAX-10_1601294733718.html | W10: =HYPERLINK("https://www.lcsc.com/search?q="&SUBSTITUTE($D10," ","+"),"LCSC search") -> LCSC search | Y10: =HYPERLINK("https://www.mouser.in/c/?q="&SUBSTITUTE($D10," ","+"),"Mouser search") -> Mouser search | AA10: =HYPERLINK("https://www.digikey.in/en/products/filter?keywords="&SUBSTITUTE($D10," ","+"),"DigiKey search") -> DigiKey search | AC10: =Inputs_Assumptions!$B$7 -> 150 | AD10: =Inputs_Assumptions!$B$7 -> 150 | AE10: =Inputs_Assumptions!$B$5 -> 0.1 | AF10: =Inputs_Assumptions!$B$6 -> 0.18 | AG10: =Inputs_Assumptions!$B$4 -> 83 | AJ10: =IF(AH10<>"",(AH10*AG10+AD10)*(1+AE10)*(1+AF10),(M10+AD10)*(1+AF10)) -> 7847 | AK10: =Inputs_Assumptions!$B$9 -> 0.35 | AL10: =IF(AJ10<>"",AJ10/(1-AK10),"") -> 12072.308 | AM10: =Inputs_Assumptions!$B$8 -> 0.18 | AN10: =IF(AND(P10<>"",AJ10<>"",AM10<>""),(P10-AJ10-P10*AM10)/P10,"") -> 0.33254814 | AO10: A | AW10: 2025-12-20 | AX10: 2025-12-21 | BH10: 2025-12-21 | BV10: Works for Direct/B2B; marketplaces need bundle/price-up. Gross≈18%. Est Amazon net≈-0% after ~18% fees. | BW10: Direct (B2B) + IndiaMART; Amazon only if bundled/priced higher. | BX10: Bundle: correct power adapter + USB cable + JTAG cable option + PMOD starter pack + demo bitstream + quick‑start + onboarding call. | BY10: Title: MAX10 Dev Board | Verified/QA Tested | Quick‑Start + Support | GST Invoice Bullets: - Key specs: Low-power FPGA + ADC - Use case: Industrial control - Pre‑tested unit with packaging QC sticker + photo proof before dispatch. - Support: setup guide (QR) + WhatsApp troubleshooting; replacement DOA policy. - Ideal for startups/labs/training centers; bulk pricing available. | BZ10: fpga development board, zynq board, artix board, cyclone board, vivado board, quartus board, fpga starter kit, pmod | CA10: Day1–2 sample+QC | Day3 assets+pack insert QR | Day4 IndiaMART+WhatsApp catalog | Week1 Amazon (kit) | Week1–2 LinkedIn/B2B outreach | Week2 small ads + optimize | Bi‑weekly price recheck | CB10: Pending (missing seller profile) | CC10: Reseller (needs confirmation) | CE10: Unknown | CH10: N | CI10: N | CJ10: 7 | CK10: 7 days DOA replacement; unopened returns as per channel policy. | CL10: Domestic shipment (GST invoice preferred) | CM10: 3 months (board functional; no over-voltage/ESD damage). | CN10: 7–14 days (confirm with supplier) | CO10: N | CR10: 2026-01-06 | CS10: Works for Direct/B2B; marketplaces need bundle/price-up. Gross≈18%. Est Amazon net≈-0% after ~18% fees. | Channels: Direct (B2B) + IndiaMART; Amazon only if bundled/priced higher. | Bundle: Bundle: correct power adapter + USB cable + JTAG cable option + PMOD starter pack + demo bitstream + quick‑start + onboarding call. | CT10: High | CU10: 31.2 | CV10: Demand 0.0/40 (units=0.0); Margin 0.0/30 (GM%=-1147842057967056768.0); Channel 5.0/10 (AmazonNet%=NA); Sourcing 6.2/10 (mode=Both); Lead 10.0/10 (days=7.0); Fit 10.0/10; Penalty 0.0/10.
A11: FPGA-CYC5GX | B11: FPGA Board | C11: Board | D11: Cyclone V GX Dev Board | E11: Intel/Altera | F11: Cyclone V GX | G11: GX board | H11: Transceivers, DDR3/DDR4 | I11: High-speed IO prototypes | J11: Industry, Labs | K11: Import | L11: Import | M11: 16500 | N11: 21000 | O11: =IF(AND(M11<>"",N11<>""),(N11-M11)/N11,"") -> 0.21428571 | Q11: https://www.amazon.in/s?k=Cyclone+V+GX+Dev+Board+Cyclone+V+GX | S11: =HYPERLINK("https://robu.in/?s="&SUBSTITUTE($D11," ","+")&"&post_type=product","Robu search") -> Robu search | U11: https://www.alibaba.com/trade/search?SearchText=Cyclone+V+GX+Dev+Board+Cyclone+V+GX | W11: =HYPERLINK("https://www.lcsc.com/search?q="&SUBSTITUTE($D11," ","+"),"LCSC search") -> LCSC search | Y11: =HYPERLINK("https://www.mouser.in/c/?q="&SUBSTITUTE($D11," ","+"),"Mouser search") -> Mouser search | AA11: =HYPERLINK("https://www.digikey.in/en/products/filter?keywords="&SUBSTITUTE($D11," ","+"),"DigiKey search") -> DigiKey search | AC11: =Inputs_Assumptions!$B$7 -> 150 | AD11: =Inputs_Assumptions!$B$7 -> 150 | AE11: =Inputs_Assumptions!$B$5 -> 0.1 | AF11: =Inputs_Assumptions!$B$6 -> 0.18 | AG11: =Inputs_Assumptions!$B$4 -> 83 | AJ11: =IF(AH11<>"",(AH11*AG11+AD11)*(1+AE11)*(1+AF11),(M11+AD11)*(1+AF11)) -> 19647 | AK11: =Inputs_Assumptions!$B$9 -> 0.35 | AL11: =IF(AJ11<>"",AJ11/(1-AK11),"") -> 30226.154 | AM11: =Inputs_Assumptions!$B$8 -> 0.18 | AN11: =IF(AND(P11<>"",AJ11<>"",AM11<>""),(P11-AJ11-P11*AM11)/P11,"") | AO11: C | AW11: 2025-12-20 | AX11: 2025-12-21 | BH11: 2025-12-21 | BV11: Risky at planned sell (needs bundle or cheaper sourcing). Gross≈13%. Est Amazon net≈-5% after ~18% fees. | BW11: Direct (B2B) + IndiaMART RFQs; avoid Amazon unless bundled/priced higher; also local resellers. | BX11: Bundle: correct power adapter + USB cable + JTAG cable option + PMOD starter pack + demo bitstream + quick‑start + onboarding call. | BY11: Title: Cyclone V GX Dev Board | Verified/QA Tested | Quick‑Start + Support | GST Invoice Bullets: - Key specs: Transceivers, DDR3/DDR4 - Use case: High-speed IO prototypes - Pre‑tested unit with packaging QC sticker + photo proof before dispatch. - Support: setup guide (QR) + WhatsApp troubleshooting; replacement DOA policy. - Ideal for startups/labs/training centers; bulk pricing available. | BZ11: fpga development board, zynq board, artix board, cyclone board, vivado board, quartus board, fpga starter kit, pmod | CA11: Day1–2 sample+QC | Day3 assets+pack insert QR | Day4 IndiaMART+WhatsApp catalog | Week1 Amazon (kit) | Week1–2 LinkedIn/B2B outreach | Week2 small ads + optimize | Bi‑weekly price recheck | CB11: Pending (missing seller profile) | CC11: Reseller (needs confirmation) | CE11: Unknown | CH11: N | CI11: N | CJ11: 7 | CK11: 7 days DOA replacement; unopened returns as per channel policy. | CL11: Domestic shipment (GST invoice preferred) | CM11: 3 months (board functional; no over-voltage/ESD damage). | CN11: 7–14 days (confirm with supplier) | CO11: N | CR11: 2026-01-06 | CS11: Risky at planned sell (needs bundle or cheaper sourcing). Gross≈13%. Est Amazon net≈-5% after ~18% fees. | Channels: Direct (B2B) + IndiaMART RFQs; avoid Amazon unless bundled/priced higher; also local resellers. | Bundle: Bundle: correct power adapter + USB cable + JTAG cable option + PMOD starter pack + demo bitstream + quick‑start + onboarding call. | CT11: Low | CU11: 20 | CV11: Demand 0.0/40 (units=0.0); Margin 0.0/30 (GM%=-529100529100529024.0); Channel 0.0/10 (AmazonNet%=NA); Sourcing 0.0/10 (mode=Import); Lead 10.0/10 (days=7.0); Fit 10.0/10; Penalty 0.0/10.
A12: FPGA-CYC10LP | B12: FPGA Board | C12: Board | D12: Cyclone 10 LP Dev Board | E12: Intel/Altera | F12: Cyclone 10 LP | G12: LP kit | H12: Low-power FPGA | I12: Education, control | J12: Colleges | K12: Import | L12: Import | M12: 7200 | N12: 9800 | O12: =IF(AND(M12<>"",N12<>""),(N12-M12)/N12,"") -> 0.26530612 | Q12: https://www.amazon.in/s?k=Cyclone+10+LP+Dev+Board+Cyclone+10+LP | S12: =HYPERLINK("https://robu.in/?s="&SUBSTITUTE($D12," ","+")&"&post_type=product","Robu search") -> Robu search | T12: 99.95 | U12: https://www.alibaba.com/product-detail/Intel-Cyclone-10-LP-FPGA-Development_1601280047239.html | W12: =HYPERLINK("https://www.lcsc.com/search?q="&SUBSTITUTE($D12," ","+"),"LCSC search") -> LCSC search | Y12: =HYPERLINK("https://www.mouser.in/c/?q="&SUBSTITUTE($D12," ","+"),"Mouser search") -> Mouser search | AA12: =HYPERLINK("https://www.digikey.in/en/products/filter?keywords="&SUBSTITUTE($D12," ","+"),"DigiKey search") -> DigiKey search | AC12: =Inputs_Assumptions!$B$7 -> 150 | AD12: =Inputs_Assumptions!$B$7 -> 150 | AE12: =Inputs_Assumptions!$B$5 -> 0.1 | AF12: =Inputs_Assumptions!$B$6 -> 0.18 | AG12: =Inputs_Assumptions!$B$4 -> 83 | AJ12: =IF(AH12<>"",(AH12*AG12+AD12)*(1+AE12)*(1+AF12),(M12+AD12)*(1+AF12)) -> 8673 | AK12: =Inputs_Assumptions!$B$9 -> 0.35 | AL12: =IF(AJ12<>"",AJ12/(1-AK12),"") -> 13343.077 | AM12: =Inputs_Assumptions!$B$8 -> 0.18 | AN12: =IF(AND(P12<>"",AJ12<>"",AM12<>""),(P12-AJ12-P12*AM12)/P12,"") | AO12: B | AR12: 4 | AW12: 2025-12-20 | AX12: 2025-12-21 | BH12: 2025-12-21 | BV12: Works for Direct/B2B; marketplaces need bundle/price-up. Gross≈18%. Est Amazon net≈0% after ~18% fees. | BW12: Direct (B2B) + IndiaMART; Amazon only if bundled/priced higher. | BX12: Bundle: correct power adapter + USB cable + JTAG cable option + PMOD starter pack + demo bitstream + quick‑start + onboarding call. | BY12: Title: Cyclone 10 LP Dev Board | Verified/QA Tested | Quick‑Start + Support | GST Invoice Bullets: - Key specs: Low-power FPGA - Use case: Education, control - Pre‑tested unit with packaging QC sticker + photo proof before dispatch. - Support: setup guide (QR) + WhatsApp troubleshooting; replacement DOA policy. - Ideal for startups/labs/training centers; bulk pricing available. | BZ12: fpga development board, zynq board, artix board, cyclone board, vivado board, quartus board, fpga starter kit, pmod | CA12: Day1–2 sample+QC | Day3 assets+pack insert QR | Day4 IndiaMART+WhatsApp catalog | Week1 Amazon (kit) | Week1–2 LinkedIn/B2B outreach | Week2 small ads + optimize | Bi‑weekly price recheck | CB12: Pending (missing seller profile) | CC12: Reseller (needs confirmation) | CE12: Unknown | CH12: N | CI12: N | CJ12: 7 | CK12: 7 days DOA replacement; unopened returns as per channel policy. | CL12: Domestic shipment (GST invoice preferred) | CM12: 3 months (board functional; no over-voltage/ESD damage). | CN12: 7–14 days (confirm with supplier) | CO12: N | CR12: 2026-01-06 | CS12: Works for Direct/B2B; marketplaces need bundle/price-up. Gross≈18%. Est Amazon net≈0% after ~18% fees. | Channels: Direct (B2B) + IndiaMART; Amazon only if bundled/priced higher. | Bundle: Bundle: correct power adapter + USB cable + JTAG cable option + PMOD starter pack + demo bitstream + quick‑start + onboarding call. | CT12: Medium | CU12: 25 | CV12: Demand 0.0/40 (units=0.0); Margin 0.0/30 (GM%=-1236858378786950912.0); Channel 5.0/10 (AmazonNet%=NA); Sourcing 0.0/10 (mode=Import); Lead 10.0/10 (days=7.0); Fit 10.0/10; Penalty 0.0/10.
A13: FPGA-ZU-DEV | B13: FPGA Board | C13: Board | D13: Zynq UltraScale+ Dev Kit | E13: AMD/Xilinx | F13: ZU3EG/ZU5EV | G13: UltraScale+ kit | H13: ARM A53 + FPGA fabric | I13: High-end edge compute | J13: Industry, funded startups | K13: Import | L13: Import | M13: 65000 | N13: 82000 | O13: =IF(AND(M13<>"",N13<>""),(N13-M13)/N13,"") -> 0.20731707 | Q13: https://www.amazon.in/s?k=Zynq+UltraScale%2B+Dev+Kit+ZU3EG%2FZU5EV | S13: =HYPERLINK("https://robu.in/?s="&SUBSTITUTE($D13," ","+")&"&post_type=product","Robu search") -> Robu search | U13: https://www.alibaba.com/trade/search?SearchText=Zynq+UltraScale%2B+Dev+Kit+ZU3EG%2FZU5EV | W13: =HYPERLINK("https://www.lcsc.com/search?q="&SUBSTITUTE($D13," ","+"),"LCSC search") -> LCSC search | Y13: =HYPERLINK("https://www.mouser.in/c/?q="&SUBSTITUTE($D13," ","+"),"Mouser search") -> Mouser search | AA13: =HYPERLINK("https://www.digikey.in/en/products/filter?keywords="&SUBSTITUTE($D13," ","+"),"DigiKey search") -> DigiKey search | AC13: =Inputs_Assumptions!$B$7 -> 150 | AD13: =Inputs_Assumptions!$B$7 -> 150 | AE13: =Inputs_Assumptions!$B$5 -> 0.1 | AF13: =Inputs_Assumptions!$B$6 -> 0.18 | AG13: =Inputs_Assumptions!$B$4 -> 83 | AJ13: =IF(AH13<>"",(AH13*AG13+AD13)*(1+AE13)*(1+AF13),(M13+AD13)*(1+AF13)) -> 76877 | AK13: =Inputs_Assumptions!$B$9 -> 0.35 | AL13: =IF(AJ13<>"",AJ13/(1-AK13),"") -> 118272.31 | AM13: =Inputs_Assumptions!$B$8 -> 0.18 | AN13: =IF(AND(P13<>"",AJ13<>"",AM13<>""),(P13-AJ13-P13*AM13)/P13,"") | AO13: C | AW13: 2025-12-20 | AX13: 2025-12-21 | BH13: 2025-12-21 | BV13: Risky at planned sell (needs bundle or cheaper sourcing). Gross≈12%. Est Amazon net≈-6% after ~18% fees. | BW13: Direct (B2B) + IndiaMART RFQs; avoid Amazon unless bundled/priced higher; also local resellers. | BX13: Bundle: correct power adapter + USB cable + JTAG cable option + PMOD starter pack + demo bitstream + quick‑start + onboarding call. | BY13: Title: Zynq UltraScale+ Dev Kit | Verified/QA Tested | Quick‑Start + Support | GST Invoice Bullets: - Key specs: ARM A53 + FPGA fabric - Use case: High-end edge compute - Pre‑tested unit with packaging QC sticker + photo proof before dispatch. - Support: setup guide (QR) + WhatsApp troubleshooting; replacement DOA policy. - Ideal for startups/labs/training centers; bulk pricing available. | BZ13: fpga development board, zynq board, artix board, cyclone board, vivado board, quartus board, fpga starter kit, pmod | CA13: Day1–2 sample+QC | Day3 assets+pack insert QR | Day4 IndiaMART+WhatsApp catalog | Week1 Amazon (kit) | Week1–2 LinkedIn/B2B outreach | Week2 small ads + optimize | Bi‑weekly price recheck | CB13: Pending (missing seller profile) | CC13: Reseller (needs confirmation) | CE13: Unknown | CH13: N | CI13: N | CJ13: 7 | CK13: 7 days DOA replacement; unopened returns as per channel policy. | CL13: Domestic shipment (GST invoice preferred) | CM13: 3 months (board functional; no over-voltage/ESD damage). | CN13: 7–14 days (confirm with supplier) | CO13: N | CR13: 2026-01-06 | CS13: Risky at planned sell (needs bundle or cheaper sourcing). Gross≈12%. Est Amazon net≈-6% after ~18% fees. | Channels: Direct (B2B) + IndiaMART RFQs; avoid Amazon unless bundled/priced higher; also local resellers. | Bundle: Bundle: correct power adapter + USB cable + JTAG cable option + PMOD starter pack + demo bitstream + quick‑start + onboarding call. | CT13: Low | CU13: 20 | CV13: Demand 0.0/40 (units=0.0); Margin 0.0/30 (GM%=-160137964794062464.0); Channel 0.0/10 (AmazonNet%=NA); Sourcing 0.0/10 (mode=Import); Lead 10.0/10 (days=7.0); Fit 10.0/10; Penalty 0.0/10.
A14: SOM-ULTRA96V2 | B14: SOM Module | C14: SOM | D14: Ultra96-V2 SOM | E14: Avnet | F14: Ultra96-V2 | G14: Zynq MPSoC | H14: Zynq UltraScale+ MPSoC, WiFi/BT | I14: Embedded AI prototyping | J14: Startups, Labs | K14: Import | L14: Import | M14: 22000 | N14: 28500 | O14: =IF(AND(M14<>"",N14<>""),(N14-M14)/N14,"") -> 0.22807018 | Q14: https://www.amazon.in/s?k=Ultra96-V2+SOM+Ultra96-V2 | S14: =HYPERLINK("https://robu.in/?s="&SUBSTITUTE($D14," ","+")&"&post_type=product","Robu search") -> Robu search | U14: https://www.alibaba.com/trade/search?SearchText=Ultra96-V2+SOM+Ultra96-V2 | W14: =HYPERLINK("https://www.lcsc.com/search?q="&SUBSTITUTE($D14," ","+"),"LCSC search") -> LCSC search | Y14: =HYPERLINK("https://www.mouser.in/c/?q="&SUBSTITUTE($D14," ","+"),"Mouser search") -> Mouser search | AA14: =HYPERLINK("https://www.digikey.in/en/products/filter?keywords="&SUBSTITUTE($D14," ","+"),"DigiKey search") -> DigiKey search | AC14: =Inputs_Assumptions!$B$7 -> 150 | AD14: =Inputs_Assumptions!$B$7 -> 150 | AE14: =Inputs_Assumptions!$B$5 -> 0.1 | AF14: =Inputs_Assumptions!$B$6 -> 0.18 | AG14: =Inputs_Assumptions!$B$4 -> 83 | AJ14: =IF(AH14<>"",(AH14*AG14+AD14)*(1+AE14)*(1+AF14),(M14+AD14)*(1+AF14)) -> 26137 | AK14: =Inputs_Assumptions!$B$9 -> 0.35 | AL14: =IF(AJ14<>"",AJ14/(1-AK14),"") -> 40210.769 | AM14: =Inputs_Assumptions!$B$8 -> 0.18 | AN14: =IF(AND(P14<>"",AJ14<>"",AM14<>""),(P14-AJ14-P14*AM14)/P14,"") | AO14: C | AW14: 2025-12-20 | AX14: 2025-12-21 | BH14: 2025-12-21 | BV14: Risky at planned sell (needs bundle or cheaper sourcing). Gross≈14%. Est Amazon net≈-4% after ~18% fees. | BW14: Direct (B2B) + IndiaMART RFQs; avoid Amazon unless bundled/priced higher; also local resellers. | BX14: Add: essentials kit (cables/adapters) + quick‑start card + basic support + 7‑day DOA replacement. | BY14: Title: Ultra96-V2 SOM | Verified/QA Tested | Quick‑Start + Support | GST Invoice Bullets: - Key specs: Zynq UltraScale+ MPSoC, WiFi/BT - Use case: Embedded AI prototyping - Pre‑tested unit with packaging QC sticker + photo proof before dispatch. - Support: setup guide (QR) + WhatsApp troubleshooting; replacement DOA policy. - Ideal for startups/labs/training centers; bulk pricing available. | BZ14: electronics module, dev kit, maker kit, embedded components | CA14: Day1–2 sample+QC | Day3 assets+pack insert QR | Day4 IndiaMART+WhatsApp catalog | Week1 Amazon (kit) | Week1–2 LinkedIn/B2B outreach | Week2 small ads + optimize | Bi‑weekly price recheck | CB14: Pending (missing seller profile) | CC14: Reseller (needs confirmation) | CE14: Unknown | CH14: N | CI14: N | CJ14: 7 | CK14: Marketplace return policy; 7 days DOA replacement. | CL14: Domestic shipment (GST invoice preferred) | CM14: 30 days replacement for DOA. | CN14: 7–14 days (confirm with supplier) | CO14: N | CR14: 2026-01-06 | CS14: Risky at planned sell (needs bundle or cheaper sourcing). Gross≈14%. Est Amazon net≈-4% after ~18% fees. | Channels: Direct (B2B) + IndiaMART RFQs; avoid Amazon unless bundled/priced higher; also local resellers. | Bundle: Add: essentials kit (cables/adapters) + quick‑start card + basic support + 7‑day DOA replacement. | CT14: Low | CU14: 11 | CV14: Demand 0.0/40 (units=0.0); Margin 0.0/30 (GM%=-496189968916285568.0); Channel 0.0/10 (AmazonNet%=NA); Sourcing 0.0/10 (mode=Import); Lead 10.0/10 (days=7.0); Fit 6.0/10; Penalty 5.0/10.
A15: SOM-KRIA-KV260 | B15: SOM Module | C15: SOM | D15: Kria KV260 Vision AI Starter Kit | E15: AMD/Xilinx | F15: KV260 | G15: Vision AI kit | H15: Kria SOM + carrier, vision ready | I15: Vision AI prototypes | J15: Startups | K15: Import | L15: Import | M15: 28000 | N15: 36000 | O15: =IF(AND(M15<>"",N15<>""),(N15-M15)/N15,"") -> 0.22222222 | Q15: https://www.amazon.in/s?k=Kria+KV260+Vision+AI+Starter+Kit+KV260 | S15: =HYPERLINK("https://robu.in/?s="&SUBSTITUTE($D15," ","+")&"&post_type=product","Robu search") -> Robu search | T15: 338.27 | U15: https://www.alibaba.com/product-detail/Original-Development-Board-Modules-KRIA-KV260_1600861591580.html | W15: =HYPERLINK("https://www.lcsc.com/search?q="&SUBSTITUTE($D15," ","+"),"LCSC search") -> LCSC search | Y15: =HYPERLINK("https://www.mouser.in/c/?q="&SUBSTITUTE($D15," ","+"),"Mouser search") -> Mouser search | AA15: =HYPERLINK("https://www.digikey.in/en/products/filter?keywords="&SUBSTITUTE($D15," ","+"),"DigiKey search") -> DigiKey search | AC15: =Inputs_Assumptions!$B$7 -> 150 | AD15: =Inputs_Assumptions!$B$7 -> 150 | AE15: =Inputs_Assumptions!$B$5 -> 0.1 | AF15: =Inputs_Assumptions!$B$6 -> 0.18 | AG15: =Inputs_Assumptions!$B$4 -> 83 | AJ15: =IF(AH15<>"",(AH15*AG15+AD15)*(1+AE15)*(1+AF15),(M15+AD15)*(1+AF15)) -> 33217 | AK15: =Inputs_Assumptions!$B$9 -> 0.35 | AL15: =IF(AJ15<>"",AJ15/(1-AK15),"") -> 51103.077 | AM15: =Inputs_Assumptions!$B$8 -> 0.18 | AN15: =IF(AND(P15<>"",AJ15<>"",AM15<>""),(P15-AJ15-P15*AM15)/P15,"") | AO15: C | AW15: 2025-12-20 | AX15: 2025-12-21 | BH15: 2025-12-21 | BV15: Risky at planned sell (needs bundle or cheaper sourcing). Gross≈13%. Est Amazon net≈-5% after ~18% fees. | BW15: Direct (B2B) + IndiaMART RFQs; avoid Amazon unless bundled/priced higher; also local resellers. | BX15: Add: essentials kit (cables/adapters) + quick‑start card + basic support + 7‑day DOA replacement. | BY15: Title: Kria KV260 Vision AI Starter Kit | Verified/QA Tested | Quick‑Start + Support | GST Invoice Bullets: - Key specs: Kria SOM + carrier, vision ready - Use case: Vision AI prototypes - Pre‑tested unit with packaging QC sticker + photo proof before dispatch. - Support: setup guide (QR) + WhatsApp troubleshooting; replacement DOA policy. - Ideal for startups/labs/training centers; bulk pricing available. | BZ15: electronics module, dev kit, maker kit, embedded components | CA15: Day1–2 sample+QC | Day3 assets+pack insert QR | Day4 IndiaMART+WhatsApp catalog | Week1 Amazon (kit) | Week1–2 LinkedIn/B2B outreach | Week2 small ads + optimize | Bi‑weekly price recheck | CB15: Pending (missing seller profile) | CC15: Reseller (needs confirmation) | CE15: Unknown | CH15: N | CI15: N | CJ15: 7 | CK15: Marketplace return policy; 7 days DOA replacement. | CL15: Domestic shipment (GST invoice preferred) | CM15: 30 days replacement for DOA. | CN15: 7–14 days (confirm with supplier) | CO15: N | CR15: 2026-01-06 | CS15: Risky at planned sell (needs bundle or cheaper sourcing). Gross≈13%. Est Amazon net≈-5% after ~18% fees. | Channels: Direct (B2B) + IndiaMART RFQs; avoid Amazon unless bundled/priced higher; also local resellers. | Bundle: Add: essentials kit (cables/adapters) + quick‑start card + basic support + 7‑day DOA replacement. | CT15: Low | CU15: 15 | CV15: Demand 0.0/40 (units=0.0); Margin 0.0/30 (GM%=-420875419864309632.0); Channel 0.0/10 (AmazonNet%=NA); Sourcing 0.0/10 (mode=Import); Lead 10.0/10 (days=7.0); Fit 10.0/10; Penalty 5.0/10.
A16: SOM-ZYBO-Z7 | B16: SOM Module | C16: Board | D16: Zybo Z7-20 | E16: Digilent | F16: Zybo Z7-20 | G16: Zynq-7020 | H16: Zynq 7020 board | I16: Embedded FPGA learning | J16: Students, Labs | K16: Import | L16: Import | M16: 19000 | N16: 24500 | O16: =IF(AND(M16<>"",N16<>""),(N16-M16)/N16,"") -> 0.2244898 | P16: 50750.1 | Q16: https://www.amazon.in/Digilent-Zybo-Z7-Zynq-7000-Development/dp/B0797G4485 | S16: =HYPERLINK("https://robu.in/?s="&SUBSTITUTE($D16," ","+")&"&post_type=product","Robu search") -> Robu search | U16: https://www.alibaba.com/trade/search?SearchText=Zybo+Z7-20+Zybo+Z7-20 | W16: =HYPERLINK("https://www.lcsc.com/search?q="&SUBSTITUTE($D16," ","+"),"LCSC search") -> LCSC search | Y16: =HYPERLINK("https://www.mouser.in/c/?q="&SUBSTITUTE($D16," ","+"),"Mouser search") -> Mouser search | AA16: =HYPERLINK("https://www.digikey.in/en/products/filter?keywords="&SUBSTITUTE($D16," ","+"),"DigiKey search") -> DigiKey search | AC16: =Inputs_Assumptions!$B$7 -> 150 | AD16: =Inputs_Assumptions!$B$7 -> 150 | AE16: =Inputs_Assumptions!$B$5 -> 0.1 | AF16: =Inputs_Assumptions!$B$6 -> 0.18 | AG16: =Inputs_Assumptions!$B$4 -> 83 | AJ16: =IF(AH16<>"",(AH16*AG16+AD16)*(1+AE16)*(1+AF16),(M16+AD16)*(1+AF16)) -> 22597 | AK16: =Inputs_Assumptions!$B$9 -> 0.35 | AL16: =IF(AJ16<>"",AJ16/(1-AK16),"") -> 34764.615 | AM16: =Inputs_Assumptions!$B$8 -> 0.18 | AN16: =IF(AND(P16<>"",AJ16<>"",AM16<>""),(P16-AJ16-P16*AM16)/P16,"") -> 0.37473979 | AO16: C | AW16: 2025-12-20 | AX16: 2025-12-21 | BH16: 2025-12-21 | BV16: Risky at planned sell (needs bundle or cheaper sourcing). Gross≈14%. Est Amazon net≈-4% after ~18% fees. | BW16: Direct (B2B) + IndiaMART RFQs; avoid Amazon unless bundled/priced higher; also local resellers. | BX16: Add: essentials kit (cables/adapters) + quick‑start card + basic support + 7‑day DOA replacement. | BY16: Title: Zybo Z7-20 | Verified/QA Tested | Quick‑Start + Support | GST Invoice Bullets: - Key specs: Zynq 7020 board - Use case: Embedded FPGA learning - Pre‑tested unit with packaging QC sticker + photo proof before dispatch. - Support: setup guide (QR) + WhatsApp troubleshooting; replacement DOA policy. - Ideal for startups/labs/training centers; bulk pricing available. | BZ16: electronics module, dev kit, maker kit, embedded components | CA16: Day1–2 sample+QC | Day3 assets+pack insert QR | Day4 IndiaMART+WhatsApp catalog | Week1 Amazon (kit) | Week1–2 LinkedIn/B2B outreach | Week2 small ads + optimize | Bi‑weekly price recheck | CB16: Pending (missing seller profile) | CC16: Reseller (needs confirmation) | CE16: Unknown | CH16: N | CI16: N | CJ16: 7 | CK16: Marketplace return policy; 7 days DOA replacement. | CL16: Domestic shipment (GST invoice preferred) | CM16: 30 days replacement for DOA. | CN16: 7–14 days (confirm with supplier) | CO16: N | CR16: 2026-01-06 | CS16: Risky at planned sell (needs bundle or cheaper sourcing). Gross≈14%. Est Amazon net≈-4% after ~18% fees. | Channels: Direct (B2B) + IndiaMART RFQs; avoid Amazon unless bundled/priced higher; also local resellers. | Bundle: Add: essentials kit (cables/adapters) + quick‑start card + basic support + 7‑day DOA replacement. | CT16: Low | CU16: 11 | CV16: Demand 0.0/40 (units=0.0); Margin 0.0/30 (GM%=-659657800657802240.0); Channel 0.0/10 (AmazonNet%=NA); Sourcing 0.0/10 (mode=Import); Lead 10.0/10 (days=7.0); Fit 6.0/10; Penalty 5.0/10.
A17: SOM-ARTY-A7 | B17: SOM Module | C17: Board | D17: Arty A7-35T | E17: Digilent | F17: Arty A7-35T | G17: Artix-7 | H17: Artix-7 + DDR3 | I17: FPGA education + prototypes | J17: Students, Labs | K17: Import | L17: Import | M17: 17500 | N17: 22500 | O17: =IF(AND(M17<>"",N17<>""),(N17-M17)/N17,"") -> 0.22222222 | P17: 3371 | Q17: https://www.amazon.in/Arty-A7-Artix-7-Development-Hobbyists/dp/B07D1DVRG6 | S17: =HYPERLINK("https://robu.in/?s="&SUBSTITUTE($D17," ","+")&"&post_type=product","Robu search") -> Robu search | T17: 282.8 | U17: https://www.alibaba.com/showroom/xilinx-fpga-kit.html | W17: =HYPERLINK("https://www.lcsc.com/search?q="&SUBSTITUTE($D17," ","+"),"LCSC search") -> LCSC search | Y17: =HYPERLINK("https://www.mouser.in/c/?q="&SUBSTITUTE($D17," ","+"),"Mouser search") -> Mouser search | AA17: =HYPERLINK("https://www.digikey.in/en/products/filter?keywords="&SUBSTITUTE($D17," ","+"),"DigiKey search") -> DigiKey search | AC17: =Inputs_Assumptions!$B$7 -> 150 | AD17: =Inputs_Assumptions!$B$7 -> 150 | AE17: =Inputs_Assumptions!$B$5 -> 0.1 | AF17: =Inputs_Assumptions!$B$6 -> 0.18 | AG17: =Inputs_Assumptions!$B$4 -> 83 | AJ17: =IF(AH17<>"",(AH17*AG17+AD17)*(1+AE17)*(1+AF17),(M17+AD17)*(1+AF17)) -> 20827 | AK17: =Inputs_Assumptions!$B$9 -> 0.35 | AL17: =IF(AJ17<>"",AJ17/(1-AK17),"") -> 32041.538 | AM17: =Inputs_Assumptions!$B$8 -> 0.18 | AN17: =IF(AND(P17<>"",AJ17<>"",AM17<>""),(P17-AJ17-P17*AM17)/P17,"") -> -5.3582854 | AO17: C | AW17: 2025-12-20 | AX17: 2025-12-21 | BH17: 2025-12-21 | BV17: Risky at planned sell (needs bundle or cheaper sourcing). Gross≈13%. Est Amazon net≈-5% after ~18% fees. | BW17: Direct (B2B) + IndiaMART RFQs; avoid Amazon unless bundled/priced higher; also local resellers. | BX17: Add: essentials kit (cables/adapters) + quick‑start card + basic support + 7‑day DOA replacement. | BY17: Title: Arty A7-35T | Verified/QA Tested | Quick‑Start + Support | GST Invoice Bullets: - Key specs: Artix-7 + DDR3 - Use case: FPGA education + prototypes - Pre‑tested unit with packaging QC sticker + photo proof before dispatch. - Support: setup guide (QR) + WhatsApp troubleshooting; replacement DOA policy. - Ideal for startups/labs/training centers; bulk pricing available. | BZ17: electronics module, dev kit, maker kit, embedded components | CA17: Day1–2 sample+QC | Day3 assets+pack insert QR | Day4 IndiaMART+WhatsApp catalog | Week1 Amazon (kit) | Week1–2 LinkedIn/B2B outreach | Week2 small ads + optimize | Bi‑weekly price recheck | CB17: Pending (missing seller profile) | CC17: Reseller (needs confirmation) | CE17: Unknown | CH17: N | CI17: N | CJ17: 7 | CK17: Marketplace return policy; 7 days DOA replacement. | CL17: Domestic shipment (GST invoice preferred) | CM17: 30 days replacement for DOA. | CN17: 7–14 days (confirm with supplier) | CO17: N | CR17: 2026-01-06 | CS17: Risky at planned sell (needs bundle or cheaper sourcing). Gross≈13%. Est Amazon net≈-5% after ~18% fees. | Channels: Direct (B2B) + IndiaMART RFQs; avoid Amazon unless bundled/priced higher; also local resellers. | Bundle: Add: essentials kit (cables/adapters) + quick‑start card + basic support + 7‑day DOA replacement. | CT17: Low | CU17: 11 | CV17: Demand 0.0/40 (units=0.0); Margin 0.0/30 (GM%=-763187427427429760.0); Channel 0.0/10 (AmazonNet%=NA); Sourcing 0.0/10 (mode=Import); Lead 10.0/10 (days=7.0); Fit 6.0/10; Penalty 5.0/10.
A18: SOM-ZTURN | B18: SOM Module | C18: Board | D18: Z-turn Board | E18: MYIR | F18: Z-turn | G18: Zynq-7010/7020 | H18: Zynq board low cost | I18: Embedded accel | J18: Startups | K18: Import | L18: Import | M18: 14500 | N18: 18500 | O18: =IF(AND(M18<>"",N18<>""),(N18-M18)/N18,"") -> 0.21621622 | Q18: https://www.amazon.in/s?k=Z-turn+Board+Z-turn | S18: =HYPERLINK("https://robu.in/?s="&SUBSTITUTE($D18," ","+")&"&post_type=product","Robu search") -> Robu search | U18: https://www.alibaba.com/trade/search?SearchText=Z-turn+Board+Z-turn | W18: =HYPERLINK("https://www.lcsc.com/search?q="&SUBSTITUTE($D18," ","+"),"LCSC search") -> LCSC search | Y18: =HYPERLINK("https://www.mouser.in/c/?q="&SUBSTITUTE($D18," ","+"),"Mouser search") -> Mouser search | AA18: =HYPERLINK("https://www.digikey.in/en/products/filter?keywords="&SUBSTITUTE($D18," ","+"),"DigiKey search") -> DigiKey search | AC18: =Inputs_Assumptions!$B$7 -> 150 | AD18: =Inputs_Assumptions!$B$7 -> 150 | AE18: =Inputs_Assumptions!$B$5 -> 0.1 | AF18: =Inputs_Assumptions!$B$6 -> 0.18 | AG18: =Inputs_Assumptions!$B$4 -> 83 | AJ18: =IF(AH18<>"",(AH18*AG18+AD18)*(1+AE18)*(1+AF18),(M18+AD18)*(1+AF18)) -> 17287 | AK18: =Inputs_Assumptions!$B$9 -> 0.35 | AL18: =IF(AJ18<>"",AJ18/(1-AK18),"") -> 26595.385 | AM18: =Inputs_Assumptions!$B$8 -> 0.18 | AN18: =IF(AND(P18<>"",AJ18<>"",AM18<>""),(P18-AJ18-P18*AM18)/P18,"") | AO18: C | AW18: 2025-12-20 | AX18: 2025-12-21 | BH18: 2025-12-21 | BV18: Risky at planned sell (needs bundle or cheaper sourcing). Gross≈13%. Est Amazon net≈-5% after ~18% fees. | BW18: Direct (B2B) + IndiaMART RFQs; avoid Amazon unless bundled/priced higher; also local resellers. | BX18: Add: essentials kit (cables/adapters) + quick‑start card + basic support + 7‑day DOA replacement. | BY18: Title: Z-turn Board | Verified/QA Tested | Quick‑Start + Support | GST Invoice Bullets: - Key specs: Zynq board low cost - Use case: Embedded accel - Pre‑tested unit with packaging QC sticker + photo proof before dispatch. - Support: setup guide (QR) + WhatsApp troubleshooting; replacement DOA policy. - Ideal for startups/labs/training centers; bulk pricing available. | BZ18: electronics module, dev kit, maker kit, embedded components | CA18: Day1–2 sample+QC | Day3 assets+pack insert QR | Day4 IndiaMART+WhatsApp catalog | Week1 Amazon (kit) | Week1–2 LinkedIn/B2B outreach | Week2 small ads + optimize | Bi‑weekly price recheck | CB18: Pending (missing seller profile) | CC18: Reseller (needs confirmation) | CE18: Unknown | CH18: N | CI18: N | CJ18: 7 | CK18: Marketplace return policy; 7 days DOA replacement. | CL18: Domestic shipment (GST invoice preferred) | CM18: 30 days replacement for DOA. | CN18: 7–14 days (confirm with supplier) | CO18: N | CR18: 2026-01-06 | CS18: Risky at planned sell (needs bundle or cheaper sourcing). Gross≈13%. Est Amazon net≈-5% after ~18% fees. | Channels: Direct (B2B) + IndiaMART RFQs; avoid Amazon unless bundled/priced higher; also local resellers. | Bundle: Add: essentials kit (cables/adapters) + quick‑start card + basic support + 7‑day DOA replacement. | CT18: Low | CU18: 11 | CV18: Demand 0.0/40 (units=0.0); Margin 0.0/30 (GM%=-982800979357739392.0); Channel 0.0/10 (AmazonNet%=NA); Sourcing 0.0/10 (mode=Import); Lead 10.0/10 (days=7.0); Fit 6.0/10; Penalty 5.0/10.
A19: SOM-TRENZ-TE | B19: SOM Module | C19: SOM | D19: Trenz TE Series (Zynq SOM) | E19: Trenz | F19: TE0720/TE0715 | G19: Zynq SOM | H19: SOM for carrier integration | I19: Productization | J19: Startups | K19: Import | L19: Import | M19: 16000 | N19: 21000 | O19: =IF(AND(M19<>"",N19<>""),(N19-M19)/N19,"") -> 0.23809524 | Q19: https://www.amazon.in/s?k=Trenz+TE+Series+%28Zynq+SOM%29+TE0720%2FTE0715 | S19: =HYPERLINK("https://robu.in/?s="&SUBSTITUTE($D19," ","+")&"&post_type=product","Robu search") -> Robu search | U19: https://www.alibaba.com/trade/search?SearchText=Trenz+TE+Series+%28Zynq+SOM%29+TE0720%2FTE0715 | W19: =HYPERLINK("https://www.lcsc.com/search?q="&SUBSTITUTE($D19," ","+"),"LCSC search") -> LCSC search | Y19: =HYPERLINK("https://www.mouser.in/c/?q="&SUBSTITUTE($D19," ","+"),"Mouser search") -> Mouser search | AA19: =HYPERLINK("https://www.digikey.in/en/products/filter?keywords="&SUBSTITUTE($D19," ","+"),"DigiKey search") -> DigiKey search | AC19: =Inputs_Assumptions!$B$7 -> 150 | AD19: =Inputs_Assumptions!$B$7 -> 150 | AE19: =Inputs_Assumptions!$B$5 -> 0.1 | AF19: =Inputs_Assumptions!$B$6 -> 0.18 | AG19: =Inputs_Assumptions!$B$4 -> 83 | AJ19: =IF(AH19<>"",(AH19*AG19+AD19)*(1+AE19)*(1+AF19),(M19+AD19)*(1+AF19)) -> 19057 | AK19: =Inputs_Assumptions!$B$9 -> 0.35 | AL19: =IF(AJ19<>"",AJ19/(1-AK19),"") -> 29318.462 | AM19: =Inputs_Assumptions!$B$8 -> 0.18 | AN19: =IF(AND(P19<>"",AJ19<>"",AM19<>""),(P19-AJ19-P19*AM19)/P19,"") | AO19: C | AW19: 2025-12-20 | AX19: 2025-12-21 | BH19: 2025-12-21 | BV19: Works for Direct/B2B; marketplaces need bundle/price-up. Gross≈15%. Est Amazon net≈-3% after ~18% fees. | BW19: Direct (B2B) + IndiaMART; Amazon only if bundled/priced higher. | BX19: Bundle: correct power adapter + USB cable + JTAG cable option + PMOD starter pack + demo bitstream + quick‑start + onboarding call. | BY19: Title: Trenz TE Series (Zynq SOM) | Verified/QA Tested | Quick‑Start + Support | GST Invoice Bullets: - Key specs: SOM for carrier integration - Use case: Productization - Pre‑tested unit with packaging QC sticker + photo proof before dispatch. - Support: setup guide (QR) + WhatsApp troubleshooting; replacement DOA policy. - Ideal for startups/labs/training centers; bulk pricing available. | BZ19: fpga development board, zynq board, artix board, cyclone board, vivado board, quartus board, fpga starter kit, pmod | CA19: Day1–2 sample+QC | Day3 assets+pack insert QR | Day4 IndiaMART+WhatsApp catalog | Week1 Amazon (kit) | Week1–2 LinkedIn/B2B outreach | Week2 small ads + optimize | Bi‑weekly price recheck | CB19: Pending (missing seller profile) | CC19: Reseller (needs confirmation) | CE19: Unknown | CH19: N | CI19: N | CJ19: 7 | CK19: 7 days DOA replacement; unopened returns as per channel policy. | CL19: Domestic shipment (GST invoice preferred) | CM19: 3 months (board functional; no over-voltage/ESD damage). | CN19: 7–14 days (confirm with supplier) | CO19: N | CR19: 2026-01-06 | CS19: Works for Direct/B2B; marketplaces need bundle/price-up. Gross≈15%. Est Amazon net≈-3% after ~18% fees. | Channels: Direct (B2B) + IndiaMART; Amazon only if bundled/priced higher. | Bundle: Bundle: correct power adapter + USB cable + JTAG cable option + PMOD starter pack + demo bitstream + quick‑start + onboarding call. | CT19: Low | CU19: 20 | CV19: Demand 0.0/40 (units=0.0); Margin 0.0/30 (GM%=-913900910434247040.0); Channel 5.0/10 (AmazonNet%=NA); Sourcing 0.0/10 (mode=Import); Lead 10.0/10 (days=7.0); Fit 10.0/10; Penalty 5.0/10.
A20: SOM-COLORLIGHT-ECP5 | B20: SOM Module | C20: Board | D20: Colorlight i5 ECP5 Board | E20: Colorlight | F20: i5 | G20: ECP5-45F/85F | H20: Low-cost ECP5 platform | I20: Open-source FPGA dev | J20: Makers, Startups | K20: Import | L20: Import | M20: 6500 | N20: 9500 | O20: =IF(AND(M20<>"",N20<>""),(N20-M20)/N20,"") -> 0.31578947 | P20: 10156.4 | Q20: https://www.amazon.in/Lattice-ECP5-FPGA-RISC-V-Development/dp/B0BKF9NDGZ | S20: =HYPERLINK("https://robu.in/?s="&SUBSTITUTE($D20," ","+")&"&post_type=product","Robu search") -> Robu search | T20: 21.28 | U20: https://m.alibaba.com/showroom/ecp5-fpga.html | W20: =HYPERLINK("https://www.lcsc.com/search?q="&SUBSTITUTE($D20," ","+"),"LCSC search") -> LCSC search | Y20: =HYPERLINK("https://www.mouser.in/c/?q="&SUBSTITUTE($D20," ","+"),"Mouser search") -> Mouser search | AA20: =HYPERLINK("https://www.digikey.in/en/products/filter?keywords="&SUBSTITUTE($D20," ","+"),"DigiKey search") -> DigiKey search | AC20: =Inputs_Assumptions!$B$7 -> 150 | AD20: =Inputs_Assumptions!$B$7 -> 150 | AE20: =Inputs_Assumptions!$B$5 -> 0.1 | AF20: =Inputs_Assumptions!$B$6 -> 0.18 | AG20: =Inputs_Assumptions!$B$4 -> 83 | AJ20: =IF(AH20<>"",(AH20*AG20+AD20)*(1+AE20)*(1+AF20),(M20+AD20)*(1+AF20)) -> 7847 | AK20: =Inputs_Assumptions!$B$9 -> 0.35 | AL20: =IF(AJ20<>"",AJ20/(1-AK20),"") -> 12072.308 | AM20: =Inputs_Assumptions!$B$8 -> 0.18 | AN20: =IF(AND(P20<>"",AJ20<>"",AM20<>""),(P20-AJ20-P20*AM20)/P20,"") -> 0.047383719 | AO20: C | AR20: 6 | AW20: 2025-12-20 | AX20: 2025-12-21 | BH20: 2025-12-21 | BV20: Works for Direct/B2B; marketplaces need bundle/price-up. Gross≈24%. Est Amazon net≈6% after ~18% fees. | BW20: Amazon (as verified kit) + Direct (B2B) + IndiaMART; also Website/WhatsApp + LinkedIn outreach. | BX20: Add: essentials kit (cables/adapters) + quick‑start card + basic support + 7‑day DOA replacement. | BY20: Title: Colorlight i5 ECP5 Board | Verified/QA Tested | Quick‑Start + Support | GST Invoice Bullets: - Key specs: Low-cost ECP5 platform - Use case: Open-source FPGA dev - Pre‑tested unit with packaging QC sticker + photo proof before dispatch. - Support: setup guide (QR) + WhatsApp troubleshooting; replacement DOA policy. - Ideal for startups/labs/training centers; bulk pricing available. | BZ20: electronics module, dev kit, maker kit, embedded components | CA20: Day1–2 sample+QC | Day3 assets+pack insert QR | Day4 IndiaMART+WhatsApp catalog | Week1 Amazon (kit) | Week1–2 LinkedIn/B2B outreach | Week2 small ads + optimize | Bi‑weekly price recheck | CB20: Pending (missing seller profile) | CC20: Reseller (needs confirmation) | CE20: Unknown | CH20: N | CI20: N | CJ20: 7 | CK20: Marketplace return policy; 7 days DOA replacement. | CL20: Domestic shipment (GST invoice preferred) | CM20: 30 days replacement for DOA. | CN20: 7–14 days (confirm with supplier) | CO20: N | CR20: 2026-01-06 | CS20: Works for Direct/B2B; marketplaces need bundle/price-up. Gross≈24%. Est Amazon net≈6% after ~18% fees. | Channels: Amazon (as verified kit) + Direct (B2B) + IndiaMART; also Website/WhatsApp + LinkedIn outreach. | Bundle: Add: essentials kit (cables/adapters) + quick‑start card + basic support + 7‑day DOA replacement. | CT20: Low | CU20: 16 | CV20: Demand 0.0/40 (units=0.0); Margin 0.0/30 (GM%=-2126528433696863232.0); Channel 5.0/10 (AmazonNet%=NA); Sourcing 0.0/10 (mode=Import); Lead 10.0/10 (days=7.0); Fit 6.0/10; Penalty 5.0/10.
A21: AI-JETSON-NANO | B21: AI Edge Board | C21: Board | D21: NVIDIA Jetson Nano Dev Kit | E21: NVIDIA | F21: Jetson Nano | G21: 4GB kit | H21: 128-core GPU, ARM CPU | I21: Edge inference, vision | J21: AI startups, Students | K21: Both | L21: Local/Import | M21: 21999 | N21: 33850 | O21: 0.3501 | P21: 37499 | Q21: https://www.amazon.in/NVIDIA-Jetson-Nano-Developer-Kit/dp/B0D3MFRG2R | R21: 21999 | S21: https://robu.in/product/okdo-nvidia-jetson-nano-c100-developer-kit/ | T21: 62.76 | U21: https://www.alibaba.com/showroom/jetson-nano.html | W21: =HYPERLINK("https://www.lcsc.com/search?q="&SUBSTITUTE($D21," ","+"),"LCSC search") -> LCSC search | Y21: =HYPERLINK("https://www.mouser.in/c/?q="&SUBSTITUTE($D21," ","+"),"Mouser search") -> Mouser search | AA21: =HYPERLINK("https://www.digikey.in/en/products/filter?keywords="&SUBSTITUTE($D21," ","+"),"DigiKey search") -> DigiKey search | AC21: =Inputs_Assumptions!$B$7 -> 150 | AD21: =Inputs_Assumptions!$B$7 -> 150 | AE21: =Inputs_Assumptions!$B$5 -> 0.1 | AF21: =Inputs_Assumptions!$B$6 -> 0.18 | AG21: =Inputs_Assumptions!$B$4 -> 83 | AJ21: =IF(AH21<>"",(AH21*AG21+AD21)*(1+AE21)*(1+AF21),(M21+AD21)*(1+AF21)) -> 26135.82 | AK21: =Inputs_Assumptions!$B$9 -> 0.35 | AL21: =IF(AJ21<>"",AJ21/(1-AK21),"") -> 40208.954 | AM21: =Inputs_Assumptions!$B$8 -> 0.18 | AN21: =IF(AND(P21<>"",AJ21<>"",AM21<>""),(P21-AJ21-P21*AM21)/P21,"") -> 0.12302621 | AO21: A | AP21: 2 | AQ21: 4 | AR21: 8 | AS21: 1 | AU21: 2025-12-21 | AV21: Robu price for Jetson Nano 2GB kit incl GST (check 4GB vs 2GB). (2025-12-20) | AW21: 2025-12-20 | AX21: 2025-12-21 | BC21: 2025-12-21 | BD21: MACFOS LIMITED (Robu.in) | BE21: https://robu.in/ | BF21: Survey No. 78/1, Sumant Building, Dynamic Logistics Trade Park, Dighi, Bhosari-Alandi Road, Pune, Maharashtra 411015, India | BG21: Phone: 1800 266 6123 / 020 6819 7600 ; Email: info@robu.in | BH21: 2025-12-21 | BM21: 21999 | BN21: Robu.in | BO21: https://robu.in/product/okdo-nvidia-jetson-nano-c100-developer-kit/ | BP21: MACFOS LIMITED (Robu.in) | BQ21: https://robu.in/ | BR21: Survey No. 78/1, Sumant Building, Dynamic Logistics Trade Park, Dighi, Bhosari-Alandi Road, Pune, Maharashtra 411015, India | BS21: Phone: 1800 266 6123 / 020 6819 7600 ; Email: info@robu.in | BT21: 2025-12-21 | BU21: Robu listing is out of stock at time of check. | BV21: Works (healthy margin). Gross≈28%. Est Amazon net≈10% after ~18% fees. | BW21: Amazon (as verified kit) + Direct (B2B) + IndiaMART; also Website/WhatsApp + LinkedIn outreach. | BX21: Bundle: official/verified power supply + high‑end SD/SSD + heatsink/fan (if needed) + camera options + enclosure + quick‑start + remote setup session. | BY21: Title: NVIDIA Jetson Nano Dev Kit | Verified/QA Tested | Quick‑Start + Support | GST Invoice Bullets: - Key specs: 128-core GPU, ARM CPU - Use case: Edge inference, vision - Pre‑tested unit with packaging QC sticker + photo proof before dispatch. - Support: setup guide (QR) + WhatsApp troubleshooting; replacement DOA policy. - Ideal for startups/labs/training centers; bulk pricing available. | BZ21: jetson orin, jetson nano, edge ai dev kit, nvidia jetson, vision ai kit, cuda devkit, ros2 ai, edge inference | CA21: Day1–2 sample+QC | Day3 assets+pack insert QR | Day4 IndiaMART+WhatsApp catalog | Week1 Amazon (kit) | Week1–2 LinkedIn/B2B outreach | Week2 small ads + optimize | Bi‑weekly price recheck | CB21: Partial (needs sample + doc evidence) | CC21: Reseller / Marketplace Seller | CD21: https://robu.in/product/okdo-nvidia-jetson-nano-c100-developer-kit/ | CE21: Marketplace seller (badge depends on platform); prefer GST invoice + established store ratings. | CH21: Y | CI21: N | CJ21: 7 | CK21: 7 days DOA replacement; channel return policy applies. | CL21: Domestic shipment (GST invoice preferred) | CM21: 3 months replacement for functional failure (conditions apply). | CN21: Bangalore: 48–72 hrs replacement (stock permitting); else 7–14 days via supplier. | CO21: Y | CP21: MACFOS LIMITED (Robu.in) | CQ21: Robu.in | https://robu.in/product/okdo-nvidia-jetson-nano-c100-developer-kit/ | CR21: 2026-01-06 | CS21: Works (healthy margin). Gross≈28%. Est Amazon net≈10% after ~18% fees. | Channels: Amazon (as verified kit) + Direct (B2B) + IndiaMART; also Website/WhatsApp + LinkedIn outreach. | Bundle: Bundle: official/verified power supply + high‑end SD/SSD + heatsink/fan (if needed) + camera options + enclosure + quick‑start + remote setup session. | CT21: High | CU21: 33.4 | CV21: Demand 2.0/40 (units=1.0); Margin 0.3/30 (GM%=0.4); Channel 5.0/10 (AmazonNet%=NA); Sourcing 6.2/10 (mode=Both); Lead 10.0/10 (days=7.0); Fit 10.0/10; Penalty 0.0/10.
A22: AI-JETSON-ORIN-NX | B22: AI Edge Board | C22: Board | D22: NVIDIA Jetson Orin NX Kit | E22: NVIDIA | F22: Orin NX | G22: 8/16GB | H22: Modern edge AI module | I22: Edge LLM/vision | J22: AI startups | K22: Import | L22: Import | M22: 49999 | N22: 76930 | O22: 0.3501 | P22: 147499 | Q22: https://www.amazon.in/Jetson-Orin-NX-Super-Developer/dp/B0D3MF7V3Y | R22: 49999 | S22: https://robu.in/product/nvidia-jetson-orin-nx-8gb-module/ | T22: 763.45 | U22: https://www.alibaba.com/showroom/jetson-orin-nx.html | W22: =HYPERLINK("https://www.lcsc.com/search?q="&SUBSTITUTE($D22," ","+"),"LCSC search") -> LCSC search | Y22: =HYPERLINK("https://www.mouser.in/c/?q="&SUBSTITUTE($D22," ","+"),"Mouser search") -> Mouser search | AA22: =HYPERLINK("https://www.digikey.in/en/products/filter?keywords="&SUBSTITUTE($D22," ","+"),"DigiKey search") -> DigiKey search | AC22: =Inputs_Assumptions!$B$7 -> 150 | AD22: =Inputs_Assumptions!$B$7 -> 150 | AE22: =Inputs_Assumptions!$B$5 -> 0.1 | AF22: =Inputs_Assumptions!$B$6 -> 0.18 | AG22: =Inputs_Assumptions!$B$4 -> 83 | AJ22: =IF(AH22<>"",(AH22*AG22+AD22)*(1+AE22)*(1+AF22),(M22+AD22)*(1+AF22)) -> 59175.82 | AK22: =Inputs_Assumptions!$B$9 -> 0.35 | AL22: =IF(AJ22<>"",AJ22/(1-AK22),"") -> 91039.723 | AM22: =Inputs_Assumptions!$B$8 -> 0.18 | AN22: =IF(AND(P22<>"",AJ22<>"",AM22<>""),(P22-AJ22-P22*AM22)/P22,"") -> 0.41880528 | AO22: B | AR22: 3 | AU22: 2025-12-21 | AW22: 2025-12-20 | AX22: 2025-12-21 | BC22: 2025-12-21 | BD22: MACFOS LIMITED (Robu.in) | BE22: https://robu.in/ | BF22: Survey No. 78/1, Sumant Building, Dynamic Logistics Trade Park, Dighi, Bhosari-Alandi Road, Pune, Maharashtra 411015, India | BG22: Phone: 1800 266 6123 / 020 6819 7600 ; Email: info@robu.in | BH22: 2025-12-21 | BM22: 49999 | BN22: Robu.in | BO22: https://robu.in/product/nvidia-jetson-orin-nx-8gb-module/ | BP22: MACFOS LIMITED (Robu.in) | BQ22: https://robu.in/ | BR22: Survey No. 78/1, Sumant Building, Dynamic Logistics Trade Park, Dighi, Bhosari-Alandi Road, Pune, Maharashtra 411015, India | BS22: Phone: 1800 266 6123 / 020 6819 7600 ; Email: info@robu.in | BT22: 2025-12-21 | BU22: Robu listing shows out of stock / restocking. | BV22: Works (healthy margin). Gross≈28%. Est Amazon net≈10% after ~18% fees. | BW22: Amazon (as verified kit) + Direct (B2B) + IndiaMART; also Website/WhatsApp + LinkedIn outreach. | BX22: Bundle: official/verified power supply + high‑end SD/SSD + heatsink/fan (if needed) + camera options + enclosure + quick‑start + remote setup session. | BY22: Title: NVIDIA Jetson Orin NX Kit | Verified/QA Tested | Quick‑Start + Support | GST Invoice Bullets: - Key specs: Modern edge AI module - Use case: Edge LLM/vision - Pre‑tested unit with packaging QC sticker + photo proof before dispatch. - Support: setup guide (QR) + WhatsApp troubleshooting; replacement DOA policy. - Ideal for startups/labs/training centers; bulk pricing available. | BZ22: jetson orin, jetson nano, edge ai dev kit, nvidia jetson, vision ai kit, cuda devkit, ros2 ai, edge inference | CA22: Day1–2 sample+QC | Day3 assets+pack insert QR | Day4 IndiaMART+WhatsApp catalog | Week1 Amazon (kit) | Week1–2 LinkedIn/B2B outreach | Week2 small ads + optimize | Bi‑weekly price recheck | CB22: Partial (needs sample + doc evidence) | CC22: Reseller / Marketplace Seller | CD22: https://robu.in/product/nvidia-jetson-orin-nx-8gb-module/ | CE22: Marketplace seller (badge depends on platform); prefer GST invoice + established store ratings. | CH22: Y | CI22: N | CJ22: 7 | CK22: 7 days DOA replacement; channel return policy applies. | CL22: Domestic shipment (GST invoice preferred) | CM22: 3 months replacement for functional failure (conditions apply). | CN22: Bangalore: 48–72 hrs replacement (stock permitting); else 7–14 days via supplier. | CO22: Y | CP22: MACFOS LIMITED (Robu.in) | CQ22: Robu.in | https://robu.in/product/nvidia-jetson-orin-nx-8gb-module/ | CR22: 2026-01-06 | CS22: Works (healthy margin). Gross≈28%. Est Amazon net≈10% after ~18% fees. | Channels: Amazon (as verified kit) + Direct (B2B) + IndiaMART; also Website/WhatsApp + LinkedIn outreach. | Bundle: Bundle: official/verified power supply + high‑end SD/SSD + heatsink/fan (if needed) + camera options + enclosure + quick‑start + remote setup session. | CT22: Medium | CU22: 25.3 | CV22: Demand 0.0/40 (units=0.0); Margin 0.3/30 (GM%=0.4); Channel 5.0/10 (AmazonNet%=NA); Sourcing 0.0/10 (mode=Import); Lead 10.0/10 (days=7.0); Fit 10.0/10; Penalty 0.0/10.
A23: AI-JETSON-ORIN-AGX | B23: AI Edge Board | C23: Board | D23: NVIDIA Jetson Orin AGX Dev Kit | E23: NVIDIA | F23: Orin AGX | G23: Dev kit | H23: High-end edge compute | I23: Robotics/Industrial AI | J23: AI startups, Industry | K23: Import | L23: Import | M23: 219999 | N23: 338460 | O23: 0.35 | P23: 217533 | Q23: https://www.amazon.in/Nvidia-Jetson-AGX-Orin-Developer/dp/B0D3MF7V3Z | R23: 219999 | S23: https://robu.in/product/nvidia-jetson-agx-orin-64gb-developer-kit/ | T23: 1899 | U23: https://www.alibaba.com/blog/jetson-agx-orin-modules-guide_4915.html | W23: =HYPERLINK("https://www.lcsc.com/search?q="&SUBSTITUTE($D23," ","+"),"LCSC search") -> LCSC search | Y23: =HYPERLINK("https://www.mouser.in/c/?q="&SUBSTITUTE($D23," ","+"),"Mouser search") -> Mouser search | AA23: =HYPERLINK("https://www.digikey.in/en/products/filter?keywords="&SUBSTITUTE($D23," ","+"),"DigiKey search") -> DigiKey search | AC23: =Inputs_Assumptions!$B$7 -> 150 | AD23: =Inputs_Assumptions!$B$7 -> 150 | AE23: =Inputs_Assumptions!$B$5 -> 0.1 | AF23: =Inputs_Assumptions!$B$6 -> 0.18 | AG23: =Inputs_Assumptions!$B$4 -> 83 | AJ23: =IF(AH23<>"",(AH23*AG23+AD23)*(1+AE23)*(1+AF23),(M23+AD23)*(1+AF23)) -> 259775.82 | AK23: =Inputs_Assumptions!$B$9 -> 0.35 | AL23: =IF(AJ23<>"",AJ23/(1-AK23),"") -> 399655.11 | AM23: =Inputs_Assumptions!$B$8 -> 0.18 | AN23: =IF(AND(P23<>"",AJ23<>"",AM23<>""),(P23-AJ23-P23*AM23)/P23,"") -> -0.3741904 | AO23: B | AU23: 2025-12-21 | AW23: 2025-12-20 | AX23: 2025-12-21 | BC23: 2025-12-21 | BD23: MACFOS LIMITED (Robu.in) | BE23: https://robu.in/ | BF23: Survey No. 78/1, Sumant Building, Dynamic Logistics Trade Park, Dighi, Bhosari-Alandi Road, Pune, Maharashtra 411015, India | BG23: Phone: 1800 266 6123 / 020 6819 7600 ; Email: info@robu.in | BH23: 2025-12-21 | BM23: 219999 | BN23: Robu.in | BO23: https://robu.in/product/nvidia-jetson-agx-orin-64gb-developer-kit/ | BP23: MACFOS LIMITED (Robu.in) | BQ23: https://robu.in/ | BR23: Survey No. 78/1, Sumant Building, Dynamic Logistics Trade Park, Dighi, Bhosari-Alandi Road, Pune, Maharashtra 411015, India | BS23: Phone: 1800 266 6123 / 020 6819 7600 ; Email: info@robu.in | BT23: 2025-12-21 | BU23: Price captured from Robu listing (AGX Orin 64GB Dev Kit). Verify exact kit variant (32GB vs 64GB). | BV23: Works (healthy margin). Gross≈28%. Est Amazon net≈10% after ~18% fees. | BW23: Amazon (as verified kit) + Direct (B2B) + IndiaMART; also Website/WhatsApp + LinkedIn outreach. | BX23: Bundle: official/verified power supply + high‑end SD/SSD + heatsink/fan (if needed) + camera options + enclosure + quick‑start + remote setup session. | BY23: Title: NVIDIA Jetson Orin AGX Dev Kit | Verified/QA Tested | Quick‑Start + Support | GST Invoice Bullets: - Key specs: High-end edge compute - Use case: Robotics/Industrial AI - Pre‑tested unit with packaging QC sticker + photo proof before dispatch. - Support: setup guide (QR) + WhatsApp troubleshooting; replacement DOA policy. - Ideal for startups/labs/training centers; bulk pricing available. | BZ23: jetson orin, jetson nano, edge ai dev kit, nvidia jetson, vision ai kit, cuda devkit, ros2 ai, edge inference | CA23: Day1–2 sample+QC | Day3 assets+pack insert QR | Day4 IndiaMART+WhatsApp catalog | Week1 Amazon (kit) | Week1–2 LinkedIn/B2B outreach | Week2 small ads + optimize | Bi‑weekly price recheck | CB23: Partial (needs sample + doc evidence) | CC23: Reseller / Marketplace Seller | CD23: https://robu.in/product/nvidia-jetson-agx-orin-64gb-developer-kit/ | CE23: Marketplace seller (badge depends on platform); prefer GST invoice + established store ratings. | CH23: Y | CI23: N | CJ23: 7 | CK23: 7 days DOA replacement; channel return policy applies. | CL23: Domestic shipment (GST invoice preferred) | CM23: 3 months replacement for functional failure (conditions apply). | CN23: Bangalore: 48–72 hrs replacement (stock permitting); else 7–14 days via supplier. | CO23: Y | CP23: MACFOS LIMITED (Robu.in) | CQ23: Robu.in | https://robu.in/product/nvidia-jetson-agx-orin-64gb-developer-kit/ | CR23: 2026-01-06 | CS23: Works (healthy margin). Gross≈28%. Est Amazon net≈10% after ~18% fees. | Channels: Amazon (as verified kit) + Direct (B2B) + IndiaMART; also Website/WhatsApp + LinkedIn outreach. | Bundle: Bundle: official/verified power supply + high‑end SD/SSD + heatsink/fan (if needed) + camera options + enclosure + quick‑start + remote setup session. | CT23: Medium | CU23: 25.3 | CV23: Demand 0.0/40 (units=0.0); Margin 0.3/30 (GM%=0.3); Channel 5.0/10 (AmazonNet%=NA); Sourcing 0.0/10 (mode=Import); Lead 10.0/10 (days=7.0); Fit 10.0/10; Penalty 0.0/10.
A24: AI-CORAL-DEV | B24: AI Edge Board | C24: Board | D24: Google Coral Dev Board | E24: Google | F24: Coral Dev Board | G24: Edge TPU | H24: Edge TPU accelerator | I24: Low-power inference | J24: Startups, Makers | K24: Import | L24: Import | M24: 14535 | N24: 22370 | O24: 0.3502 | P24: 14990 | Q24: https://www.amazon.in/Google-Coral-Dev-Board/dp/B08DFP4VY8 | R24: 14535 | S24: https://robu.in/product/coral-g650-03324-01-development-board-mini-mt8167s-soc-mcu-arm-cortex-a35-mcu/ | T24: 51.5 | U24: https://www.alibaba.com/showroom/coral-tpu.html | W24: =HYPERLINK("https://www.lcsc.com/search?q="&SUBSTITUTE($D24," ","+"),"LCSC search") -> LCSC search | Y24: =HYPERLINK("https://www.mouser.in/c/?q="&SUBSTITUTE($D24," ","+"),"Mouser search") -> Mouser search | AA24: =HYPERLINK("https://www.digikey.in/en/products/filter?keywords="&SUBSTITUTE($D24," ","+"),"DigiKey search") -> DigiKey search | AC24: =Inputs_Assumptions!$B$7 -> 150 | AD24: =Inputs_Assumptions!$B$7 -> 150 | AE24: =Inputs_Assumptions!$B$5 -> 0.1 | AF24: =Inputs_Assumptions!$B$6 -> 0.18 | AG24: =Inputs_Assumptions!$B$4 -> 83 | AJ24: =IF(AH24<>"",(AH24*AG24+AD24)*(1+AE24)*(1+AF24),(M24+AD24)*(1+AF24)) -> 17328.3 | AK24: =Inputs_Assumptions!$B$9 -> 0.35 | AL24: =IF(AJ24<>"",AJ24/(1-AK24),"") -> 26658.923 | AM24: =Inputs_Assumptions!$B$8 -> 0.18 | AN24: =IF(AND(P24<>"",AJ24<>"",AM24<>""),(P24-AJ24-P24*AM24)/P24,"") -> -0.33599066 | AO24: B | AP24: 1 | AQ24: 2 | AR24: 4 | AS24: 1 | AU24: 2025-12-21 | AW24: 2025-12-20 | AX24: 2025-12-21 | BC24: 2025-12-21 | BD24: MACFOS LIMITED (Robu.in) | BE24: https://robu.in/ | BF24: Survey No. 78/1, Sumant Building, Dynamic Logistics Trade Park, Dighi, Bhosari-Alandi Road, Pune, Maharashtra 411015, India | BG24: Phone: 1800 266 6123 / 020 6819 7600 ; Email: info@robu.in | BH24: 2025-12-21 | BM24: 14535 | BN24: Robu.in | BO24: https://robu.in/product/coral-g650-03324-01-development-board-mini-mt8167s-soc-mcu-arm-cortex-a35-mcu/ | BP24: MACFOS LIMITED (Robu.in) | BQ24: https://robu.in/ | BR24: Survey No. 78/1, Sumant Building, Dynamic Logistics Trade Park, Dighi, Bhosari-Alandi Road, Pune, Maharashtra 411015, India | BS24: Phone: 1800 266 6123 / 020 6819 7600 ; Email: info@robu.in | BT24: 2025-12-21 | BU24: Coral Dev Board Mini used as closest match. | BV24: Works (healthy margin). Gross≈28%. Est Amazon net≈10% after ~18% fees. | BW24: Amazon (as verified kit) + Direct (B2B) + IndiaMART; also Website/WhatsApp + LinkedIn outreach. | BX24: Bundle: official/verified power supply + high‑end SD/SSD + heatsink/fan (if needed) + camera options + enclosure + quick‑start + remote setup session. | BY24: Title: Google Coral Dev Board | Verified/QA Tested | Quick‑Start + Support | GST Invoice Bullets: - Key specs: Edge TPU accelerator - Use case: Low-power inference - Pre‑tested unit with packaging QC sticker + photo proof before dispatch. - Support: setup guide (QR) + WhatsApp troubleshooting; replacement DOA policy. - Ideal for startups/labs/training centers; bulk pricing available. | BZ24: jetson orin, jetson nano, edge ai dev kit, nvidia jetson, vision ai kit, cuda devkit, ros2 ai, edge inference | CA24: Day1–2 sample+QC | Day3 assets+pack insert QR | Day4 IndiaMART+WhatsApp catalog | Week1 Amazon (kit) | Week1–2 LinkedIn/B2B outreach | Week2 small ads + optimize | Bi‑weekly price recheck | CB24: Partial (needs sample + doc evidence) | CC24: Reseller / Marketplace Seller | CD24: https://robu.in/product/coral-g650-03324-01-development-board-mini-mt8167s-soc-mcu-arm-cortex-a35-mcu/ | CE24: Marketplace seller (badge depends on platform); prefer GST invoice + established store ratings. | CH24: Y | CI24: N | CJ24: 7 | CK24: 7 days DOA replacement; unopened returns as per channel policy. | CL24: Domestic shipment (GST invoice preferred) | CM24: 3 months (board functional; no over-voltage/ESD damage). | CN24: Bangalore: 48–72 hrs replacement (stock permitting); else 7–14 days via supplier. | CO24: Y | CP24: MACFOS LIMITED (Robu.in) | CQ24: Robu.in | https://robu.in/product/coral-g650-03324-01-development-board-mini-mt8167s-soc-mcu-arm-cortex-a35-mcu/ | CR24: 2026-01-06 | CS24: Works (healthy margin). Gross≈28%. Est Amazon net≈10% after ~18% fees. | Channels: Amazon (as verified kit) + Direct (B2B) + IndiaMART; also Website/WhatsApp + LinkedIn outreach. | Bundle: Bundle: official/verified power supply + high‑end SD/SSD + heatsink/fan (if needed) + camera options + enclosure + quick‑start + remote setup session. | CT24: Medium | CU24: 27.3 | CV24: Demand 2.0/40 (units=1.0); Margin 0.3/30 (GM%=0.4); Channel 5.0/10 (AmazonNet%=NA); Sourcing 0.0/10 (mode=Import); Lead 10.0/10 (days=7.0); Fit 10.0/10; Penalty 0.0/10.
A25: AI-RK3588 | B25: AI Edge Board | C25: Board | D25: Rockchip RK3588 Dev Board | E25: Rockchip | F25: RK3588 | G25: 8GB typical | H25: ARM + NPU, HDMI/MIPI | I25: Vision AI gateway | J25: Startups | K25: Import | L25: Import | M25: 9200 | N25: 11500 | O25: =IF(AND(M25<>"",N25<>""),(N25-M25)/N25,"") -> 0.2 | Q25: https://www.amazon.in/s?k=Rockchip+RK3588+Dev+Board+RK3588 | S25: =HYPERLINK("https://robu.in/?s="&SUBSTITUTE($D25," ","+")&"&post_type=product","Robu search") -> Robu search | T25: 143.06 | U25: https://www.alibaba.com/showroom/rk3588.html | W25: =HYPERLINK("https://www.lcsc.com/search?q="&SUBSTITUTE($D25," ","+"),"LCSC search") -> LCSC search | Y25: =HYPERLINK("https://www.mouser.in/c/?q="&SUBSTITUTE($D25," ","+"),"Mouser search") -> Mouser search | AA25: =HYPERLINK("https://www.digikey.in/en/products/filter?keywords="&SUBSTITUTE($D25," ","+"),"DigiKey search") -> DigiKey search | AC25: =Inputs_Assumptions!$B$7 -> 150 | AD25: =Inputs_Assumptions!$B$7 -> 150 | AE25: =Inputs_Assumptions!$B$5 -> 0.1 | AF25: =Inputs_Assumptions!$B$6 -> 0.18 | AG25: =Inputs_Assumptions!$B$4 -> 83 | AJ25: =IF(AH25<>"",(AH25*AG25+AD25)*(1+AE25)*(1+AF25),(M25+AD25)*(1+AF25)) -> 11033 | AK25: =Inputs_Assumptions!$B$9 -> 0.35 | AL25: =IF(AJ25<>"",AJ25/(1-AK25),"") -> 16973.846 | AM25: =Inputs_Assumptions!$B$8 -> 0.18 | AN25: =IF(AND(P25<>"",AJ25<>"",AM25<>""),(P25-AJ25-P25*AM25)/P25,"") | AO25: C | AR25: 6 | AW25: 2025-12-20 | AX25: 2025-12-21 | BH25: 2025-12-21 | BI25: Shenzhen Rongpin Electronic Technology Co., Ltd. | BJ25: https://www.alibaba.com/product-detail/Rockchip-RK3588-Development-Board-8K-Rongpin_1600529003431.html | BV25: Risky at planned sell (needs bundle or cheaper sourcing). Gross≈11%. Est Amazon net≈-7% after ~18% fees. | BW25: Direct (B2B) + IndiaMART RFQs; avoid Amazon unless bundled/priced higher; also local resellers. | BX25: Bundle: official/verified power supply + high‑end SD/SSD + heatsink/fan (if needed) + camera options + enclosure + quick‑start + remote setup session. | BY25: Title: Rockchip RK3588 Dev Board | Verified/QA Tested | Quick‑Start + Support | GST Invoice Bullets: - Key specs: ARM + NPU, HDMI/MIPI - Use case: Vision AI gateway - Pre‑tested unit with packaging QC sticker + photo proof before dispatch. - Support: setup guide (QR) + WhatsApp troubleshooting; replacement DOA policy. - Ideal for startups/labs/training centers; bulk pricing available. | BZ25: jetson orin, jetson nano, edge ai dev kit, nvidia jetson, vision ai kit, cuda devkit, ros2 ai, edge inference | CA25: Day1–2 sample+QC | Day3 assets+pack insert QR | Day4 IndiaMART+WhatsApp catalog | Week1 Amazon (kit) | Week1–2 LinkedIn/B2B outreach | Week2 small ads + optimize | Bi‑weekly price recheck | CB25: Partial (needs sample + doc evidence) | CC25: OEM/Manufacturer or Reseller (confirm on Alibaba profile) | CD25: https://www.alibaba.com/product-detail/Rockchip-RK3588-Development-Board-8K-Rongpin_1600529003431.html | CE25: Check Alibaba badges: Verified Supplier / Trade Assurance / Onsite Check (if shown). | CF25: https://www.alibaba.com/product-detail/Rockchip-RK3588-Development-Board-8K-Rongpin_1600529003431.html | CH25: Y | CI25: N | CJ25: 7 | CK25: 7 days DOA replacement; unopened returns as per channel policy. | CL25: DAP/DDP (confirm) via Trade Assurance | CM25: 3 months (board functional; no over-voltage/ESD damage). | CN25: 7–14 days (confirm with supplier) | CO25: N | CP25: Shenzhen Rongpin Electronic Technology Co., Ltd. | CR25: 2026-01-06 | CS25: Risky at planned sell (needs bundle or cheaper sourcing). Gross≈11%. Est Amazon net≈-7% after ~18% fees. | Channels: Direct (B2B) + IndiaMART RFQs; avoid Amazon unless bundled/priced higher; also local resellers. | Bundle: Bundle: official/verified power supply + high‑end SD/SSD + heatsink/fan (if needed) + camera options + enclosure + quick‑start + remote setup session. | CT25: Low | CU25: 16 | CV25: Demand 0.0/40 (units=0.0); Margin 0.0/30 (GM%=-2195871750010891520.0); Channel 0.0/10 (AmazonNet%=NA); Sourcing 0.0/10 (mode=Import); Lead 10.0/10 (days=7.0); Fit 6.0/10; Penalty 0.0/10.
A26: AI-K210 | B26: AI Edge Board | C26: Board | D26: Kendryte K210 RISC-V AI Board | E26: Canaan/Kendryte | F26: K210 | G26: K210 dev | H26: RISC-V + KPU | I26: Tiny ML/vision | J26: Students, Makers | K26: Both | L26: Import | M26: 1500 | N26: 2500 | O26: =IF(AND(M26<>"",N26<>""),(N26-M26)/N26,"") -> 0.4 | P26: 12499 | Q26: https://www.amazon.in/s?k=Sipeed+Maixduino+K210 | S26: =HYPERLINK("https://robu.in/?s="&SUBSTITUTE($D26," ","+")&"&post_type=product","Robu search") -> Robu search | T26: 22.66 | U26: https://www.alibaba.com/showroom/sipeed-maix-i.html | W26: =HYPERLINK("https://www.lcsc.com/search?q="&SUBSTITUTE($D26," ","+"),"LCSC search") -> LCSC search | Y26: =HYPERLINK("https://www.mouser.in/c/?q="&SUBSTITUTE($D26," ","+"),"Mouser search") -> Mouser search | AA26: =HYPERLINK("https://www.digikey.in/en/products/filter?keywords="&SUBSTITUTE($D26," ","+"),"DigiKey search") -> DigiKey search | AC26: =Inputs_Assumptions!$B$7 -> 150 | AD26: =Inputs_Assumptions!$B$7 -> 150 | AE26: =Inputs_Assumptions!$B$5 -> 0.1 | AF26: =Inputs_Assumptions!$B$6 -> 0.18 | AG26: =Inputs_Assumptions!$B$4 -> 83 | AJ26: =IF(AH26<>"",(AH26*AG26+AD26)*(1+AE26)*(1+AF26),(M26+AD26)*(1+AF26)) -> 1947 | AK26: =Inputs_Assumptions!$B$9 -> 0.35 | AL26: =IF(AJ26<>"",AJ26/(1-AK26),"") -> 2995.3846 | AM26: =Inputs_Assumptions!$B$8 -> 0.18 | AN26: =IF(AND(P26<>"",AJ26<>"",AM26<>""),(P26-AJ26-P26*AM26)/P26,"") -> 0.66422754 | AO26: B | AP26: 5 | AQ26: 5 | AR26: 10 | AS26: 2 | AW26: 2025-12-20 | AX26: 2025-12-21 | BH26: 2025-12-21 | BV26: Works (healthy margin). Gross≈33%. Est Amazon net≈15% after ~18% fees. | BW26: Amazon (as verified kit) + Direct (B2B) + IndiaMART; also Website/WhatsApp + LinkedIn outreach. | BX26: Bundle: official/verified power supply + high‑end SD/SSD + heatsink/fan (if needed) + camera options + enclosure + quick‑start + remote setup session. | BY26: Title: Kendryte K210 RISC-V AI Board | Verified/QA Tested | Quick‑Start + Support | GST Invoice Bullets: - Key specs: RISC-V + KPU - Use case: Tiny ML/vision - Pre‑tested unit with packaging QC sticker + photo proof before dispatch. - Support: setup guide (QR) + WhatsApp troubleshooting; replacement DOA policy. - Ideal for startups/labs/training centers; bulk pricing available. | BZ26: jetson orin, jetson nano, edge ai dev kit, nvidia jetson, vision ai kit, cuda devkit, ros2 ai, edge inference | CA26: Day1–2 sample+QC | Day3 assets+pack insert QR | Day4 IndiaMART+WhatsApp catalog | Week1 Amazon (kit) | Week1–2 LinkedIn/B2B outreach | Week2 small ads + optimize | Bi‑weekly price recheck | CB26: Pending (missing seller profile) | CC26: Reseller (needs confirmation) | CE26: Unknown | CH26: N | CI26: N | CJ26: 7 | CK26: 7 days DOA replacement; channel return policy applies. | CL26: Domestic shipment (GST invoice preferred) | CM26: 3 months replacement for functional failure (conditions apply). | CN26: 7–14 days (confirm with supplier) | CO26: N | CR26: 2026-01-06 | CS26: Works (healthy margin). Gross≈33%. Est Amazon net≈15% after ~18% fees. | Channels: Amazon (as verified kit) + Direct (B2B) + IndiaMART; also Website/WhatsApp + LinkedIn outreach. | Bundle: Bundle: official/verified power supply + high‑end SD/SSD + heatsink/fan (if needed) + camera options + enclosure + quick‑start + remote setup session. | CT26: Medium | CU26: 25.2 | CV26: Demand 4.0/40 (units=2.0); Margin 0.0/30 (GM%=-10505050450450503680.0); Channel 5.0/10 (AmazonNet%=NA); Sourcing 6.2/10 (mode=Both); Lead 10.0/10 (days=7.0); Fit 0.0/10; Penalty 0.0/10.
A27: PMOD-GPIO | B27: PMOD Module | C27: Module | D27: PMOD GPIO | E27: Generic/Digilent | F27: PMOD GPIO | H27: 8-bit IO expansion | I27: Peripheral IO | J27: FPGA users | K27: Local | L27: Local | M27: 180 | N27: 350 | O27: =IF(AND(M27<>"",N27<>""),(N27-M27)/N27,"") -> 0.48571429 | Q27: https://www.amazon.in/s?k=PMOD+GPIO+PMOD+GPIO | S27: =HYPERLINK("https://robu.in/?s="&SUBSTITUTE($D27," ","+")&"&post_type=product","Robu search") -> Robu search | U27: https://www.alibaba.com/trade/search?SearchText=PMOD+GPIO+PMOD+GPIO | W27: =HYPERLINK("https://www.lcsc.com/search?q="&SUBSTITUTE($D27," ","+"),"LCSC search") -> LCSC search | Y27: =HYPERLINK("https://www.mouser.in/c/?q="&SUBSTITUTE($D27," ","+"),"Mouser search") -> Mouser search | AA27: =HYPERLINK("https://www.digikey.in/en/products/filter?keywords="&SUBSTITUTE($D27," ","+"),"DigiKey search") -> DigiKey search | AC27: =Inputs_Assumptions!$B$7 -> 150 | AD27: =Inputs_Assumptions!$B$7 -> 150 | AE27: =Inputs_Assumptions!$B$5 -> 0.1 | AF27: =Inputs_Assumptions!$B$6 -> 0.18 | AG27: =Inputs_Assumptions!$B$4 -> 83 | AJ27: =IF(AH27<>"",(AH27*AG27+AD27)*(1+AE27)*(1+AF27),(M27+AD27)*(1+AF27)) -> 389.4 | AK27: =Inputs_Assumptions!$B$9 -> 0.35 | AL27: =IF(AJ27<>"",AJ27/(1-AK27),"") -> 599.07692 | AM27: =Inputs_Assumptions!$B$8 -> 0.18 | AN27: =IF(AND(P27<>"",AJ27<>"",AM27<>""),(P27-AJ27-P27*AM27)/P27,"") | AO27: B | AP27: 15 | AQ27: 15 | AR27: 30 | AS27: 4 | AW27: 2025-12-20 | AX27: 2025-12-21 | BH27: 2025-12-21 | BV27: Works (healthy margin). Gross≈41%. Est Amazon net≈23% after ~18% fees. | BW27: Amazon (as verified kit) + Direct (B2B) + IndiaMART; also Website/WhatsApp + LinkedIn outreach. | BX27: Add: essentials kit (cables/adapters) + quick‑start card + basic support + 7‑day DOA replacement. | BY27: Title: PMOD GPIO | Verified/QA Tested | Quick‑Start + Support | GST Invoice Bullets: - Key specs: 8-bit IO expansion - Use case: Peripheral IO - Pre‑tested unit with packaging QC sticker + photo proof before dispatch. - Support: setup guide (QR) + WhatsApp troubleshooting; replacement DOA policy. - Ideal for startups/labs/training centers; bulk pricing available. | BZ27: electronics module, dev kit, maker kit, embedded components | CA27: Day1–2 sample+QC | Day3 assets+pack insert QR | Day4 IndiaMART+WhatsApp catalog | Week1 Amazon (kit) | Week1–2 LinkedIn/B2B outreach | Week2 small ads + optimize | Bi‑weekly price recheck | CB27: Pending (missing seller profile) | CC27: Reseller (needs confirmation) | CE27: Unknown | CH27: N | CI27: N | CJ27: 7 | CK27: Marketplace return policy; 7 days DOA replacement. | CL27: Domestic shipment (GST invoice preferred) | CM27: 30 days replacement for DOA. | CN27: 7–14 days (confirm with supplier) | CO27: N | CR27: 2026-01-06 | CS27: Works (healthy margin). Gross≈41%. Est Amazon net≈23% after ~18% fees. | Channels: Amazon (as verified kit) + Direct (B2B) + IndiaMART; also Website/WhatsApp + LinkedIn outreach. | Bundle: Add: essentials kit (cables/adapters) + quick‑start card + basic support + 7‑day DOA replacement. | CT27: Medium | CU27: 28.2 | CV27: Demand 8.0/40 (units=4.0); Margin 0.0/30 (GM%=-77922077506077933568.0); Channel 5.0/10 (AmazonNet%=NA); Sourcing 6.2/10 (mode=Local); Lead 10.0/10 (days=7.0); Fit 4.0/10; Penalty 5.0/10.
A28: PMOD-OLED | B28: PMOD Module | C28: Module | D28: PMOD OLED Display | E28: Generic/Digilent | F28: PMOD OLED | H28: 0.96" OLED | I28: UI | J28: FPGA users | K28: Local | L28: Local | M28: 700 | N28: 1200 | O28: =IF(AND(M28<>"",N28<>""),(N28-M28)/N28,"") -> 0.41666667 | Q28: https://www.amazon.in/s?k=PMOD+OLED+Display+PMOD+OLED | S28: =HYPERLINK("https://robu.in/?s="&SUBSTITUTE($D28," ","+")&"&post_type=product","Robu search") -> Robu search | U28: https://www.alibaba.com/trade/search?SearchText=PMOD+OLED+Display+PMOD+OLED | W28: =HYPERLINK("https://www.lcsc.com/search?q="&SUBSTITUTE($D28," ","+"),"LCSC search") -> LCSC search | Y28: =HYPERLINK("https://www.mouser.in/c/?q="&SUBSTITUTE($D28," ","+"),"Mouser search") -> Mouser search | AA28: =HYPERLINK("https://www.digikey.in/en/products/filter?keywords="&SUBSTITUTE($D28," ","+"),"DigiKey search") -> DigiKey search | AC28: =Inputs_Assumptions!$B$7 -> 150 | AD28: =Inputs_Assumptions!$B$7 -> 150 | AE28: =Inputs_Assumptions!$B$5 -> 0.1 | AF28: =Inputs_Assumptions!$B$6 -> 0.18 | AG28: =Inputs_Assumptions!$B$4 -> 83 | AJ28: =IF(AH28<>"",(AH28*AG28+AD28)*(1+AE28)*(1+AF28),(M28+AD28)*(1+AF28)) -> 1003 | AK28: =Inputs_Assumptions!$B$9 -> 0.35 | AL28: =IF(AJ28<>"",AJ28/(1-AK28),"") -> 1543.0769 | AM28: =Inputs_Assumptions!$B$8 -> 0.18 | AN28: =IF(AND(P28<>"",AJ28<>"",AM28<>""),(P28-AJ28-P28*AM28)/P28,"") | AO28: B | AP28: 6 | AQ28: 6 | AR28: 12 | AS28: 2 | AW28: 2025-12-20 | AX28: 2025-12-21 | BH28: 2025-12-21 | BV28: Works (healthy margin). Gross≈34%. Est Amazon net≈16% after ~18% fees. | BW28: Amazon (as verified kit) + Direct (B2B) + IndiaMART; also Website/WhatsApp + LinkedIn outreach. | BX28: Add: essentials kit (cables/adapters) + quick‑start card + basic support + 7‑day DOA replacement. | BY28: Title: PMOD OLED Display | Verified/QA Tested | Quick‑Start + Support | GST Invoice Bullets: - Key specs: 0.96" OLED - Use case: UI - Pre‑tested unit with packaging QC sticker + photo proof before dispatch. - Support: setup guide (QR) + WhatsApp troubleshooting; replacement DOA policy. - Ideal for startups/labs/training centers; bulk pricing available. | BZ28: electronics module, dev kit, maker kit, embedded components | CA28: Day1–2 sample+QC | Day3 assets+pack insert QR | Day4 IndiaMART+WhatsApp catalog | Week1 Amazon (kit) | Week1–2 LinkedIn/B2B outreach | Week2 small ads + optimize | Bi‑weekly price recheck | CB28: Pending (missing seller profile) | CC28: Reseller (needs confirmation) | CE28: Unknown | CH28: N | CI28: N | CJ28: 7 | CK28: Marketplace return policy; 7 days DOA replacement. | CL28: Domestic shipment (GST invoice preferred) | CM28: 30 days replacement for DOA. | CN28: 7–14 days (confirm with supplier) | CO28: N | CR28: 2026-01-06 | CS28: Works (healthy margin). Gross≈34%. Est Amazon net≈16% after ~18% fees. | Channels: Amazon (as verified kit) + Direct (B2B) + IndiaMART; also Website/WhatsApp + LinkedIn outreach. | Bundle: Add: essentials kit (cables/adapters) + quick‑start card + basic support + 7‑day DOA replacement. | CT28: Medium | CU28: 24.2 | CV28: Demand 4.0/40 (units=2.0); Margin 0.0/30 (GM%=-23569023440106901504.0); Channel 5.0/10 (AmazonNet%=NA); Sourcing 6.2/10 (mode=Local); Lead 10.0/10 (days=7.0); Fit 4.0/10; Penalty 5.0/10.
A29: PMOD-CAM-OV5640 | B29: PMOD Module | C29: Module | D29: PMOD Camera OV5640 | E29: Generic | F29: OV5640 | G29: 5MP | H29: DVP camera module | I29: Vision input | J29: FPGA/AI devs | K29: Import | L29: Import | M29: 850 | N29: 1500 | O29: =IF(AND(M29<>"",N29<>""),(N29-M29)/N29,"") -> 0.43333333 | Q29: https://www.amazon.in/s?k=PMOD+Camera+OV5640+OV5640 | S29: =HYPERLINK("https://robu.in/?s="&SUBSTITUTE($D29," ","+")&"&post_type=product","Robu search") -> Robu search | U29: https://www.alibaba.com/trade/search?SearchText=PMOD+Camera+OV5640+OV5640 | W29: =HYPERLINK("https://www.lcsc.com/search?q="&SUBSTITUTE($D29," ","+"),"LCSC search") -> LCSC search | Y29: =HYPERLINK("https://www.mouser.in/c/?q="&SUBSTITUTE($D29," ","+"),"Mouser search") -> Mouser search | AA29: =HYPERLINK("https://www.digikey.in/en/products/filter?keywords="&SUBSTITUTE($D29," ","+"),"DigiKey search") -> DigiKey search | AC29: =Inputs_Assumptions!$B$7 -> 150 | AD29: =Inputs_Assumptions!$B$7 -> 150 | AE29: =Inputs_Assumptions!$B$5 -> 0.1 | AF29: =Inputs_Assumptions!$B$6 -> 0.18 | AG29: =Inputs_Assumptions!$B$4 -> 83 | AJ29: =IF(AH29<>"",(AH29*AG29+AD29)*(1+AE29)*(1+AF29),(M29+AD29)*(1+AF29)) -> 1180 | AK29: =Inputs_Assumptions!$B$9 -> 0.35 | AL29: =IF(AJ29<>"",AJ29/(1-AK29),"") -> 1815.3846 | AM29: =Inputs_Assumptions!$B$8 -> 0.18 | AN29: =IF(AND(P29<>"",AJ29<>"",AM29<>""),(P29-AJ29-P29*AM29)/P29,"") | AO29: C | AP29: 6 | AQ29: 6 | AR29: 12 | AS29: 2 | AW29: 2025-12-20 | AX29: 2025-12-21 | BH29: 2025-12-21 | BV29: Works (healthy margin). Gross≈36%. Est Amazon net≈18% after ~18% fees. | BW29: Amazon (as verified kit) + Direct (B2B) + IndiaMART; also Website/WhatsApp + LinkedIn outreach. | BX29: Bundle: flex cable + lens options + mounting kit + sample pipelines + quick‑start for Jetson/RPi. | BY29: Title: PMOD Camera OV5640 | Verified/QA Tested | Quick‑Start + Support | GST Invoice Bullets: - Key specs: DVP camera module - Use case: Vision input - Pre‑tested unit with packaging QC sticker + photo proof before dispatch. - Support: setup guide (QR) + WhatsApp troubleshooting; replacement DOA policy. - Ideal for startups/labs/training centers; bulk pricing available. | BZ29: csi camera, imx camera module, jetson camera, raspberry pi camera, mipi csi, vision module | CA29: Day1–2 sample+QC | Day3 assets+pack insert QR | Day4 IndiaMART+WhatsApp catalog | Week1 Amazon (kit) | Week1–2 LinkedIn/B2B outreach | Week2 small ads + optimize | Bi‑weekly price recheck | CB29: Pending (missing seller profile) | CC29: Reseller (needs confirmation) | CE29: Unknown | CH29: N | CI29: N | CJ29: 7 | CK29: Marketplace return policy; 7 days DOA replacement. | CL29: Domestic shipment (GST invoice preferred) | CM29: 30 days replacement for DOA. | CN29: 7–14 days (confirm with supplier) | CO29: N | CR29: 2026-01-06 | CS29: Works (healthy margin). Gross≈36%. Est Amazon net≈18% after ~18% fees. | Channels: Amazon (as verified kit) + Direct (B2B) + IndiaMART; also Website/WhatsApp + LinkedIn outreach. | Bundle: Bundle: flex cable + lens options + mounting kit + sample pipelines + quick‑start for Jetson/RPi. | CT29: Low | CU29: 18 | CV29: Demand 4.0/40 (units=2.0); Margin 0.0/30 (GM%=-19528619419419529216.0); Channel 5.0/10 (AmazonNet%=NA); Sourcing 0.0/10 (mode=Import); Lead 10.0/10 (days=7.0); Fit 4.0/10; Penalty 5.0/10.
A30: PMOD-ADC | B30: PMOD Module | C30: Module | D30: PMOD ADC | E30: Generic/Digilent | F30: PMOD ADC | H30: Analog input module | I30: Sensors | J30: FPGA devs | K30: Local | L30: Local | M30: 350 | N30: 700 | O30: =IF(AND(M30<>"",N30<>""),(N30-M30)/N30,"") -> 0.5 | Q30: https://www.amazon.in/s?k=PMOD+ADC+PMOD+ADC | S30: =HYPERLINK("https://robu.in/?s="&SUBSTITUTE($D30," ","+")&"&post_type=product","Robu search") -> Robu search | U30: https://www.alibaba.com/trade/search?SearchText=PMOD+ADC+PMOD+ADC | W30: =HYPERLINK("https://www.lcsc.com/search?q="&SUBSTITUTE($D30," ","+"),"LCSC search") -> LCSC search | Y30: =HYPERLINK("https://www.mouser.in/c/?q="&SUBSTITUTE($D30," ","+"),"Mouser search") -> Mouser search | AA30: =HYPERLINK("https://www.digikey.in/en/products/filter?keywords="&SUBSTITUTE($D30," ","+"),"DigiKey search") -> DigiKey search | AC30: =Inputs_Assumptions!$B$7 -> 150 | AD30: =Inputs_Assumptions!$B$7 -> 150 | AE30: =Inputs_Assumptions!$B$5 -> 0.1 | AF30: =Inputs_Assumptions!$B$6 -> 0.18 | AG30: =Inputs_Assumptions!$B$4 -> 83 | AJ30: =IF(AH30<>"",(AH30*AG30+AD30)*(1+AE30)*(1+AF30),(M30+AD30)*(1+AF30)) -> 590 | AK30: =Inputs_Assumptions!$B$9 -> 0.35 | AL30: =IF(AJ30<>"",AJ30/(1-AK30),"") -> 907.69231 | AM30: =Inputs_Assumptions!$B$8 -> 0.18 | AN30: =IF(AND(P30<>"",AJ30<>"",AM30<>""),(P30-AJ30-P30*AM30)/P30,"") | AO30: B | AP30: 10 | AQ30: 10 | AR30: 20 | AS30: 3 | AW30: 2025-12-20 | AX30: 2025-12-21 | BH30: 2025-12-21 | BV30: Works (healthy margin). Gross≈43%. Est Amazon net≈25% after ~18% fees. | BW30: Amazon (as verified kit) + Direct (B2B) + IndiaMART; also Website/WhatsApp + LinkedIn outreach. | BX30: Add: essentials kit (cables/adapters) + quick‑start card + basic support + 7‑day DOA replacement. | BY30: Title: PMOD ADC | Verified/QA Tested | Quick‑Start + Support | GST Invoice Bullets: - Key specs: Analog input module - Use case: Sensors - Pre‑tested unit with packaging QC sticker + photo proof before dispatch. - Support: setup guide (QR) + WhatsApp troubleshooting; replacement DOA policy. - Ideal for startups/labs/training centers; bulk pricing available. | BZ30: electronics module, dev kit, maker kit, embedded components | CA30: Day1–2 sample+QC | Day3 assets+pack insert QR | Day4 IndiaMART+WhatsApp catalog | Week1 Amazon (kit) | Week1–2 LinkedIn/B2B outreach | Week2 small ads + optimize | Bi‑weekly price recheck | CB30: Pending (missing seller profile) | CC30: Reseller (needs confirmation) | CE30: Unknown | CH30: N | CI30: N | CJ30: 7 | CK30: Marketplace return policy; 7 days DOA replacement. | CL30: Domestic shipment (GST invoice preferred) | CM30: 30 days replacement for DOA. | CN30: 7–14 days (confirm with supplier) | CO30: N | CR30: 2026-01-06 | CS30: Works (healthy margin). Gross≈43%. Est Amazon net≈25% after ~18% fees. | Channels: Amazon (as verified kit) + Direct (B2B) + IndiaMART; also Website/WhatsApp + LinkedIn outreach. | Bundle: Add: essentials kit (cables/adapters) + quick‑start card + basic support + 7‑day DOA replacement. | CT30: Medium | CU30: 26.2 | CV30: Demand 6.0/40 (units=3.0); Margin 0.0/30 (GM%=-43290043043043287040.0); Channel 5.0/10 (AmazonNet%=NA); Sourcing 6.2/10 (mode=Local); Lead 10.0/10 (days=7.0); Fit 4.0/10; Penalty 5.0/10.
A31: PMOD-WIFI | B31: PMOD Module | C31: Module | D31: PMOD WiFi/Bluetooth | E31: Generic | F31: ESP8266/BT | H31: Wireless connectivity | I31: IoT | J31: FPGA/MCU devs | K31: Local | L31: Local | M31: 550 | N31: 950 | O31: =IF(AND(M31<>"",N31<>""),(N31-M31)/N31,"") -> 0.42105263 | Q31: https://www.amazon.in/s?k=PMOD+WiFi%2FBluetooth+ESP8266%2FBT | S31: =HYPERLINK("https://robu.in/?s="&SUBSTITUTE($D31," ","+")&"&post_type=product","Robu search") -> Robu search | U31: https://www.alibaba.com/trade/search?SearchText=PMOD+WiFi%2FBluetooth+ESP8266%2FBT | W31: =HYPERLINK("https://www.lcsc.com/search?q="&SUBSTITUTE($D31," ","+"),"LCSC search") -> LCSC search | Y31: =HYPERLINK("https://www.mouser.in/c/?q="&SUBSTITUTE($D31," ","+"),"Mouser search") -> Mouser search | AA31: =HYPERLINK("https://www.digikey.in/en/products/filter?keywords="&SUBSTITUTE($D31," ","+"),"DigiKey search") -> DigiKey search | AC31: =Inputs_Assumptions!$B$7 -> 150 | AD31: =Inputs_Assumptions!$B$7 -> 150 | AE31: =Inputs_Assumptions!$B$5 -> 0.1 | AF31: =Inputs_Assumptions!$B$6 -> 0.18 | AG31: =Inputs_Assumptions!$B$4 -> 83 | AJ31: =IF(AH31<>"",(AH31*AG31+AD31)*(1+AE31)*(1+AF31),(M31+AD31)*(1+AF31)) -> 826 | AK31: =Inputs_Assumptions!$B$9 -> 0.35 | AL31: =IF(AJ31<>"",AJ31/(1-AK31),"") -> 1270.7692 | AM31: =Inputs_Assumptions!$B$8 -> 0.18 | AN31: =IF(AND(P31<>"",AJ31<>"",AM31<>""),(P31-AJ31-P31*AM31)/P31,"") | AO31: B | AP31: 8 | AQ31: 8 | AR31: 16 | AS31: 2 | AW31: 2025-12-20 | AX31: 2025-12-21 | BH31: 2025-12-21 | BV31: Works (healthy margin). Gross≈35%. Est Amazon net≈17% after ~18% fees. | BW31: Amazon (as verified kit) + Direct (B2B) + IndiaMART; also Website/WhatsApp + LinkedIn outreach. | BX31: Add: essentials kit (cables/adapters) + quick‑start card + basic support + 7‑day DOA replacement. | BY31: Title: PMOD WiFi/Bluetooth | Verified/QA Tested | Quick‑Start + Support | GST Invoice Bullets: - Key specs: Wireless connectivity - Use case: IoT - Pre‑tested unit with packaging QC sticker + photo proof before dispatch. - Support: setup guide (QR) + WhatsApp troubleshooting; replacement DOA policy. - Ideal for startups/labs/training centers; bulk pricing available. | BZ31: electronics module, dev kit, maker kit, embedded components | CA31: Day1–2 sample+QC | Day3 assets+pack insert QR | Day4 IndiaMART+WhatsApp catalog | Week1 Amazon (kit) | Week1–2 LinkedIn/B2B outreach | Week2 small ads + optimize | Bi‑weekly price recheck | CB31: Pending (missing seller profile) | CC31: Reseller (needs confirmation) | CE31: Unknown | CH31: N | CI31: N | CJ31: 7 | CK31: Marketplace return policy; 7 days DOA replacement. | CL31: Domestic shipment (GST invoice preferred) | CM31: 30 days replacement for DOA. | CN31: 7–14 days (confirm with supplier) | CO31: N | CR31: 2026-01-06 | CS31: Works (healthy margin). Gross≈35%. Est Amazon net≈17% after ~18% fees. | Channels: Amazon (as verified kit) + Direct (B2B) + IndiaMART; also Website/WhatsApp + LinkedIn outreach. | Bundle: Add: essentials kit (cables/adapters) + quick‑start card + basic support + 7‑day DOA replacement. | CT31: Medium | CU31: 24.2 | CV31: Demand 4.0/40 (units=2.0); Margin 0.0/30 (GM%=-32961190664348749824.0); Channel 5.0/10 (AmazonNet%=NA); Sourcing 6.2/10 (mode=Local); Lead 10.0/10 (days=7.0); Fit 4.0/10; Penalty 5.0/10.
A32: PMOD-ETH | B32: PMOD Module | C32: Module | D32: PMOD Ethernet | E32: Generic | F32: W5500 | H32: Ethernet interface | I32: Networking | J32: FPGA devs | K32: Import | L32: Import | M32: 950 | N32: 1600 | O32: =IF(AND(M32<>"",N32<>""),(N32-M32)/N32,"") -> 0.40625 | Q32: =HYPERLINK("https://www.amazon.in/s?k="&SUBSTITUTE($D32," ","+"),"Amazon search") -> Amazon search | S32: =HYPERLINK("https://robu.in/?s="&SUBSTITUTE($D32," ","+")&"&post_type=product","Robu search") -> Robu search | U32: =HYPERLINK("https://www.alibaba.com/trade/search?SearchText="&SUBSTITUTE($D32," ","+"),"Alibaba search") -> Alibaba search | W32: =HYPERLINK("https://www.lcsc.com/search?q="&SUBSTITUTE($D32," ","+"),"LCSC search") -> LCSC search | Y32: =HYPERLINK("https://www.mouser.in/c/?q="&SUBSTITUTE($D32," ","+"),"Mouser search") -> Mouser search | AA32: =HYPERLINK("https://www.digikey.in/en/products/filter?keywords="&SUBSTITUTE($D32," ","+"),"DigiKey search") -> DigiKey search | AC32: =Inputs_Assumptions!$B$7 -> 150 | AD32: =Inputs_Assumptions!$B$7 -> 150 | AE32: =Inputs_Assumptions!$B$5 -> 0.1 | AF32: =Inputs_Assumptions!$B$6 -> 0.18 | AG32: =Inputs_Assumptions!$B$4 -> 83 | AJ32: =IF(AH32<>"",(AH32*AG32+AD32)*(1+AE32)*(1+AF32),(M32+AD32)*(1+AF32)) -> 1298 | AK32: =Inputs_Assumptions!$B$9 -> 0.35 | AL32: =IF(AJ32<>"",AJ32/(1-AK32),"") -> 1996.9231 | AM32: =Inputs_Assumptions!$B$8 -> 0.18 | AN32: =IF(AND(P32<>"",AJ32<>"",AM32<>""),(P32-AJ32-P32*AM32)/P32,"") | AO32: C | AQ32: 6 | AR32: 12 | AS32: 2 | AW32: 2025-12-20 | BV32: Works (healthy margin). Gross≈33%. Est Amazon net≈15% after ~18% fees. | BW32: Amazon (as verified kit) + Direct (B2B) + IndiaMART; also Website/WhatsApp + LinkedIn outreach. | BX32: Add: essentials kit (cables/adapters) + quick‑start card + basic support + 7‑day DOA replacement. | BY32: Title: PMOD Ethernet | Verified/QA Tested | Quick‑Start + Support | GST Invoice Bullets: - Key specs: Ethernet interface - Use case: Networking - Pre‑tested unit with packaging QC sticker + photo proof before dispatch. - Support: setup guide (QR) + WhatsApp troubleshooting; replacement DOA policy. - Ideal for startups/labs/training centers; bulk pricing available. | BZ32: electronics module, dev kit, maker kit, embedded components | CA32: Day1–2 sample+QC | Day3 assets+pack insert QR | Day4 IndiaMART+WhatsApp catalog | Week1 Amazon (kit) | Week1–2 LinkedIn/B2B outreach | Week2 small ads + optimize | Bi‑weekly price recheck | CB32: Pending (missing seller profile) | CC32: Reseller (needs confirmation) | CE32: Unknown | CH32: N | CI32: N | CJ32: 7 | CK32: Marketplace return policy; 7 days DOA replacement. | CL32: Domestic shipment (GST invoice preferred) | CM32: 30 days replacement for DOA. | CN32: 7–14 days (confirm with supplier) | CO32: N | CR32: 2026-01-06 | CS32: Works (healthy margin). Gross≈33%. Est Amazon net≈15% after ~18% fees. | Channels: Amazon (as verified kit) + Direct (B2B) + IndiaMART; also Website/WhatsApp + LinkedIn outreach. | Bundle: Add: essentials kit (cables/adapters) + quick‑start card + basic support + 7‑day DOA replacement. | CT32: Low | CU32: 18 | CV32: Demand 4.0/40 (units=2.0); Margin 0.0/30 (GM%=-20202020082582700032.0); Channel 5.0/10 (AmazonNet%=NA); Sourcing 0.0/10 (mode=Import); Lead 10.0/10 (days=7.0); Fit 4.0/10; Penalty 5.0/10.
A33: CAM-IMX219 | B33: Camera | C33: Module | D33: Sony IMX219 MIPI Camera | E33: Sony | F33: IMX219 | G33: 8MP | H33: MIPI CSI-2 | I33: Jetson/RPi vision | J33: AI devs | K33: Local | L33: Local | M33: 1649 | N33: 2540 | O33: 0.3508 | Q33: =HYPERLINK("https://www.amazon.in/s?k="&SUBSTITUTE($D33," ","+"),"Amazon search") -> Amazon search | R33: 1649 | S33: https://robu.in/product/raspberry-pi-camera-v2/ | U33: =HYPERLINK("https://www.alibaba.com/trade/search?SearchText="&SUBSTITUTE($D33," ","+"),"Alibaba search") -> Alibaba search | W33: =HYPERLINK("https://www.lcsc.com/search?q="&SUBSTITUTE($D33," ","+"),"LCSC search") -> LCSC search | Y33: =HYPERLINK("https://www.mouser.in/c/?q="&SUBSTITUTE($D33," ","+"),"Mouser search") -> Mouser search | AA33: =HYPERLINK("https://www.digikey.in/en/products/filter?keywords="&SUBSTITUTE($D33," ","+"),"DigiKey search") -> DigiKey search | AC33: =Inputs_Assumptions!$B$7 -> 150 | AD33: =Inputs_Assumptions!$B$7 -> 150 | AE33: =Inputs_Assumptions!$B$5 -> 0.1 | AF33: =Inputs_Assumptions!$B$6 -> 0.18 | AG33: =Inputs_Assumptions!$B$4 -> 83 | AJ33: =IF(AH33<>"",(AH33*AG33+AD33)*(1+AE33)*(1+AF33),(M33+AD33)*(1+AF33)) -> 2122.82 | AK33: =Inputs_Assumptions!$B$9 -> 0.35 | AL33: =IF(AJ33<>"",AJ33/(1-AK33),"") -> 3265.8769 | AM33: =Inputs_Assumptions!$B$8 -> 0.18 | AN33: =IF(AND(P33<>"",AJ33<>"",AM33<>""),(P33-AJ33-P33*AM33)/P33,"") | AO33: B | AP33: 6 | AQ33: 6 | AR33: 12 | AS33: 2 | AU33: 2025-12-21 | AV33: Robu price for Arducam IMX219 wide-angle module incl GST. (2025-12-20) | AW33: 2025-12-20 | BC33: 2025-12-21 | BD33: MACFOS LIMITED (Robu.in) | BE33: https://robu.in/ | BF33: Survey No. 78/1, Sumant Building, Dynamic Logistics Trade Park, Dighi, Bhosari-Alandi Road, Pune, Maharashtra 411015, India | BG33: Phone: 1800 266 6123 / 020 6819 7600 ; Email: info@robu.in | BM33: 1649 | BN33: Robu.in | BO33: https://robu.in/product/raspberry-pi-camera-v2/ | BP33: MACFOS LIMITED (Robu.in) | BQ33: https://robu.in/ | BR33: Survey No. 78/1, Sumant Building, Dynamic Logistics Trade Park, Dighi, Bhosari-Alandi Road, Pune, Maharashtra 411015, India | BS33: Phone: 1800 266 6123 / 020 6819 7600 ; Email: info@robu.in | BT33: 2025-12-21 | BU33: Official Raspberry Pi Camera V2 (IMX219) used. | BV33: Works (healthy margin). Gross≈27%. Est Amazon net≈9% after ~18% fees. | BW33: Amazon (as verified kit) + Direct (B2B) + IndiaMART; also Website/WhatsApp + LinkedIn outreach. | BX33: Bundle: flex cable + lens options + mounting kit + sample pipelines + quick‑start for Jetson/RPi. | BY33: Title: Sony IMX219 MIPI Camera | Verified/QA Tested | Quick‑Start + Support | GST Invoice Bullets: - Key specs: MIPI CSI-2 - Use case: Jetson/RPi vision - Pre‑tested unit with packaging QC sticker + photo proof before dispatch. - Support: setup guide (QR) + WhatsApp troubleshooting; replacement DOA policy. - Ideal for startups/labs/training centers; bulk pricing available. | BZ33: csi camera, imx camera module, jetson camera, raspberry pi camera, mipi csi, vision module | CA33: Day1–2 sample+QC | Day3 assets+pack insert QR | Day4 IndiaMART+WhatsApp catalog | Week1 Amazon (kit) | Week1–2 LinkedIn/B2B outreach | Week2 small ads + optimize | Bi‑weekly price recheck | CB33: Partial (needs sample + doc evidence) | CC33: Reseller / Marketplace Seller | CD33: https://robu.in/product/raspberry-pi-camera-v2/ | CE33: Marketplace seller (badge depends on platform); prefer GST invoice + established store ratings. | CH33: Y | CI33: N | CJ33: 7 | CK33: Marketplace return policy; 7 days DOA replacement. | CL33: Domestic shipment (GST invoice preferred) | CM33: 30 days replacement for DOA. | CN33: Bangalore: 48–72 hrs replacement (stock permitting); else 7–14 days via supplier. | CO33: Y | CP33: MACFOS LIMITED (Robu.in) | CQ33: Robu.in | https://robu.in/product/raspberry-pi-camera-v2/ | CR33: 2026-01-06 | CS33: Works (healthy margin). Gross≈27%. Est Amazon net≈9% after ~18% fees. | Channels: Amazon (as verified kit) + Direct (B2B) + IndiaMART; also Website/WhatsApp + LinkedIn outreach. | Bundle: Bundle: flex cable + lens options + mounting kit + sample pipelines + quick‑start for Jetson/RPi. | CT33: Medium | CU33: 25.4 | CV33: Demand 4.0/40 (units=2.0); Margin 0.3/30 (GM%=0.4); Channel 5.0/10 (AmazonNet%=NA); Sourcing 6.2/10 (mode=Local); Lead 10.0/10 (days=7.0); Fit 0.0/10; Penalty 0.0/10.
A34: CAM-IMX477 | B34: Camera | C34: Module | D34: Sony IMX477 HQ Camera | E34: Sony | F34: IMX477 | G34: 12MP | H34: MIPI CSI-2 HQ | I34: High quality vision | J34: AI devs | K34: Import | L34: Import | M34: 6999 | N34: 10770 | O34: 0.3501 | Q34: =HYPERLINK("https://www.amazon.in/s?k="&SUBSTITUTE($D34," ","+"),"Amazon search") -> Amazon search | R34: 6999 | S34: https://robu.in/product/waveshare-imx477-160-12-3mp-camera-160-fov-applicable-for-jetson-nano-compute-module/ | U34: =HYPERLINK("https://www.alibaba.com/trade/search?SearchText="&SUBSTITUTE($D34," ","+"),"Alibaba search") -> Alibaba search | W34: =HYPERLINK("https://www.lcsc.com/search?q="&SUBSTITUTE($D34," ","+"),"LCSC search") -> LCSC search | Y34: =HYPERLINK("https://www.mouser.in/c/?q="&SUBSTITUTE($D34," ","+"),"Mouser search") -> Mouser search | AA34: =HYPERLINK("https://www.digikey.in/en/products/filter?keywords="&SUBSTITUTE($D34," ","+"),"DigiKey search") -> DigiKey search | AC34: =Inputs_Assumptions!$B$7 -> 150 | AD34: =Inputs_Assumptions!$B$7 -> 150 | AE34: =Inputs_Assumptions!$B$5 -> 0.1 | AF34: =Inputs_Assumptions!$B$6 -> 0.18 | AG34: =Inputs_Assumptions!$B$4 -> 83 | AJ34: =IF(AH34<>"",(AH34*AG34+AD34)*(1+AE34)*(1+AF34),(M34+AD34)*(1+AF34)) -> 8435.82 | AK34: =Inputs_Assumptions!$B$9 -> 0.35 | AL34: =IF(AJ34<>"",AJ34/(1-AK34),"") -> 12978.185 | AM34: =Inputs_Assumptions!$B$8 -> 0.18 | AN34: =IF(AND(P34<>"",AJ34<>"",AM34<>""),(P34-AJ34-P34*AM34)/P34,"") | AO34: C | AQ34: 3 | AR34: 6 | AS34: 1 | AU34: 2025-12-21 | AV34: Robu price for Arducam IMX477 motorized focus incl GST. (2025-12-20) | AW34: 2025-12-20 | BC34: 2025-12-21 | BD34: MACFOS LIMITED (Robu.in) | BE34: https://robu.in/ | BF34: Survey No. 78/1, Sumant Building, Dynamic Logistics Trade Park, Dighi, Bhosari-Alandi Road, Pune, Maharashtra 411015, India | BG34: Phone: 1800 266 6123 / 020 6819 7600 ; Email: info@robu.in | BM34: 6999 | BN34: Robu.in | BO34: https://robu.in/product/waveshare-imx477-160-12-3mp-camera-160-fov-applicable-for-jetson-nano-compute-module/ | BP34: MACFOS LIMITED (Robu.in) | BQ34: https://robu.in/ | BR34: Survey No. 78/1, Sumant Building, Dynamic Logistics Trade Park, Dighi, Bhosari-Alandi Road, Pune, Maharashtra 411015, India | BS34: Phone: 1800 266 6123 / 020 6819 7600 ; Email: info@robu.in | BT34: 2025-12-21 | BU34: Waveshare IMX477-160 (12.3MP) used. | BV34: Works (healthy margin). Gross≈28%. Est Amazon net≈10% after ~18% fees. | BW34: Amazon (as verified kit) + Direct (B2B) + IndiaMART; also Website/WhatsApp + LinkedIn outreach. | BX34: Bundle: flex cable + lens options + mounting kit + sample pipelines + quick‑start for Jetson/RPi. | BY34: Title: Sony IMX477 HQ Camera | Verified/QA Tested | Quick‑Start + Support | GST Invoice Bullets: - Key specs: MIPI CSI-2 HQ - Use case: High quality vision - Pre‑tested unit with packaging QC sticker + photo proof before dispatch. - Support: setup guide (QR) + WhatsApp troubleshooting; replacement DOA policy. - Ideal for startups/labs/training centers; bulk pricing available. | BZ34: csi camera, imx camera module, jetson camera, raspberry pi camera, mipi csi, vision module | CA34: Day1–2 sample+QC | Day3 assets+pack insert QR | Day4 IndiaMART+WhatsApp catalog | Week1 Amazon (kit) | Week1–2 LinkedIn/B2B outreach | Week2 small ads + optimize | Bi‑weekly price recheck | CB34: Partial (needs sample + doc evidence) | CC34: Reseller / Marketplace Seller | CD34: https://robu.in/product/waveshare-imx477-160-12-3mp-camera-160-fov-applicable-for-jetson-nano-compute-module/ | CE34: Marketplace seller (badge depends on platform); prefer GST invoice + established store ratings. | CH34: Y | CI34: N | CJ34: 7 | CK34: Marketplace return policy; 7 days DOA replacement. | CL34: Domestic shipment (GST invoice preferred) | CM34: 30 days replacement for DOA. | CN34: Bangalore: 48–72 hrs replacement (stock permitting); else 7–14 days via supplier. | CO34: Y | CP34: MACFOS LIMITED (Robu.in) | CQ34: Robu.in | https://robu.in/product/waveshare-imx477-160-12-3mp-camera-160-fov-applicable-for-jetson-nano-compute-module/ | CR34: 2026-01-06 | CS34: Works (healthy margin). Gross≈28%. Est Amazon net≈10% after ~18% fees. | Channels: Amazon (as verified kit) + Direct (B2B) + IndiaMART; also Website/WhatsApp + LinkedIn outreach. | Bundle: Bundle: flex cable + lens options + mounting kit + sample pipelines + quick‑start for Jetson/RPi. | CT34: Low | CU34: 17.3 | CV34: Demand 2.0/40 (units=1.0); Margin 0.3/30 (GM%=0.4); Channel 5.0/10 (AmazonNet%=NA); Sourcing 0.0/10 (mode=Import); Lead 10.0/10 (days=7.0); Fit 0.0/10; Penalty 0.0/10.
A35: CAM-OV5647 | B35: Camera | C35: Module | D35: MIPI CSI-2 Camera (OV5647) | E35: OmniVision | F35: OV5647 | G35: 5MP | H35: MIPI CSI-2 | I35: Low-cost vision | J35: Students | K35: Local | L35: Local | M35: 550 | N35: 900 | O35: =IF(AND(M35<>"",N35<>""),(N35-M35)/N35,"") -> 0.38888889 | Q35: =HYPERLINK("https://www.amazon.in/s?k="&SUBSTITUTE($D35," ","+"),"Amazon search") -> Amazon search | S35: =HYPERLINK("https://robu.in/?s="&SUBSTITUTE($D35," ","+")&"&post_type=product","Robu search") -> Robu search | U35: =HYPERLINK("https://www.alibaba.com/trade/search?SearchText="&SUBSTITUTE($D35," ","+"),"Alibaba search") -> Alibaba search | W35: =HYPERLINK("https://www.lcsc.com/search?q="&SUBSTITUTE($D35," ","+"),"LCSC search") -> LCSC search | Y35: =HYPERLINK("https://www.mouser.in/c/?q="&SUBSTITUTE($D35," ","+"),"Mouser search") -> Mouser search | AA35: =HYPERLINK("https://www.digikey.in/en/products/filter?keywords="&SUBSTITUTE($D35," ","+"),"DigiKey search") -> DigiKey search | AC35: =Inputs_Assumptions!$B$7 -> 150 | AD35: =Inputs_Assumptions!$B$7 -> 150 | AE35: =Inputs_Assumptions!$B$5 -> 0.1 | AF35: =Inputs_Assumptions!$B$6 -> 0.18 | AG35: =Inputs_Assumptions!$B$4 -> 83 | AJ35: =IF(AH35<>"",(AH35*AG35+AD35)*(1+AE35)*(1+AF35),(M35+AD35)*(1+AF35)) -> 826 | AK35: =Inputs_Assumptions!$B$9 -> 0.35 | AL35: =IF(AJ35<>"",AJ35/(1-AK35),"") -> 1270.7692 | AM35: =Inputs_Assumptions!$B$8 -> 0.18 | AN35: =IF(AND(P35<>"",AJ35<>"",AM35<>""),(P35-AJ35-P35*AM35)/P35,"") | AO35: B | AP35: 6 | AQ35: 6 | AR35: 12 | AS35: 2 | AW35: 2025-12-20 | BV35: Works (healthy margin). Gross≈31%. Est Amazon net≈13% after ~18% fees. | BW35: Amazon (as verified kit) + Direct (B2B) + IndiaMART; also Website/WhatsApp + LinkedIn outreach. | BX35: Bundle: flex cable + lens options + mounting kit + sample pipelines + quick‑start for Jetson/RPi. | BY35: Title: MIPI CSI-2 Camera (OV5647) | Verified/QA Tested | Quick‑Start + Support | GST Invoice Bullets: - Key specs: MIPI CSI-2 - Use case: Low-cost vision - Pre‑tested unit with packaging QC sticker + photo proof before dispatch. - Support: setup guide (QR) + WhatsApp troubleshooting; replacement DOA policy. - Ideal for startups/labs/training centers; bulk pricing available. | BZ35: csi camera, imx camera module, jetson camera, raspberry pi camera, mipi csi, vision module | CA35: Day1–2 sample+QC | Day3 assets+pack insert QR | Day4 IndiaMART+WhatsApp catalog | Week1 Amazon (kit) | Week1–2 LinkedIn/B2B outreach | Week2 small ads + optimize | Bi‑weekly price recheck | CB35: Pending (missing seller profile) | CC35: Reseller (needs confirmation) | CE35: Unknown | CH35: N | CI35: N | CJ35: 7 | CK35: Marketplace return policy; 7 days DOA replacement. | CL35: Domestic shipment (GST invoice preferred) | CM35: 30 days replacement for DOA. | CN35: 7–14 days (confirm with supplier) | CO35: N | CR35: 2026-01-06 | CS35: Works (healthy margin). Gross≈31%. Est Amazon net≈13% after ~18% fees. | Channels: Amazon (as verified kit) + Direct (B2B) + IndiaMART; also Website/WhatsApp + LinkedIn outreach. | Bundle: Bundle: flex cable + lens options + mounting kit + sample pipelines + quick‑start for Jetson/RPi. | CT35: Medium | CU35: 25.2 | CV35: Demand 4.0/40 (units=2.0); Margin 0.0/30 (GM%=-39281705705705955328.0); Channel 5.0/10 (AmazonNet%=NA); Sourcing 6.2/10 (mode=Local); Lead 10.0/10 (days=7.0); Fit 0.0/10; Penalty 0.0/10.
A36: CAM-OV7670 | B36: Camera | C36: Module | D36: DVP Camera OV7670 | E36: OmniVision | F36: OV7670 | G36: 0.3MP | H36: Parallel DVP | I36: FPGA intro vision | J36: Students | K36: Local | L36: Local | M36: 120 | N36: 250 | O36: =IF(AND(M36<>"",N36<>""),(N36-M36)/N36,"") -> 0.52 | Q36: =HYPERLINK("https://www.amazon.in/s?k="&SUBSTITUTE($D36," ","+"),"Amazon search") -> Amazon search | S36: =HYPERLINK("https://robu.in/?s="&SUBSTITUTE($D36," ","+")&"&post_type=product","Robu search") -> Robu search | U36: =HYPERLINK("https://www.alibaba.com/trade/search?SearchText="&SUBSTITUTE($D36," ","+"),"Alibaba search") -> Alibaba search | W36: =HYPERLINK("https://www.lcsc.com/search?q="&SUBSTITUTE($D36," ","+"),"LCSC search") -> LCSC search | Y36: =HYPERLINK("https://www.mouser.in/c/?q="&SUBSTITUTE($D36," ","+"),"Mouser search") -> Mouser search | AA36: =HYPERLINK("https://www.digikey.in/en/products/filter?keywords="&SUBSTITUTE($D36," ","+"),"DigiKey search") -> DigiKey search | AC36: =Inputs_Assumptions!$B$7 -> 150 | AD36: =Inputs_Assumptions!$B$7 -> 150 | AE36: =Inputs_Assumptions!$B$5 -> 0.1 | AF36: =Inputs_Assumptions!$B$6 -> 0.18 | AG36: =Inputs_Assumptions!$B$4 -> 83 | AJ36: =IF(AH36<>"",(AH36*AG36+AD36)*(1+AE36)*(1+AF36),(M36+AD36)*(1+AF36)) -> 318.6 | AK36: =Inputs_Assumptions!$B$9 -> 0.35 | AL36: =IF(AJ36<>"",AJ36/(1-AK36),"") -> 490.15385 | AM36: =Inputs_Assumptions!$B$8 -> 0.18 | AN36: =IF(AND(P36<>"",AJ36<>"",AM36<>""),(P36-AJ36-P36*AM36)/P36,"") | AO36: B | AW36: 2025-12-20 | BV36: Works (healthy margin). Gross≈43%. Est Amazon net≈25% after ~18% fees. | BW36: Amazon (as verified kit) + Direct (B2B) + IndiaMART; also Website/WhatsApp + LinkedIn outreach. | BX36: Bundle: flex cable + lens options + mounting kit + sample pipelines + quick‑start for Jetson/RPi. | BY36: Title: DVP Camera OV7670 | Verified/QA Tested | Quick‑Start + Support | GST Invoice Bullets: - Key specs: Parallel DVP - Use case: FPGA intro vision - Pre‑tested unit with packaging QC sticker + photo proof before dispatch. - Support: setup guide (QR) + WhatsApp troubleshooting; replacement DOA policy. - Ideal for startups/labs/training centers; bulk pricing available. | BZ36: csi camera, imx camera module, jetson camera, raspberry pi camera, mipi csi, vision module | CA36: Day1–2 sample+QC | Day3 assets+pack insert QR | Day4 IndiaMART+WhatsApp catalog | Week1 Amazon (kit) | Week1–2 LinkedIn/B2B outreach | Week2 small ads + optimize | Bi‑weekly price recheck | CB36: Pending (missing seller profile) | CC36: Reseller (needs confirmation) | CE36: Unknown | CH36: N | CI36: N | CJ36: 7 | CK36: Marketplace return policy; 7 days DOA replacement. | CL36: Domestic shipment (GST invoice preferred) | CM36: 30 days replacement for DOA. | CN36: 7–14 days (confirm with supplier) | CO36: N | CR36: 2026-01-06 | CS36: Works (healthy margin). Gross≈43%. Est Amazon net≈25% after ~18% fees. | Channels: Amazon (as verified kit) + Direct (B2B) + IndiaMART; also Website/WhatsApp + LinkedIn outreach. | Bundle: Bundle: flex cable + lens options + mounting kit + sample pipelines + quick‑start for Jetson/RPi. | CT36: Medium | CU36: 21.2 | CV36: Demand 0.0/40 (units=0.0); Margin 0.0/30 (GM%=-145454544544545456128.0); Channel 5.0/10 (AmazonNet%=NA); Sourcing 6.2/10 (mode=Local); Lead 10.0/10 (days=7.0); Fit 0.0/10; Penalty 0.0/10.
A37: CAM-MLX90640 | B37: Camera | C37: Module | D37: Thermal Array MLX90640 Module | E37: Melexis | F37: MLX90640 | G37: 32x24 | H37: Thermal IR sensor | I37: Thermal inspection | J37: Industry, labs | K37: Import | L37: Import | M37: 6180 | N37: 9510 | O37: 0.3502 | Q37: =HYPERLINK("https://www.amazon.in/s?k="&SUBSTITUTE($D37," ","+"),"Amazon search") -> Amazon search | R37: 6180 | S37: https://robu.in/product/seeedstudio-grove-ir-array-sensor-mlx90640/ | U37: =HYPERLINK("https://www.alibaba.com/trade/search?SearchText="&SUBSTITUTE($D37," ","+"),"Alibaba search") -> Alibaba search | W37: =HYPERLINK("https://www.lcsc.com/search?q="&SUBSTITUTE($D37," ","+"),"LCSC search") -> LCSC search | Y37: =HYPERLINK("https://www.mouser.in/c/?q="&SUBSTITUTE($D37," ","+"),"Mouser search") -> Mouser search | AA37: =HYPERLINK("https://www.digikey.in/en/products/filter?keywords="&SUBSTITUTE($D37," ","+"),"DigiKey search") -> DigiKey search | AC37: =Inputs_Assumptions!$B$7 -> 150 | AD37: =Inputs_Assumptions!$B$7 -> 150 | AE37: =Inputs_Assumptions!$B$5 -> 0.1 | AF37: =Inputs_Assumptions!$B$6 -> 0.18 | AG37: =Inputs_Assumptions!$B$4 -> 83 | AJ37: =IF(AH37<>"",(AH37*AG37+AD37)*(1+AE37)*(1+AF37),(M37+AD37)*(1+AF37)) -> 7469.4 | AK37: =Inputs_Assumptions!$B$9 -> 0.35 | AL37: =IF(AJ37<>"",AJ37/(1-AK37),"") -> 11491.385 | AM37: =Inputs_Assumptions!$B$8 -> 0.18 | AN37: =IF(AND(P37<>"",AJ37<>"",AM37<>""),(P37-AJ37-P37*AM37)/P37,"") | AO37: C | AU37: 2025-12-21 | AW37: 2025-12-20 | BC37: 2025-12-21 | BD37: MACFOS LIMITED (Robu.in) | BE37: https://robu.in/ | BF37: Survey No. 78/1, Sumant Building, Dynamic Logistics Trade Park, Dighi, Bhosari-Alandi Road, Pune, Maharashtra 411015, India | BG37: Phone: 1800 266 6123 / 020 6819 7600 ; Email: info@robu.in | BM37: 6180 | BN37: Robu.in | BO37: https://robu.in/product/seeedstudio-grove-ir-array-sensor-mlx90640/ | BP37: MACFOS LIMITED (Robu.in) | BQ37: https://robu.in/ | BR37: Survey No. 78/1, Sumant Building, Dynamic Logistics Trade Park, Dighi, Bhosari-Alandi Road, Pune, Maharashtra 411015, India | BS37: Phone: 1800 266 6123 / 020 6819 7600 ; Email: info@robu.in | BT37: 2025-12-21 | BU37: Seeed Grove MLX90640 used. | BV37: Works (healthy margin). Gross≈28%. Est Amazon net≈10% after ~18% fees. | BW37: Amazon (as verified kit) + Direct (B2B) + IndiaMART; also Website/WhatsApp + LinkedIn outreach. | BX37: Bundle: flex cable + lens options + mounting kit + sample pipelines + quick‑start for Jetson/RPi. | BY37: Title: Thermal Array MLX90640 Module | Verified/QA Tested | Quick‑Start + Support | GST Invoice Bullets: - Key specs: Thermal IR sensor - Use case: Thermal inspection - Pre‑tested unit with packaging QC sticker + photo proof before dispatch. - Support: setup guide (QR) + WhatsApp troubleshooting; replacement DOA policy. - Ideal for startups/labs/training centers; bulk pricing available. | BZ37: csi camera, imx camera module, jetson camera, raspberry pi camera, mipi csi, vision module | CA37: Day1–2 sample+QC | Day3 assets+pack insert QR | Day4 IndiaMART+WhatsApp catalog | Week1 Amazon (kit) | Week1–2 LinkedIn/B2B outreach | Week2 small ads + optimize | Bi‑weekly price recheck | CB37: Partial (needs sample + doc evidence) | CC37: Reseller / Marketplace Seller | CD37: https://robu.in/product/seeedstudio-grove-ir-array-sensor-mlx90640/ | CE37: Marketplace seller (badge depends on platform); prefer GST invoice + established store ratings. | CH37: Y | CI37: N | CJ37: 7 | CK37: Marketplace return policy; 7 days DOA replacement. | CL37: Domestic shipment (GST invoice preferred) | CM37: 30 days replacement for DOA. | CN37: Bangalore: 48–72 hrs replacement (stock permitting); else 7–14 days via supplier. | CO37: Y | CP37: MACFOS LIMITED (Robu.in) | CQ37: Robu.in | https://robu.in/product/seeedstudio-grove-ir-array-sensor-mlx90640/ | CR37: 2026-01-06 | CS37: Works (healthy margin). Gross≈28%. Est Amazon net≈10% after ~18% fees. | Channels: Amazon (as verified kit) + Direct (B2B) + IndiaMART; also Website/WhatsApp + LinkedIn outreach. | Bundle: Bundle: flex cable + lens options + mounting kit + sample pipelines + quick‑start for Jetson/RPi. | CT37: Low | CU37: 16.3 | CV37: Demand 0.0/40 (units=0.0); Margin 0.3/30 (GM%=0.4); Channel 5.0/10 (AmazonNet%=NA); Sourcing 0.0/10 (mode=Import); Lead 10.0/10 (days=7.0); Fit 6.0/10; Penalty 5.0/10.
A38: SENS-MPU6050 | B38: Sensor | C38: Module | D38: IMU MPU6050 Module | E38: InvenSense | F38: MPU6050 | H38: 6-axis IMU | I38: Robotics | J38: Students, robotics | K38: Local | L38: Local | M38: 165 | N38: 260 | O38: 0.3654 | Q38: =HYPERLINK("https://www.amazon.in/s?k="&SUBSTITUTE($D38," ","+"),"Amazon search") -> Amazon search | R38: 165 | S38: https://robu.in/product/mpu-6050-gyro-sensor-module/ | U38: =HYPERLINK("https://www.alibaba.com/trade/search?SearchText="&SUBSTITUTE($D38," ","+"),"Alibaba search") -> Alibaba search | W38: =HYPERLINK("https://www.lcsc.com/search?q="&SUBSTITUTE($D38," ","+"),"LCSC search") -> LCSC search | Y38: =HYPERLINK("https://www.mouser.in/c/?q="&SUBSTITUTE($D38," ","+"),"Mouser search") -> Mouser search | AA38: =HYPERLINK("https://www.digikey.in/en/products/filter?keywords="&SUBSTITUTE($D38," ","+"),"DigiKey search") -> DigiKey search | AC38: =Inputs_Assumptions!$B$7 -> 150 | AD38: =Inputs_Assumptions!$B$7 -> 150 | AE38: =Inputs_Assumptions!$B$5 -> 0.1 | AF38: =Inputs_Assumptions!$B$6 -> 0.18 | AG38: =Inputs_Assumptions!$B$4 -> 83 | AJ38: =IF(AH38<>"",(AH38*AG38+AD38)*(1+AE38)*(1+AF38),(M38+AD38)*(1+AF38)) -> 371.7 | AK38: =Inputs_Assumptions!$B$9 -> 0.35 | AL38: =IF(AJ38<>"",AJ38/(1-AK38),"") -> 571.84615 | AM38: =Inputs_Assumptions!$B$8 -> 0.18 | AN38: =IF(AND(P38<>"",AJ38<>"",AM38<>""),(P38-AJ38-P38*AM38)/P38,"") | AO38: A | AP38: 30 | AQ38: 30 | AR38: 60 | AS38: 9 | AU38: 2025-12-21 | AV38: Robu price incl GST. (2025-12-20) | AW38: 2025-12-20 | BC38: 2025-12-21 | BD38: MACFOS LIMITED (Robu.in) | BE38: https://robu.in/ | BF38: Survey No. 78/1, Sumant Building, Dynamic Logistics Trade Park, Dighi, Bhosari-Alandi Road, Pune, Maharashtra 411015, India | BG38: Phone: 1800 266 6123 / 020 6819 7600 ; Email: info@robu.in | BM38: 165 | BN38: Robu.in | BO38: https://robu.in/product/mpu-6050-gyro-sensor-module/ | BP38: MACFOS LIMITED (Robu.in) | BQ38: https://robu.in/ | BR38: Survey No. 78/1, Sumant Building, Dynamic Logistics Trade Park, Dighi, Bhosari-Alandi Road, Pune, Maharashtra 411015, India | BS38: Phone: 1800 266 6123 / 020 6819 7600 ; Email: info@robu.in | BT38: 2025-12-21 | BV38: Works (healthy margin). Gross≈26%. Est Amazon net≈8% after ~18% fees. | BW38: Amazon (as verified kit) + Direct (B2B) + IndiaMART; also Website/WhatsApp + LinkedIn outreach. | BX38: Add: essentials kit (cables/adapters) + quick‑start card + basic support + 7‑day DOA replacement. | BY38: Title: IMU MPU6050 Module | Verified/QA Tested | Quick‑Start + Support | GST Invoice Bullets: - Key specs: 6-axis IMU - Use case: Robotics - Pre‑tested unit with packaging QC sticker + photo proof before dispatch. - Support: setup guide (QR) + WhatsApp troubleshooting; replacement DOA policy. - Ideal for startups/labs/training centers; bulk pricing available. | BZ38: electronics module, dev kit, maker kit, embedded components | CA38: Day1–2 sample+QC | Day3 assets+pack insert QR | Day4 IndiaMART+WhatsApp catalog | Week1 Amazon (kit) | Week1–2 LinkedIn/B2B outreach | Week2 small ads + optimize | Bi‑weekly price recheck | CB38: Partial (needs sample + doc evidence) | CC38: Reseller / Marketplace Seller | CD38: https://robu.in/product/mpu-6050-gyro-sensor-module/ | CE38: Marketplace seller (badge depends on platform); prefer GST invoice + established store ratings. | CH38: Y | CI38: N | CJ38: 7 | CK38: Marketplace return policy; 7 days DOA replacement. | CL38: Domestic shipment (GST invoice preferred) | CM38: 30 days replacement for DOA. | CN38: Bangalore: 48–72 hrs replacement (stock permitting); else 7–14 days via supplier. | CO38: Y | CP38: MACFOS LIMITED (Robu.in) | CQ38: Robu.in | https://robu.in/product/mpu-6050-gyro-sensor-module/ | CR38: 2026-01-06 | CS38: Works (healthy margin). Gross≈26%. Est Amazon net≈8% after ~18% fees. | Channels: Amazon (as verified kit) + Direct (B2B) + IndiaMART; also Website/WhatsApp + LinkedIn outreach. | Bundle: Add: essentials kit (cables/adapters) + quick‑start card + basic support + 7‑day DOA replacement. | CT38: High | CU38: 39.4 | CV38: Demand 18.0/40 (units=9.0); Margin 0.3/30 (GM%=0.4); Channel 5.0/10 (AmazonNet%=NA); Sourcing 6.2/10 (mode=Local); Lead 10.0/10 (days=7.0); Fit 0.0/10; Penalty 0.0/10.
A39: SENS-ICM20948 | B39: Sensor | C39: Module | D39: IMU ICM20948 9-axis Module | E39: TDK/InvenSense | F39: ICM20948 | H39: 9-axis IMU | I39: Drones, robotics | J39: Startups | K39: Import | L39: Import | M39: 2459 | N39: 3790 | O39: 0.3512 | Q39: =HYPERLINK("https://www.amazon.in/s?k="&SUBSTITUTE($D39," ","+"),"Amazon search") -> Amazon search | R39: 2459 | S39: https://robu.in/product/sparkfun-9dof-imu-breakout-icm-20948-qwiic/ | U39: =HYPERLINK("https://www.alibaba.com/trade/search?SearchText="&SUBSTITUTE($D39," ","+"),"Alibaba search") -> Alibaba search | W39: =HYPERLINK("https://www.lcsc.com/search?q="&SUBSTITUTE($D39," ","+"),"LCSC search") -> LCSC search | Y39: =HYPERLINK("https://www.mouser.in/c/?q="&SUBSTITUTE($D39," ","+"),"Mouser search") -> Mouser search | AA39: =HYPERLINK("https://www.digikey.in/en/products/filter?keywords="&SUBSTITUTE($D39," ","+"),"DigiKey search") -> DigiKey search | AC39: =Inputs_Assumptions!$B$7 -> 150 | AD39: =Inputs_Assumptions!$B$7 -> 150 | AE39: =Inputs_Assumptions!$B$5 -> 0.1 | AF39: =Inputs_Assumptions!$B$6 -> 0.18 | AG39: =Inputs_Assumptions!$B$4 -> 83 | AJ39: =IF(AH39<>"",(AH39*AG39+AD39)*(1+AE39)*(1+AF39),(M39+AD39)*(1+AF39)) -> 3078.62 | AK39: =Inputs_Assumptions!$B$9 -> 0.35 | AL39: =IF(AJ39<>"",AJ39/(1-AK39),"") -> 4736.3385 | AM39: =Inputs_Assumptions!$B$8 -> 0.18 | AN39: =IF(AND(P39<>"",AJ39<>"",AM39<>""),(P39-AJ39-P39*AM39)/P39,"") | AO39: B | AQ39: 10 | AR39: 20 | AS39: 3 | AU39: 2025-12-21 | AW39: 2025-12-20 | BC39: 2025-12-21 | BD39: MACFOS LIMITED (Robu.in) | BE39: https://robu.in/ | BF39: Survey No. 78/1, Sumant Building, Dynamic Logistics Trade Park, Dighi, Bhosari-Alandi Road, Pune, Maharashtra 411015, India | BG39: Phone: 1800 266 6123 / 020 6819 7600 ; Email: info@robu.in | BM39: 2459 | BN39: Robu.in | BO39: https://robu.in/product/sparkfun-9dof-imu-breakout-icm-20948-qwiic/ | BP39: MACFOS LIMITED (Robu.in) | BQ39: https://robu.in/ | BR39: Survey No. 78/1, Sumant Building, Dynamic Logistics Trade Park, Dighi, Bhosari-Alandi Road, Pune, Maharashtra 411015, India | BS39: Phone: 1800 266 6123 / 020 6819 7600 ; Email: info@robu.in | BT39: 2025-12-21 | BU39: SparkFun breakout used. | BV39: Works (healthy margin). Gross≈28%. Est Amazon net≈10% after ~18% fees. | BW39: Amazon (as verified kit) + Direct (B2B) + IndiaMART; also Website/WhatsApp + LinkedIn outreach. | BX39: Add: essentials kit (cables/adapters) + quick‑start card + basic support + 7‑day DOA replacement. | BY39: Title: IMU ICM20948 9-axis Module | Verified/QA Tested | Quick‑Start + Support | GST Invoice Bullets: - Key specs: 9-axis IMU - Use case: Drones, robotics - Pre‑tested unit with packaging QC sticker + photo proof before dispatch. - Support: setup guide (QR) + WhatsApp troubleshooting; replacement DOA policy. - Ideal for startups/labs/training centers; bulk pricing available. | BZ39: electronics module, dev kit, maker kit, embedded components | CA39: Day1–2 sample+QC | Day3 assets+pack insert QR | Day4 IndiaMART+WhatsApp catalog | Week1 Amazon (kit) | Week1–2 LinkedIn/B2B outreach | Week2 small ads + optimize | Bi‑weekly price recheck | CB39: Partial (needs sample + doc evidence) | CC39: Reseller / Marketplace Seller | CD39: https://robu.in/product/sparkfun-9dof-imu-breakout-icm-20948-qwiic/ | CE39: Marketplace seller (badge depends on platform); prefer GST invoice + established store ratings. | CH39: Y | CI39: N | CJ39: 7 | CK39: Marketplace return policy; 7 days DOA replacement. | CL39: Domestic shipment (GST invoice preferred) | CM39: 30 days replacement for DOA. | CN39: Bangalore: 48–72 hrs replacement (stock permitting); else 7–14 days via supplier. | CO39: Y | CP39: MACFOS LIMITED (Robu.in) | CQ39: Robu.in | https://robu.in/product/sparkfun-9dof-imu-breakout-icm-20948-qwiic/ | CR39: 2026-01-06 | CS39: Works (healthy margin). Gross≈28%. Est Amazon net≈10% after ~18% fees. | Channels: Amazon (as verified kit) + Direct (B2B) + IndiaMART; also Website/WhatsApp + LinkedIn outreach. | Bundle: Add: essentials kit (cables/adapters) + quick‑start card + basic support + 7‑day DOA replacement. | CT39: Medium | CU39: 22.3 | CV39: Demand 6.0/40 (units=3.0); Margin 0.3/30 (GM%=0.4); Channel 5.0/10 (AmazonNet%=NA); Sourcing 0.0/10 (mode=Import); Lead 10.0/10 (days=7.0); Fit 6.0/10; Penalty 5.0/10.
A40: SENS-VL53L1X | B40: Sensor | C40: Module | D40: ToF Sensor VL53L1X Module | E40: STMicro | F40: VL53L1X | H40: Distance sensing | I40: Robotics | J40: Robotics startups | K40: Local | L40: Local | M40: 1506 | N40: 2320 | O40: 0.3509 | Q40: =HYPERLINK("https://www.amazon.in/s?k="&SUBSTITUTE($D40," ","+"),"Amazon search") -> Amazon search | R40: 1506 | S40: https://robu.in/product/waveshare-vl53l1x-tof-sensor-module-iv-measuring-range-4m/ | U40: =HYPERLINK("https://www.alibaba.com/trade/search?SearchText="&SUBSTITUTE($D40," ","+"),"Alibaba search") -> Alibaba search | W40: =HYPERLINK("https://www.lcsc.com/search?q="&SUBSTITUTE($D40," ","+"),"LCSC search") -> LCSC search | Y40: =HYPERLINK("https://www.mouser.in/c/?q="&SUBSTITUTE($D40," ","+"),"Mouser search") -> Mouser search | AA40: =HYPERLINK("https://www.digikey.in/en/products/filter?keywords="&SUBSTITUTE($D40," ","+"),"DigiKey search") -> DigiKey search | AC40: =Inputs_Assumptions!$B$7 -> 150 | AD40: =Inputs_Assumptions!$B$7 -> 150 | AE40: =Inputs_Assumptions!$B$5 -> 0.1 | AF40: =Inputs_Assumptions!$B$6 -> 0.18 | AG40: =Inputs_Assumptions!$B$4 -> 83 | AJ40: =IF(AH40<>"",(AH40*AG40+AD40)*(1+AE40)*(1+AF40),(M40+AD40)*(1+AF40)) -> 1954.08 | AK40: =Inputs_Assumptions!$B$9 -> 0.35 | AL40: =IF(AJ40<>"",AJ40/(1-AK40),"") -> 3006.2769 | AM40: =Inputs_Assumptions!$B$8 -> 0.18 | AN40: =IF(AND(P40<>"",AJ40<>"",AM40<>""),(P40-AJ40-P40*AM40)/P40,"") | AO40: B | AP40: 6 | AQ40: 6 | AR40: 12 | AS40: 2 | AU40: 2025-12-21 | AV40: Robu price for VL53L1X unit incl GST. (2025-12-20) | AW40: 2025-12-20 | BC40: 2025-12-21 | BD40: MACFOS LIMITED (Robu.in) | BE40: https://robu.in/ | BF40: Survey No. 78/1, Sumant Building, Dynamic Logistics Trade Park, Dighi, Bhosari-Alandi Road, Pune, Maharashtra 411015, India | BG40: Phone: 1800 266 6123 / 020 6819 7600 ; Email: info@robu.in | BM40: 1506 | BN40: Robu.in | BO40: https://robu.in/product/waveshare-vl53l1x-tof-sensor-module-iv-measuring-range-4m/ | BP40: MACFOS LIMITED (Robu.in) | BQ40: https://robu.in/ | BR40: Survey No. 78/1, Sumant Building, Dynamic Logistics Trade Park, Dighi, Bhosari-Alandi Road, Pune, Maharashtra 411015, India | BS40: Phone: 1800 266 6123 / 020 6819 7600 ; Email: info@robu.in | BT40: 2025-12-21 | BU40: Waveshare breakout price. | BV40: Works (healthy margin). Gross≈27%. Est Amazon net≈9% after ~18% fees. | BW40: Amazon (as verified kit) + Direct (B2B) + IndiaMART; also Website/WhatsApp + LinkedIn outreach. | BX40: Add: essentials kit (cables/adapters) + quick‑start card + basic support + 7‑day DOA replacement. | BY40: Title: ToF Sensor VL53L1X Module | Verified/QA Tested | Quick‑Start + Support | GST Invoice Bullets: - Key specs: Distance sensing - Use case: Robotics - Pre‑tested unit with packaging QC sticker + photo proof before dispatch. - Support: setup guide (QR) + WhatsApp troubleshooting; replacement DOA policy. - Ideal for startups/labs/training centers; bulk pricing available. | BZ40: electronics module, dev kit, maker kit, embedded components | CA40: Day1–2 sample+QC | Day3 assets+pack insert QR | Day4 IndiaMART+WhatsApp catalog | Week1 Amazon (kit) | Week1–2 LinkedIn/B2B outreach | Week2 small ads + optimize | Bi‑weekly price recheck | CB40: Partial (needs sample + doc evidence) | CC40: Reseller / Marketplace Seller | CD40: https://robu.in/product/waveshare-vl53l1x-tof-sensor-module-iv-measuring-range-4m/ | CE40: Marketplace seller (badge depends on platform); prefer GST invoice + established store ratings. | CH40: Y | CI40: N | CJ40: 7 | CK40: Marketplace return policy; 7 days DOA replacement. | CL40: Domestic shipment (GST invoice preferred) | CM40: 30 days replacement for DOA. | CN40: Bangalore: 48–72 hrs replacement (stock permitting); else 7–14 days via supplier. | CO40: Y | CP40: MACFOS LIMITED (Robu.in) | CQ40: Robu.in | https://robu.in/product/waveshare-vl53l1x-tof-sensor-module-iv-measuring-range-4m/ | CR40: 2026-01-06 | CS40: Works (healthy margin). Gross≈27%. Est Amazon net≈9% after ~18% fees. | Channels: Amazon (as verified kit) + Direct (B2B) + IndiaMART; also Website/WhatsApp + LinkedIn outreach. | Bundle: Add: essentials kit (cables/adapters) + quick‑start card + basic support + 7‑day DOA replacement. | CT40: Medium | CU40: 26.4 | CV40: Demand 4.0/40 (units=2.0); Margin 0.3/30 (GM%=0.4); Channel 5.0/10 (AmazonNet%=NA); Sourcing 6.2/10 (mode=Local); Lead 10.0/10 (days=7.0); Fit 6.0/10; Penalty 5.0/10.
A41: SENS-RPLIDAR-A1 | B41: Sensor | C41: Module | D41: LiDAR Module RPLIDAR A1 | E41: Slamtec | F41: RPLIDAR A1 | H41: 2D LiDAR | I41: SLAM robots | J41: Robotics startups | K41: Import | L41: Import | M41: 7926 | N41: 12200 | O41: 0.3503 | Q41: =HYPERLINK("https://www.amazon.in/s?k="&SUBSTITUTE($D41," ","+"),"Amazon search") -> Amazon search | R41: 7926 | S41: https://robu.in/product/rplidar-a1m8-360-degree-laser-range-scanner-development-kit/ | U41: =HYPERLINK("https://www.alibaba.com/trade/search?SearchText="&SUBSTITUTE($D41," ","+"),"Alibaba search") -> Alibaba search | W41: =HYPERLINK("https://www.lcsc.com/search?q="&SUBSTITUTE($D41," ","+"),"LCSC search") -> LCSC search | Y41: =HYPERLINK("https://www.mouser.in/c/?q="&SUBSTITUTE($D41," ","+"),"Mouser search") -> Mouser search | AA41: =HYPERLINK("https://www.digikey.in/en/products/filter?keywords="&SUBSTITUTE($D41," ","+"),"DigiKey search") -> DigiKey search | AC41: =Inputs_Assumptions!$B$7 -> 150 | AD41: =Inputs_Assumptions!$B$7 -> 150 | AE41: =Inputs_Assumptions!$B$5 -> 0.1 | AF41: =Inputs_Assumptions!$B$6 -> 0.18 | AG41: =Inputs_Assumptions!$B$4 -> 83 | AJ41: =IF(AH41<>"",(AH41*AG41+AD41)*(1+AE41)*(1+AF41),(M41+AD41)*(1+AF41)) -> 9529.68 | AK41: =Inputs_Assumptions!$B$9 -> 0.35 | AL41: =IF(AJ41<>"",AJ41/(1-AK41),"") -> 14661.046 | AM41: =Inputs_Assumptions!$B$8 -> 0.18 | AN41: =IF(AND(P41<>"",AJ41<>"",AM41<>""),(P41-AJ41-P41*AM41)/P41,"") | AO41: C | AQ41: 2 | AR41: 4 | AS41: 1 | AU41: 2025-12-21 | AW41: 2025-12-20 | BC41: 2025-12-21 | BD41: MACFOS LIMITED (Robu.in) | BE41: https://robu.in/ | BF41: Survey No. 78/1, Sumant Building, Dynamic Logistics Trade Park, Dighi, Bhosari-Alandi Road, Pune, Maharashtra 411015, India | BG41: Phone: 1800 266 6123 / 020 6819 7600 ; Email: info@robu.in | BM41: 7926 | BN41: Robu.in | BO41: https://robu.in/product/rplidar-a1m8-360-degree-laser-range-scanner-development-kit/ | BP41: MACFOS LIMITED (Robu.in) | BQ41: https://robu.in/ | BR41: Survey No. 78/1, Sumant Building, Dynamic Logistics Trade Park, Dighi, Bhosari-Alandi Road, Pune, Maharashtra 411015, India | BS41: Phone: 1800 266 6123 / 020 6819 7600 ; Email: info@robu.in | BT41: 2025-12-21 | BV41: Works (healthy margin). Gross≈28%. Est Amazon net≈10% after ~18% fees. | BW41: Amazon (as verified kit) + Direct (B2B) + IndiaMART; also Website/WhatsApp + LinkedIn outreach. | BX41: Add: essentials kit (cables/adapters) + quick‑start card + basic support + 7‑day DOA replacement. | BY41: Title: LiDAR Module RPLIDAR A1 | Verified/QA Tested | Quick‑Start + Support | GST Invoice Bullets: - Key specs: 2D LiDAR - Use case: SLAM robots - Pre‑tested unit with packaging QC sticker + photo proof before dispatch. - Support: setup guide (QR) + WhatsApp troubleshooting; replacement DOA policy. - Ideal for startups/labs/training centers; bulk pricing available. | BZ41: electronics module, dev kit, maker kit, embedded components | CA41: Day1–2 sample+QC | Day3 assets+pack insert QR | Day4 IndiaMART+WhatsApp catalog | Week1 Amazon (kit) | Week1–2 LinkedIn/B2B outreach | Week2 small ads + optimize | Bi‑weekly price recheck | CB41: Partial (needs sample + doc evidence) | CC41: Reseller / Marketplace Seller | CD41: https://robu.in/product/rplidar-a1m8-360-degree-laser-range-scanner-development-kit/ | CE41: Marketplace seller (badge depends on platform); prefer GST invoice + established store ratings. | CH41: Y | CI41: N | CJ41: 7 | CK41: Marketplace return policy; 7 days DOA replacement. | CL41: Domestic shipment (GST invoice preferred) | CM41: 30 days replacement for DOA. | CN41: Bangalore: 48–72 hrs replacement (stock permitting); else 7–14 days via supplier. | CO41: Y | CP41: MACFOS LIMITED (Robu.in) | CQ41: Robu.in | https://robu.in/product/rplidar-a1m8-360-degree-laser-range-scanner-development-kit/ | CR41: 2026-01-06 | CS41: Works (healthy margin). Gross≈28%. Est Amazon net≈10% after ~18% fees. | Channels: Amazon (as verified kit) + Direct (B2B) + IndiaMART; also Website/WhatsApp + LinkedIn outreach. | Bundle: Add: essentials kit (cables/adapters) + quick‑start card + basic support + 7‑day DOA replacement. | CT41: Low | CU41: 18.3 | CV41: Demand 2.0/40 (units=1.0); Margin 0.3/30 (GM%=0.4); Channel 5.0/10 (AmazonNet%=NA); Sourcing 0.0/10 (mode=Import); Lead 10.0/10 (days=7.0); Fit 6.0/10; Penalty 5.0/10.
A42: SENS-GPS-NEO6M | B42: Sensor | C42: Module | D42: GPS Module NEO-6M | E42: u-blox | F42: NEO-6M | H42: GPS/GNSS | I42: Drones/Tracking | J42: Startups, makers | K42: Local | L42: Local | M42: 239 | N42: 370 | O42: 0.3541 | Q42: =HYPERLINK("https://www.amazon.in/s?k="&SUBSTITUTE($D42," ","+"),"Amazon search") -> Amazon search | R42: 239 | S42: https://robu.in/product/neo-6m-gps-module/ | U42: =HYPERLINK("https://www.alibaba.com/trade/search?SearchText="&SUBSTITUTE($D42," ","+"),"Alibaba search") -> Alibaba search | W42: =HYPERLINK("https://www.lcsc.com/search?q="&SUBSTITUTE($D42," ","+"),"LCSC search") -> LCSC search | Y42: =HYPERLINK("https://www.mouser.in/c/?q="&SUBSTITUTE($D42," ","+"),"Mouser search") -> Mouser search | AA42: =HYPERLINK("https://www.digikey.in/en/products/filter?keywords="&SUBSTITUTE($D42," ","+"),"DigiKey search") -> DigiKey search | AC42: =Inputs_Assumptions!$B$7 -> 150 | AD42: =Inputs_Assumptions!$B$7 -> 150 | AE42: =Inputs_Assumptions!$B$5 -> 0.1 | AF42: =Inputs_Assumptions!$B$6 -> 0.18 | AG42: =Inputs_Assumptions!$B$4 -> 83 | AJ42: =IF(AH42<>"",(AH42*AG42+AD42)*(1+AE42)*(1+AF42),(M42+AD42)*(1+AF42)) -> 459.02 | AK42: =Inputs_Assumptions!$B$9 -> 0.35 | AL42: =IF(AJ42<>"",AJ42/(1-AK42),"") -> 706.18462 | AM42: =Inputs_Assumptions!$B$8 -> 0.18 | AN42: =IF(AND(P42<>"",AJ42<>"",AM42<>""),(P42-AJ42-P42*AM42)/P42,"") | AO42: B | AP42: 6 | AQ42: 6 | AR42: 12 | AS42: 2 | AU42: 2025-12-21 | AW42: 2025-12-20 | BC42: 2025-12-21 | BD42: MACFOS LIMITED (Robu.in) | BE42: https://robu.in/ | BF42: Survey No. 78/1, Sumant Building, Dynamic Logistics Trade Park, Dighi, Bhosari-Alandi Road, Pune, Maharashtra 411015, India | BG42: Phone: 1800 266 6123 / 020 6819 7600 ; Email: info@robu.in | BM42: 239 | BN42: Robu.in | BO42: https://robu.in/product/neo-6m-gps-module/ | BP42: MACFOS LIMITED (Robu.in) | BQ42: https://robu.in/ | BR42: Survey No. 78/1, Sumant Building, Dynamic Logistics Trade Park, Dighi, Bhosari-Alandi Road, Pune, Maharashtra 411015, India | BS42: Phone: 1800 266 6123 / 020 6819 7600 ; Email: info@robu.in | BT42: 2025-12-21 | BV42: Works (healthy margin). Gross≈26%. Est Amazon net≈8% after ~18% fees. | BW42: Amazon (as verified kit) + Direct (B2B) + IndiaMART; also Website/WhatsApp + LinkedIn outreach. | BX42: Add: essentials kit (cables/adapters) + quick‑start card + basic support + 7‑day DOA replacement. | BY42: Title: GPS Module NEO-6M | Verified/QA Tested | Quick‑Start + Support | GST Invoice Bullets: - Key specs: GPS/GNSS - Use case: Drones/Tracking - Pre‑tested unit with packaging QC sticker + photo proof before dispatch. - Support: setup guide (QR) + WhatsApp troubleshooting; replacement DOA policy. - Ideal for startups/labs/training centers; bulk pricing available. | BZ42: electronics module, dev kit, maker kit, embedded components | CA42: Day1–2 sample+QC | Day3 assets+pack insert QR | Day4 IndiaMART+WhatsApp catalog | Week1 Amazon (kit) | Week1–2 LinkedIn/B2B outreach | Week2 small ads + optimize | Bi‑weekly price recheck | CB42: Partial (needs sample + doc evidence) | CC42: Reseller / Marketplace Seller | CD42: https://robu.in/product/neo-6m-gps-module/ | CE42: Marketplace seller (badge depends on platform); prefer GST invoice + established store ratings. | CH42: Y | CI42: N | CJ42: 7 | CK42: Marketplace return policy; 7 days DOA replacement. | CL42: Domestic shipment (GST invoice preferred) | CM42: 30 days replacement for DOA. | CN42: Bangalore: 48–72 hrs replacement (stock permitting); else 7–14 days via supplier. | CO42: Y | CP42: MACFOS LIMITED (Robu.in) | CQ42: Robu.in | https://robu.in/product/neo-6m-gps-module/ | CR42: 2026-01-06 | CS42: Works (healthy margin). Gross≈26%. Est Amazon net≈8% after ~18% fees. | Channels: Amazon (as verified kit) + Direct (B2B) + IndiaMART; also Website/WhatsApp + LinkedIn outreach. | Bundle: Add: essentials kit (cables/adapters) + quick‑start card + basic support + 7‑day DOA replacement. | CT42: Medium | CU42: 26.4 | CV42: Demand 4.0/40 (units=2.0); Margin 0.3/30 (GM%=0.4); Channel 5.0/10 (AmazonNet%=NA); Sourcing 6.2/10 (mode=Local); Lead 10.0/10 (days=7.0); Fit 6.0/10; Penalty 5.0/10.
A43: SENS-BMP280 | B43: Sensor | C43: Module | D43: Pressure Sensor BMP280 | E43: Bosch | F43: BMP280 | H43: Pressure/Temp | I43: IoT weather | J43: Students | K43: Local | L43: Local | M43: 29 | N43: 50 | O43: 0.42 | Q43: =HYPERLINK("https://www.amazon.in/s?k="&SUBSTITUTE($D43," ","+"),"Amazon search") -> Amazon search | R43: 29 | S43: https://robu.in/product/bmp280-barometric-pressure-sensor-module/ | U43: =HYPERLINK("https://www.alibaba.com/trade/search?SearchText="&SUBSTITUTE($D43," ","+"),"Alibaba search") -> Alibaba search | W43: =HYPERLINK("https://www.lcsc.com/search?q="&SUBSTITUTE($D43," ","+"),"LCSC search") -> LCSC search | Y43: =HYPERLINK("https://www.mouser.in/c/?q="&SUBSTITUTE($D43," ","+"),"Mouser search") -> Mouser search | AA43: =HYPERLINK("https://www.digikey.in/en/products/filter?keywords="&SUBSTITUTE($D43," ","+"),"DigiKey search") -> DigiKey search | AC43: =Inputs_Assumptions!$B$7 -> 150 | AD43: =Inputs_Assumptions!$B$7 -> 150 | AE43: =Inputs_Assumptions!$B$5 -> 0.1 | AF43: =Inputs_Assumptions!$B$6 -> 0.18 | AG43: =Inputs_Assumptions!$B$4 -> 83 | AJ43: =IF(AH43<>"",(AH43*AG43+AD43)*(1+AE43)*(1+AF43),(M43+AD43)*(1+AF43)) -> 211.22 | AK43: =Inputs_Assumptions!$B$9 -> 0.35 | AL43: =IF(AJ43<>"",AJ43/(1-AK43),"") -> 324.95385 | AM43: =Inputs_Assumptions!$B$8 -> 0.18 | AN43: =IF(AND(P43<>"",AJ43<>"",AM43<>""),(P43-AJ43-P43*AM43)/P43,"") | AO43: B | AU43: 2025-12-21 | AW43: 2025-12-20 | BC43: 2025-12-21 | BD43: MACFOS LIMITED (Robu.in) | BE43: https://robu.in/ | BF43: Survey No. 78/1, Sumant Building, Dynamic Logistics Trade Park, Dighi, Bhosari-Alandi Road, Pune, Maharashtra 411015, India | BG43: Phone: 1800 266 6123 / 020 6819 7600 ; Email: info@robu.in | BM43: 29 | BN43: Robu.in | BO43: https://robu.in/product/bmp280-barometric-pressure-sensor-module/ | BP43: MACFOS LIMITED (Robu.in) | BQ43: https://robu.in/ | BR43: Survey No. 78/1, Sumant Building, Dynamic Logistics Trade Park, Dighi, Bhosari-Alandi Road, Pune, Maharashtra 411015, India | BS43: Phone: 1800 266 6123 / 020 6819 7600 ; Email: info@robu.in | BT43: 2025-12-21 | BV43: Works for Direct/B2B; marketplaces need bundle/price-up. Gross≈20%. Est Amazon net≈2% after ~18% fees. | BW43: Direct (B2B) + IndiaMART; Amazon only if bundled/priced higher. | BX43: Add: essentials kit (cables/adapters) + quick‑start card + basic support + 7‑day DOA replacement. | BY43: Title: Pressure Sensor BMP280 | Verified/QA Tested | Quick‑Start + Support | GST Invoice Bullets: - Key specs: Pressure/Temp - Use case: IoT weather - Pre‑tested unit with packaging QC sticker + photo proof before dispatch. - Support: setup guide (QR) + WhatsApp troubleshooting; replacement DOA policy. - Ideal for startups/labs/training centers; bulk pricing available. | BZ43: electronics module, dev kit, maker kit, embedded components | CA43: Day1–2 sample+QC | Day3 assets+pack insert QR | Day4 IndiaMART+WhatsApp catalog | Week1 Amazon (kit) | Week1–2 LinkedIn/B2B outreach | Week2 small ads + optimize | Bi‑weekly price recheck | CB43: Partial (needs sample + doc evidence) | CC43: Reseller / Marketplace Seller | CD43: https://robu.in/product/bmp280-barometric-pressure-sensor-module/ | CE43: Marketplace seller (badge depends on platform); prefer GST invoice + established store ratings. | CH43: Y | CI43: N | CJ43: 7 | CK43: Marketplace return policy; 7 days DOA replacement. | CL43: Domestic shipment (GST invoice preferred) | CM43: 30 days replacement for DOA. | CN43: Bangalore: 48–72 hrs replacement (stock permitting); else 7–14 days via supplier. | CO43: Y | CP43: MACFOS LIMITED (Robu.in) | CQ43: Robu.in | https://robu.in/product/bmp280-barometric-pressure-sensor-module/ | CR43: 2026-01-06 | CS43: Works for Direct/B2B; marketplaces need bundle/price-up. Gross≈20%. Est Amazon net≈2% after ~18% fees. | Channels: Direct (B2B) + IndiaMART; Amazon only if bundled/priced higher. | Bundle: Add: essentials kit (cables/adapters) + quick‑start card + basic support + 7‑day DOA replacement. | CT43: Medium | CU43: 21.5 | CV43: Demand 0.0/40 (units=0.0); Margin 0.3/30 (GM%=0.4); Channel 5.0/10 (AmazonNet%=NA); Sourcing 6.2/10 (mode=Local); Lead 10.0/10 (days=7.0); Fit 0.0/10; Penalty 0.0/10.
A44: SENS-HCSR04 | B44: Sensor | C44: Module | D44: Ultrasonic HC-SR04 | E44: Generic | F44: HC-SR04 | H44: Distance sensor | I44: Robotics | J44: Students | K44: Local | L44: Local | M44: 59 | N44: 100 | O44: 0.41 | Q44: =HYPERLINK("https://www.amazon.in/s?k="&SUBSTITUTE($D44," ","+"),"Amazon search") -> Amazon search | R44: 59 | S44: https://robu.in/product/ultrasonic-sensor-module-hc-sr04/ | U44: =HYPERLINK("https://www.alibaba.com/trade/search?SearchText="&SUBSTITUTE($D44," ","+"),"Alibaba search") -> Alibaba search | W44: =HYPERLINK("https://www.lcsc.com/search?q="&SUBSTITUTE($D44," ","+"),"LCSC search") -> LCSC search | Y44: =HYPERLINK("https://www.mouser.in/c/?q="&SUBSTITUTE($D44," ","+"),"Mouser search") -> Mouser search | AA44: =HYPERLINK("https://www.digikey.in/en/products/filter?keywords="&SUBSTITUTE($D44," ","+"),"DigiKey search") -> DigiKey search | AC44: =Inputs_Assumptions!$B$7 -> 150 | AD44: =Inputs_Assumptions!$B$7 -> 150 | AE44: =Inputs_Assumptions!$B$5 -> 0.1 | AF44: =Inputs_Assumptions!$B$6 -> 0.18 | AG44: =Inputs_Assumptions!$B$4 -> 83 | AJ44: =IF(AH44<>"",(AH44*AG44+AD44)*(1+AE44)*(1+AF44),(M44+AD44)*(1+AF44)) -> 246.62 | AK44: =Inputs_Assumptions!$B$9 -> 0.35 | AL44: =IF(AJ44<>"",AJ44/(1-AK44),"") -> 379.41538 | AM44: =Inputs_Assumptions!$B$8 -> 0.18 | AN44: =IF(AND(P44<>"",AJ44<>"",AM44<>""),(P44-AJ44-P44*AM44)/P44,"") | AO44: A | AP44: 20 | AQ44: 20 | AR44: 40 | AS44: 6 | AU44: 2025-12-21 | AW44: 2025-12-20 | BC44: 2025-12-21 | BD44: MACFOS LIMITED (Robu.in) | BE44: https://robu.in/ | BF44: Survey No. 78/1, Sumant Building, Dynamic Logistics Trade Park, Dighi, Bhosari-Alandi Road, Pune, Maharashtra 411015, India | BG44: Phone: 1800 266 6123 / 020 6819 7600 ; Email: info@robu.in | BM44: 59 | BN44: Robu.in | BO44: https://robu.in/product/ultrasonic-sensor-module-hc-sr04/ | BP44: MACFOS LIMITED (Robu.in) | BQ44: https://robu.in/ | BR44: Survey No. 78/1, Sumant Building, Dynamic Logistics Trade Park, Dighi, Bhosari-Alandi Road, Pune, Maharashtra 411015, India | BS44: Phone: 1800 266 6123 / 020 6819 7600 ; Email: info@robu.in | BT44: 2025-12-21 | BU44: Price from category/listing; verify on product page. | BV44: Works (healthy margin). Gross≈27%. Est Amazon net≈9% after ~18% fees. | BW44: Amazon (as verified kit) + Direct (B2B) + IndiaMART; also Website/WhatsApp + LinkedIn outreach. | BX44: Add: essentials kit (cables/adapters) + quick‑start card + basic support + 7‑day DOA replacement. | BY44: Title: Ultrasonic HC-SR04 | Verified/QA Tested | Quick‑Start + Support | GST Invoice Bullets: - Key specs: Distance sensor - Use case: Robotics - Pre‑tested unit with packaging QC sticker + photo proof before dispatch. - Support: setup guide (QR) + WhatsApp troubleshooting; replacement DOA policy. - Ideal for startups/labs/training centers; bulk pricing available. | BZ44: electronics module, dev kit, maker kit, embedded components | CA44: Day1–2 sample+QC | Day3 assets+pack insert QR | Day4 IndiaMART+WhatsApp catalog | Week1 Amazon (kit) | Week1–2 LinkedIn/B2B outreach | Week2 small ads + optimize | Bi‑weekly price recheck | CB44: Partial (needs sample + doc evidence) | CC44: Reseller / Marketplace Seller | CD44: https://robu.in/product/ultrasonic-sensor-module-hc-sr04/ | CE44: Marketplace seller (badge depends on platform); prefer GST invoice + established store ratings. | CH44: Y | CI44: N | CJ44: 7 | CK44: Marketplace return policy; 7 days DOA replacement. | CL44: Domestic shipment (GST invoice preferred) | CM44: 30 days replacement for DOA. | CN44: Bangalore: 48–72 hrs replacement (stock permitting); else 7–14 days via supplier. | CO44: Y | CP44: MACFOS LIMITED (Robu.in) | CQ44: Robu.in | https://robu.in/product/ultrasonic-sensor-module-hc-sr04/ | CR44: 2026-01-06 | CS44: Works (healthy margin). Gross≈27%. Est Amazon net≈9% after ~18% fees. | Channels: Amazon (as verified kit) + Direct (B2B) + IndiaMART; also Website/WhatsApp + LinkedIn outreach. | Bundle: Add: essentials kit (cables/adapters) + quick‑start card + basic support + 7‑day DOA replacement. | CT44: High | CU44: 33.5 | CV44: Demand 12.0/40 (units=6.0); Margin 0.3/30 (GM%=0.4); Channel 5.0/10 (AmazonNet%=NA); Sourcing 6.2/10 (mode=Local); Lead 10.0/10 (days=7.0); Fit 0.0/10; Penalty 0.0/10.
A45: MCU-ESP32 | B45: Microcontroller | C45: Board | D45: ESP32 DevKit | E45: Espressif | F45: ESP32-WROOM | G45: WROOM-32 | H45: WiFi/BT MCU | I45: IoT edge | J45: Students, startups | K45: Local | L45: Local | M45: 339 | N45: 530 | O45: 0.3604 | Q45: =HYPERLINK("https://www.amazon.in/s?k="&SUBSTITUTE($D45," ","+"),"Amazon search") -> Amazon search | R45: 339 | S45: https://robu.in/product/esp32-38pin-development-board/ | U45: =HYPERLINK("https://www.alibaba.com/trade/search?SearchText="&SUBSTITUTE($D45," ","+"),"Alibaba search") -> Alibaba search | W45: =HYPERLINK("https://www.lcsc.com/search?q="&SUBSTITUTE($D45," ","+"),"LCSC search") -> LCSC search | Y45: =HYPERLINK("https://www.mouser.in/c/?q="&SUBSTITUTE($D45," ","+"),"Mouser search") -> Mouser search | AA45: =HYPERLINK("https://www.digikey.in/en/products/filter?keywords="&SUBSTITUTE($D45," ","+"),"DigiKey search") -> DigiKey search | AC45: =Inputs_Assumptions!$B$7 -> 150 | AD45: =Inputs_Assumptions!$B$7 -> 150 | AE45: =Inputs_Assumptions!$B$5 -> 0.1 | AF45: =Inputs_Assumptions!$B$6 -> 0.18 | AG45: =Inputs_Assumptions!$B$4 -> 83 | AJ45: =IF(AH45<>"",(AH45*AG45+AD45)*(1+AE45)*(1+AF45),(M45+AD45)*(1+AF45)) -> 577.02 | AK45: =Inputs_Assumptions!$B$9 -> 0.35 | AL45: =IF(AJ45<>"",AJ45/(1-AK45),"") -> 887.72308 | AM45: =Inputs_Assumptions!$B$8 -> 0.18 | AN45: =IF(AND(P45<>"",AJ45<>"",AM45<>""),(P45-AJ45-P45*AM45)/P45,"") | AO45: A | AP45: 20 | AQ45: 20 | AR45: 40 | AS45: 6 | AU45: 2025-12-21 | AV45: Robu price incl GST. (2025-12-20) | AW45: 2025-12-20 | BC45: 2025-12-21 | BD45: MACFOS LIMITED (Robu.in) | BE45: https://robu.in/ | BF45: Survey No. 78/1, Sumant Building, Dynamic Logistics Trade Park, Dighi, Bhosari-Alandi Road, Pune, Maharashtra 411015, India | BG45: Phone: 1800 266 6123 / 020 6819 7600 ; Email: info@robu.in | BM45: 339 | BN45: Robu.in | BO45: https://robu.in/product/esp32-38pin-development-board/ | BP45: MACFOS LIMITED (Robu.in) | BQ45: https://robu.in/ | BR45: Survey No. 78/1, Sumant Building, Dynamic Logistics Trade Park, Dighi, Bhosari-Alandi Road, Pune, Maharashtra 411015, India | BS45: Phone: 1800 266 6123 / 020 6819 7600 ; Email: info@robu.in | BT45: 2025-12-21 | BV45: Works (healthy margin). Gross≈27%. Est Amazon net≈9% after ~18% fees. | BW45: Amazon (as verified kit) + Direct (B2B) + IndiaMART; also Website/WhatsApp + LinkedIn outreach. | BX45: Add: essentials kit (cables/adapters) + quick‑start card + basic support + 7‑day DOA replacement. | BY45: Title: ESP32 DevKit | Verified/QA Tested | Quick‑Start + Support | GST Invoice Bullets: - Key specs: WiFi/BT MCU - Use case: IoT edge - Pre‑tested unit with packaging QC sticker + photo proof before dispatch. - Support: setup guide (QR) + WhatsApp troubleshooting; replacement DOA policy. - Ideal for startups/labs/training centers; bulk pricing available. | BZ45: electronics module, dev kit, maker kit, embedded components | CA45: Day1–2 sample+QC | Day3 assets+pack insert QR | Day4 IndiaMART+WhatsApp catalog | Week1 Amazon (kit) | Week1–2 LinkedIn/B2B outreach | Week2 small ads + optimize | Bi‑weekly price recheck | CB45: Partial (needs sample + doc evidence) | CC45: Reseller / Marketplace Seller | CD45: https://robu.in/product/esp32-38pin-development-board/ | CE45: Marketplace seller (badge depends on platform); prefer GST invoice + established store ratings. | CH45: Y | CI45: N | CJ45: 7 | CK45: 7 days DOA replacement; channel return policy applies. | CL45: Domestic shipment (GST invoice preferred) | CM45: 3 months replacement for functional failure (conditions apply). | CN45: Bangalore: 48–72 hrs replacement (stock permitting); else 7–14 days via supplier. | CO45: Y | CP45: MACFOS LIMITED (Robu.in) | CQ45: Robu.in | https://robu.in/product/esp32-38pin-development-board/ | CR45: 2026-01-06 | CS45: Works (healthy margin). Gross≈27%. Est Amazon net≈9% after ~18% fees. | Channels: Amazon (as verified kit) + Direct (B2B) + IndiaMART; also Website/WhatsApp + LinkedIn outreach. | Bundle: Add: essentials kit (cables/adapters) + quick‑start card + basic support + 7‑day DOA replacement. | CT45: High | CU45: 39.4 | CV45: Demand 12.0/40 (units=6.0); Margin 0.3/30 (GM%=0.4); Channel 5.0/10 (AmazonNet%=NA); Sourcing 6.2/10 (mode=Local); Lead 10.0/10 (days=7.0); Fit 6.0/10; Penalty 0.0/10.
A46: MCU-STM32F401 | B46: Microcontroller | C46: Board | D46: STM32F401 Dev Board | E46: STMicro | F46: STM32F401 | G46: Black Pill | H46: Cortex-M4 | I46: Control, DSP | J46: Students, startups | K46: Local | L46: Local | M46: 284 | N46: 440 | O46: 0.3545 | Q46: =HYPERLINK("https://www.amazon.in/s?k="&SUBSTITUTE($D46," ","+"),"Amazon search") -> Amazon search | R46: 284 | S46: https://robu.in/product/weact-black-pill-v2-0-stm32f401ccu6-development-board/ | U46: =HYPERLINK("https://www.alibaba.com/trade/search?SearchText="&SUBSTITUTE($D46," ","+"),"Alibaba search") -> Alibaba search | W46: =HYPERLINK("https://www.lcsc.com/search?q="&SUBSTITUTE($D46," ","+"),"LCSC search") -> LCSC search | Y46: =HYPERLINK("https://www.mouser.in/c/?q="&SUBSTITUTE($D46," ","+"),"Mouser search") -> Mouser search | AA46: =HYPERLINK("https://www.digikey.in/en/products/filter?keywords="&SUBSTITUTE($D46," ","+"),"DigiKey search") -> DigiKey search | AC46: =Inputs_Assumptions!$B$7 -> 150 | AD46: =Inputs_Assumptions!$B$7 -> 150 | AE46: =Inputs_Assumptions!$B$5 -> 0.1 | AF46: =Inputs_Assumptions!$B$6 -> 0.18 | AG46: =Inputs_Assumptions!$B$4 -> 83 | AJ46: =IF(AH46<>"",(AH46*AG46+AD46)*(1+AE46)*(1+AF46),(M46+AD46)*(1+AF46)) -> 512.12 | AK46: =Inputs_Assumptions!$B$9 -> 0.35 | AL46: =IF(AJ46<>"",AJ46/(1-AK46),"") -> 787.87692 | AM46: =Inputs_Assumptions!$B$8 -> 0.18 | AN46: =IF(AND(P46<>"",AJ46<>"",AM46<>""),(P46-AJ46-P46*AM46)/P46,"") | AO46: A | AP46: 10 | AQ46: 10 | AR46: 20 | AS46: 3 | AU46: 2025-12-21 | AW46: 2025-12-20 | BC46: 2025-12-21 | BD46: MACFOS LIMITED (Robu.in) | BE46: https://robu.in/ | BF46: Survey No. 78/1, Sumant Building, Dynamic Logistics Trade Park, Dighi, Bhosari-Alandi Road, Pune, Maharashtra 411015, India | BG46: Phone: 1800 266 6123 / 020 6819 7600 ; Email: info@robu.in | BM46: 284 | BN46: Robu.in | BO46: https://robu.in/product/weact-black-pill-v2-0-stm32f401ccu6-development-board/ | BP46: MACFOS LIMITED (Robu.in) | BQ46: https://robu.in/ | BR46: Survey No. 78/1, Sumant Building, Dynamic Logistics Trade Park, Dighi, Bhosari-Alandi Road, Pune, Maharashtra 411015, India | BS46: Phone: 1800 266 6123 / 020 6819 7600 ; Email: info@robu.in | BT46: 2025-12-21 | BV46: Works (healthy margin). Gross≈26%. Est Amazon net≈8% after ~18% fees. | BW46: Amazon (as verified kit) + Direct (B2B) + IndiaMART; also Website/WhatsApp + LinkedIn outreach. | BX46: Add: essentials kit (cables/adapters) + quick‑start card + basic support + 7‑day DOA replacement. | BY46: Title: STM32F401 Dev Board | Verified/QA Tested | Quick‑Start + Support | GST Invoice Bullets: - Key specs: Cortex-M4 - Use case: Control, DSP - Pre‑tested unit with packaging QC sticker + photo proof before dispatch. - Support: setup guide (QR) + WhatsApp troubleshooting; replacement DOA policy. - Ideal for startups/labs/training centers; bulk pricing available. | BZ46: electronics module, dev kit, maker kit, embedded components | CA46: Day1–2 sample+QC | Day3 assets+pack insert QR | Day4 IndiaMART+WhatsApp catalog | Week1 Amazon (kit) | Week1–2 LinkedIn/B2B outreach | Week2 small ads + optimize | Bi‑weekly price recheck | CB46: Partial (needs sample + doc evidence) | CC46: Reseller / Marketplace Seller | CD46: https://robu.in/product/weact-black-pill-v2-0-stm32f401ccu6-development-board/ | CE46: Marketplace seller (badge depends on platform); prefer GST invoice + established store ratings. | CH46: Y | CI46: N | CJ46: 7 | CK46: 7 days DOA replacement; unopened returns as per channel policy. | CL46: Domestic shipment (GST invoice preferred) | CM46: 3 months (board functional; no over-voltage/ESD damage). | CN46: Bangalore: 48–72 hrs replacement (stock permitting); else 7–14 days via supplier. | CO46: Y | CP46: MACFOS LIMITED (Robu.in) | CQ46: Robu.in | https://robu.in/product/weact-black-pill-v2-0-stm32f401ccu6-development-board/ | CR46: 2026-01-06 | CS46: Works (healthy margin). Gross≈26%. Est Amazon net≈8% after ~18% fees. | Channels: Amazon (as verified kit) + Direct (B2B) + IndiaMART; also Website/WhatsApp + LinkedIn outreach. | Bundle: Add: essentials kit (cables/adapters) + quick‑start card + basic support + 7‑day DOA replacement. | CT46: High | CU46: 33.4 | CV46: Demand 6.0/40 (units=3.0); Margin 0.3/30 (GM%=0.4); Channel 5.0/10 (AmazonNet%=NA); Sourcing 6.2/10 (mode=Local); Lead 10.0/10 (days=7.0); Fit 6.0/10; Penalty 0.0/10.
A47: MCU-RP2040-PICO | B47: Microcontroller | C47: Board | D47: Raspberry Pi Pico | E47: Raspberry Pi | F47: RP2040 | G47: Pico | H47: Dual-core MCU | I47: Education | J47: Students | K47: Local | L47: Local | M47: 359 | N47: 560 | O47: 0.3589 | Q47: =HYPERLINK("https://www.amazon.in/s?k="&SUBSTITUTE($D47," ","+"),"Amazon search") -> Amazon search | R47: 359 | S47: https://robu.in/product/raspberry-pi-pico/ | U47: =HYPERLINK("https://www.alibaba.com/trade/search?SearchText="&SUBSTITUTE($D47," ","+"),"Alibaba search") -> Alibaba search | W47: =HYPERLINK("https://www.lcsc.com/search?q="&SUBSTITUTE($D47," ","+"),"LCSC search") -> LCSC search | Y47: =HYPERLINK("https://www.mouser.in/c/?q="&SUBSTITUTE($D47," ","+"),"Mouser search") -> Mouser search | AA47: =HYPERLINK("https://www.digikey.in/en/products/filter?keywords="&SUBSTITUTE($D47," ","+"),"DigiKey search") -> DigiKey search | AC47: =Inputs_Assumptions!$B$7 -> 150 | AD47: =Inputs_Assumptions!$B$7 -> 150 | AE47: =Inputs_Assumptions!$B$5 -> 0.1 | AF47: =Inputs_Assumptions!$B$6 -> 0.18 | AG47: =Inputs_Assumptions!$B$4 -> 83 | AJ47: =IF(AH47<>"",(AH47*AG47+AD47)*(1+AE47)*(1+AF47),(M47+AD47)*(1+AF47)) -> 600.62 | AK47: =Inputs_Assumptions!$B$9 -> 0.35 | AL47: =IF(AJ47<>"",AJ47/(1-AK47),"") -> 924.03077 | AM47: =Inputs_Assumptions!$B$8 -> 0.18 | AN47: =IF(AND(P47<>"",AJ47<>"",AM47<>""),(P47-AJ47-P47*AM47)/P47,"") | AO47: B | AP47: 10 | AQ47: 10 | AR47: 20 | AS47: 3 | AU47: 2025-12-21 | AV47: Robu price incl GST. (2025-12-20) | AW47: 2025-12-20 | BC47: 2025-12-21 | BD47: MACFOS LIMITED (Robu.in) | BE47: https://robu.in/ | BF47: Survey No. 78/1, Sumant Building, Dynamic Logistics Trade Park, Dighi, Bhosari-Alandi Road, Pune, Maharashtra 411015, India | BG47: Phone: 1800 266 6123 / 020 6819 7600 ; Email: info@robu.in | BM47: 359 | BN47: Robu.in | BO47: https://robu.in/product/raspberry-pi-pico/ | BP47: MACFOS LIMITED (Robu.in) | BQ47: https://robu.in/ | BR47: Survey No. 78/1, Sumant Building, Dynamic Logistics Trade Park, Dighi, Bhosari-Alandi Road, Pune, Maharashtra 411015, India | BS47: Phone: 1800 266 6123 / 020 6819 7600 ; Email: info@robu.in | BT47: 2025-12-21 | BV47: Works (healthy margin). Gross≈27%. Est Amazon net≈9% after ~18% fees. | BW47: Amazon (as verified kit) + Direct (B2B) + IndiaMART; also Website/WhatsApp + LinkedIn outreach. | BX47: Add: essentials kit (cables/adapters) + quick‑start card + basic support + 7‑day DOA replacement. | BY47: Title: Raspberry Pi Pico | Verified/QA Tested | Quick‑Start + Support | GST Invoice Bullets: - Key specs: Dual-core MCU - Use case: Education - Pre‑tested unit with packaging QC sticker + photo proof before dispatch. - Support: setup guide (QR) + WhatsApp troubleshooting; replacement DOA policy. - Ideal for startups/labs/training centers; bulk pricing available. | BZ47: electronics module, dev kit, maker kit, embedded components | CA47: Day1–2 sample+QC | Day3 assets+pack insert QR | Day4 IndiaMART+WhatsApp catalog | Week1 Amazon (kit) | Week1–2 LinkedIn/B2B outreach | Week2 small ads + optimize | Bi‑weekly price recheck | CB47: Partial (needs sample + doc evidence) | CC47: Reseller / Marketplace Seller | CD47: https://robu.in/product/raspberry-pi-pico/ | CE47: Marketplace seller (badge depends on platform); prefer GST invoice + established store ratings. | CH47: Y | CI47: N | CJ47: 7 | CK47: 7 days DOA replacement; channel return policy applies. | CL47: Domestic shipment (GST invoice preferred) | CM47: 3 months replacement for functional failure (conditions apply). | CN47: Bangalore: 48–72 hrs replacement (stock permitting); else 7–14 days via supplier. | CO47: Y | CP47: MACFOS LIMITED (Robu.in) | CQ47: Robu.in | https://robu.in/product/raspberry-pi-pico/ | CR47: 2026-01-06 | CS47: Works (healthy margin). Gross≈27%. Est Amazon net≈9% after ~18% fees. | Channels: Amazon (as verified kit) + Direct (B2B) + IndiaMART; also Website/WhatsApp + LinkedIn outreach. | Bundle: Add: essentials kit (cables/adapters) + quick‑start card + basic support + 7‑day DOA replacement. | CT47: Medium | CU47: 27.4 | CV47: Demand 6.0/40 (units=3.0); Margin 0.3/30 (GM%=0.4); Channel 5.0/10 (AmazonNet%=NA); Sourcing 6.2/10 (mode=Local); Lead 10.0/10 (days=7.0); Fit 0.0/10; Penalty 0.0/10.
A48: MCU-ARD-UNO-R4 | B48: Microcontroller | C48: Board | D48: Arduino UNO R4 | E48: Arduino | F48: UNO R4 | G48: Minima/WiFi | H48: Arduino ecosystem | I48: Education/IoT | J48: Students | K48: Local | L48: Local | M48: 699 | N48: 1080 | O48: 0.3528 | Q48: =HYPERLINK("https://www.amazon.in/s?k="&SUBSTITUTE($D48," ","+"),"Amazon search") -> Amazon search | R48: 699 | S48: https://robu.in/product/official-arduino-uno-ek-minima/ | U48: =HYPERLINK("https://www.alibaba.com/trade/search?SearchText="&SUBSTITUTE($D48," ","+"),"Alibaba search") -> Alibaba search | W48: =HYPERLINK("https://www.lcsc.com/search?q="&SUBSTITUTE($D48," ","+"),"LCSC search") -> LCSC search | Y48: =HYPERLINK("https://www.mouser.in/c/?q="&SUBSTITUTE($D48," ","+"),"Mouser search") -> Mouser search | AA48: =HYPERLINK("https://www.digikey.in/en/products/filter?keywords="&SUBSTITUTE($D48," ","+"),"DigiKey search") -> DigiKey search | AC48: =Inputs_Assumptions!$B$7 -> 150 | AD48: =Inputs_Assumptions!$B$7 -> 150 | AE48: =Inputs_Assumptions!$B$5 -> 0.1 | AF48: =Inputs_Assumptions!$B$6 -> 0.18 | AG48: =Inputs_Assumptions!$B$4 -> 83 | AJ48: =IF(AH48<>"",(AH48*AG48+AD48)*(1+AE48)*(1+AF48),(M48+AD48)*(1+AF48)) -> 1001.82 | AK48: =Inputs_Assumptions!$B$9 -> 0.35 | AL48: =IF(AJ48<>"",AJ48/(1-AK48),"") -> 1541.2615 | AM48: =Inputs_Assumptions!$B$8 -> 0.18 | AN48: =IF(AND(P48<>"",AJ48<>"",AM48<>""),(P48-AJ48-P48*AM48)/P48,"") | AO48: B | AU48: 2025-12-21 | AW48: 2025-12-20 | BC48: 2025-12-21 | BD48: MACFOS LIMITED (Robu.in) | BE48: https://robu.in/ | BF48: Survey No. 78/1, Sumant Building, Dynamic Logistics Trade Park, Dighi, Bhosari-Alandi Road, Pune, Maharashtra 411015, India | BG48: Phone: 1800 266 6123 / 020 6819 7600 ; Email: info@robu.in | BM48: 699 | BN48: Robu.in | BO48: https://robu.in/product/official-arduino-uno-ek-minima/ | BP48: MACFOS LIMITED (Robu.in) | BQ48: https://robu.in/ | BR48: Survey No. 78/1, Sumant Building, Dynamic Logistics Trade Park, Dighi, Bhosari-Alandi Road, Pune, Maharashtra 411015, India | BS48: Phone: 1800 266 6123 / 020 6819 7600 ; Email: info@robu.in | BT48: 2025-12-21 | BU48: Official UNO R4 Minima listing. | BV48: Works (healthy margin). Gross≈27%. Est Amazon net≈9% after ~18% fees. | BW48: Amazon (as verified kit) + Direct (B2B) + IndiaMART; also Website/WhatsApp + LinkedIn outreach. | BX48: Add: essentials kit (cables/adapters) + quick‑start card + basic support + 7‑day DOA replacement. | BY48: Title: Arduino UNO R4 | Verified/QA Tested | Quick‑Start + Support | GST Invoice Bullets: - Key specs: Arduino ecosystem - Use case: Education/IoT - Pre‑tested unit with packaging QC sticker + photo proof before dispatch. - Support: setup guide (QR) + WhatsApp troubleshooting; replacement DOA policy. - Ideal for startups/labs/training centers; bulk pricing available. | BZ48: electronics module, dev kit, maker kit, embedded components | CA48: Day1–2 sample+QC | Day3 assets+pack insert QR | Day4 IndiaMART+WhatsApp catalog | Week1 Amazon (kit) | Week1–2 LinkedIn/B2B outreach | Week2 small ads + optimize | Bi‑weekly price recheck | CB48: Partial (needs sample + doc evidence) | CC48: Reseller / Marketplace Seller | CD48: https://robu.in/product/official-arduino-uno-ek-minima/ | CE48: Marketplace seller (badge depends on platform); prefer GST invoice + established store ratings. | CH48: Y | CI48: N | CJ48: 7 | CK48: 7 days DOA replacement; channel return policy applies. | CL48: Domestic shipment (GST invoice preferred) | CM48: 3 months replacement for functional failure (conditions apply). | CN48: Bangalore: 48–72 hrs replacement (stock permitting); else 7–14 days via supplier. | CO48: Y | CP48: MACFOS LIMITED (Robu.in) | CQ48: Robu.in | https://robu.in/product/official-arduino-uno-ek-minima/ | CR48: 2026-01-06 | CS48: Works (healthy margin). Gross≈27%. Est Amazon net≈9% after ~18% fees. | Channels: Amazon (as verified kit) + Direct (B2B) + IndiaMART; also Website/WhatsApp + LinkedIn outreach. | Bundle: Add: essentials kit (cables/adapters) + quick‑start card + basic support + 7‑day DOA replacement. | CT48: Medium | CU48: 21.4 | CV48: Demand 0.0/40 (units=0.0); Margin 0.3/30 (GM%=0.4); Channel 5.0/10 (AmazonNet%=NA); Sourcing 6.2/10 (mode=Local); Lead 10.0/10 (days=7.0); Fit 0.0/10; Penalty 0.0/10.
A49: MCU-ARD-NANO-EVERY | B49: Microcontroller | C49: Board | D49: Arduino Nano Every | E49: Arduino | F49: Nano Every | H49: ATmega4809 | I49: Education | J49: Students | K49: Local | L49: Local | M49: 700 | N49: 1000 | O49: =IF(AND(M49<>"",N49<>""),(N49-M49)/N49,"") -> 0.3 | Q49: =HYPERLINK("https://www.amazon.in/s?k="&SUBSTITUTE($D49," ","+"),"Amazon search") -> Amazon search | S49: =HYPERLINK("https://robu.in/?s="&SUBSTITUTE($D49," ","+")&"&post_type=product","Robu search") -> Robu search | U49: =HYPERLINK("https://www.alibaba.com/trade/search?SearchText="&SUBSTITUTE($D49," ","+"),"Alibaba search") -> Alibaba search | W49: =HYPERLINK("https://www.lcsc.com/search?q="&SUBSTITUTE($D49," ","+"),"LCSC search") -> LCSC search | Y49: =HYPERLINK("https://www.mouser.in/c/?q="&SUBSTITUTE($D49," ","+"),"Mouser search") -> Mouser search | AA49: =HYPERLINK("https://www.digikey.in/en/products/filter?keywords="&SUBSTITUTE($D49," ","+"),"DigiKey search") -> DigiKey search | AC49: =Inputs_Assumptions!$B$7 -> 150 | AD49: =Inputs_Assumptions!$B$7 -> 150 | AE49: =Inputs_Assumptions!$B$5 -> 0.1 | AF49: =Inputs_Assumptions!$B$6 -> 0.18 | AG49: =Inputs_Assumptions!$B$4 -> 83 | AJ49: =IF(AH49<>"",(AH49*AG49+AD49)*(1+AE49)*(1+AF49),(M49+AD49)*(1+AF49)) -> 1003 | AK49: =Inputs_Assumptions!$B$9 -> 0.35 | AL49: =IF(AJ49<>"",AJ49/(1-AK49),"") -> 1543.0769 | AM49: =Inputs_Assumptions!$B$8 -> 0.18 | AN49: =IF(AND(P49<>"",AJ49<>"",AM49<>""),(P49-AJ49-P49*AM49)/P49,"") | AO49: B | AW49: 2025-12-20 | BV49: Works for Direct/B2B; marketplaces need bundle/price-up. Gross≈21%. Est Amazon net≈3% after ~18% fees. | BW49: Direct (B2B) + IndiaMART; Amazon only if bundled/priced higher. | BX49: Bundle: official/verified power supply + high‑end SD/SSD + heatsink/fan (if needed) + camera options + enclosure + quick‑start + remote setup session. | BY49: Title: Arduino Nano Every | Verified/QA Tested | Quick‑Start + Support | GST Invoice Bullets: - Key specs: ATmega4809 - Use case: Education - Pre‑tested unit with packaging QC sticker + photo proof before dispatch. - Support: setup guide (QR) + WhatsApp troubleshooting; replacement DOA policy. - Ideal for startups/labs/training centers; bulk pricing available. | BZ49: jetson orin, jetson nano, edge ai dev kit, nvidia jetson, vision ai kit, cuda devkit, ros2 ai, edge inference | CA49: Day1–2 sample+QC | Day3 assets+pack insert QR | Day4 IndiaMART+WhatsApp catalog | Week1 Amazon (kit) | Week1–2 LinkedIn/B2B outreach | Week2 small ads + optimize | Bi‑weekly price recheck | CB49: Pending (missing seller profile) | CC49: Reseller (needs confirmation) | CE49: Unknown | CH49: N | CI49: N | CJ49: 7 | CK49: 7 days DOA replacement; channel return policy applies. | CL49: Domestic shipment (GST invoice preferred) | CM49: 3 months replacement for functional failure (conditions apply). | CN49: 7–14 days (confirm with supplier) | CO49: N | CR49: 2026-01-06 | CS49: Works for Direct/B2B; marketplaces need bundle/price-up. Gross≈21%. Est Amazon net≈3% after ~18% fees. | Channels: Direct (B2B) + IndiaMART; Amazon only if bundled/priced higher. | Bundle: Bundle: official/verified power supply + high‑end SD/SSD + heatsink/fan (if needed) + camera options + enclosure + quick‑start + remote setup session. | CT49: Medium | CU49: 25.2 | CV49: Demand 0.0/40 (units=0.0); Margin 0.0/30 (GM%=-49494949149149495296.0); Channel 5.0/10 (AmazonNet%=NA); Sourcing 6.2/10 (mode=Local); Lead 10.0/10 (days=7.0); Fit 4.0/10; Penalty 0.0/10.
A50: CONN-CP2102 | B50: Connectivity | C50: Module | D50: USB-UART CP2102 Module | E50: Silicon Labs | F50: CP2102 | H50: USB to UART | I50: Debug/program | J50: All devs | K50: Local | L50: Local | M50: 107 | N50: 170 | O50: 0.3706 | Q50: =HYPERLINK("https://www.amazon.in/s?k="&SUBSTITUTE($D50," ","+"),"Amazon search") -> Amazon search | R50: 107 | S50: https://robu.in/product/cp2102-usb-to-ttl-serial-converter-module-2/ | U50: =HYPERLINK("https://www.alibaba.com/trade/search?SearchText="&SUBSTITUTE($D50," ","+"),"Alibaba search") -> Alibaba search | W50: =HYPERLINK("https://www.lcsc.com/search?q="&SUBSTITUTE($D50," ","+"),"LCSC search") -> LCSC search | Y50: =HYPERLINK("https://www.mouser.in/c/?q="&SUBSTITUTE($D50," ","+"),"Mouser search") -> Mouser search | AA50: =HYPERLINK("https://www.digikey.in/en/products/filter?keywords="&SUBSTITUTE($D50," ","+"),"DigiKey search") -> DigiKey search | AC50: =Inputs_Assumptions!$B$7 -> 150 | AD50: =Inputs_Assumptions!$B$7 -> 150 | AE50: =Inputs_Assumptions!$B$5 -> 0.1 | AF50: =Inputs_Assumptions!$B$6 -> 0.18 | AG50: =Inputs_Assumptions!$B$4 -> 83 | AJ50: =IF(AH50<>"",(AH50*AG50+AD50)*(1+AE50)*(1+AF50),(M50+AD50)*(1+AF50)) -> 303.26 | AK50: =Inputs_Assumptions!$B$9 -> 0.35 | AL50: =IF(AJ50<>"",AJ50/(1-AK50),"") -> 466.55385 | AM50: =Inputs_Assumptions!$B$8 -> 0.18 | AN50: =IF(AND(P50<>"",AJ50<>"",AM50<>""),(P50-AJ50-P50*AM50)/P50,"") | AO50: A | AP50: 30 | AQ50: 30 | AR50: 60 | AS50: 9 | AU50: 2025-12-21 | AW50: 2025-12-20 | BC50: 2025-12-21 | BD50: MACFOS LIMITED (Robu.in) | BE50: https://robu.in/ | BF50: Survey No. 78/1, Sumant Building, Dynamic Logistics Trade Park, Dighi, Bhosari-Alandi Road, Pune, Maharashtra 411015, India | BG50: Phone: 1800 266 6123 / 020 6819 7600 ; Email: info@robu.in | BM50: 107 | BN50: Robu.in | BO50: https://robu.in/product/cp2102-usb-to-ttl-serial-converter-module-2/ | BP50: MACFOS LIMITED (Robu.in) | BQ50: https://robu.in/ | BR50: Survey No. 78/1, Sumant Building, Dynamic Logistics Trade Park, Dighi, Bhosari-Alandi Road, Pune, Maharashtra 411015, India | BS50: Phone: 1800 266 6123 / 020 6819 7600 ; Email: info@robu.in | BT50: 2025-12-21 | BV50: Works (healthy margin). Gross≈25%. Est Amazon net≈7% after ~18% fees. | BW50: Amazon (as verified kit) + Direct (B2B) + IndiaMART; also Website/WhatsApp + LinkedIn outreach. | BX50: Add: essentials kit (cables/adapters) + quick‑start card + basic support + 7‑day DOA replacement. | BY50: Title: USB-UART CP2102 Module | Verified/QA Tested | Quick‑Start + Support | GST Invoice Bullets: - Key specs: USB to UART - Use case: Debug/program - Pre‑tested unit with packaging QC sticker + photo proof before dispatch. - Support: setup guide (QR) + WhatsApp troubleshooting; replacement DOA policy. - Ideal for startups/labs/training centers; bulk pricing available. | BZ50: electronics module, dev kit, maker kit, embedded components | CA50: Day1–2 sample+QC | Day3 assets+pack insert QR | Day4 IndiaMART+WhatsApp catalog | Week1 Amazon (kit) | Week1–2 LinkedIn/B2B outreach | Week2 small ads + optimize | Bi‑weekly price recheck | CB50: Partial (needs sample + doc evidence) | CC50: Reseller / Marketplace Seller | CD50: https://robu.in/product/cp2102-usb-to-ttl-serial-converter-module-2/ | CE50: Marketplace seller (badge depends on platform); prefer GST invoice + established store ratings. | CH50: Y | CI50: N | CJ50: 7 | CK50: Marketplace return policy; 7 days DOA replacement. | CL50: Domestic shipment (GST invoice preferred) | CM50: 30 days replacement for DOA. | CN50: Bangalore: 48–72 hrs replacement (stock permitting); else 7–14 days via supplier. | CO50: Y | CP50: MACFOS LIMITED (Robu.in) | CQ50: Robu.in | https://robu.in/product/cp2102-usb-to-ttl-serial-converter-module-2/ | CR50: 2026-01-06 | CS50: Works (healthy margin). Gross≈25%. Est Amazon net≈7% after ~18% fees. | Channels: Amazon (as verified kit) + Direct (B2B) + IndiaMART; also Website/WhatsApp + LinkedIn outreach. | Bundle: Add: essentials kit (cables/adapters) + quick‑start card + basic support + 7‑day DOA replacement. | CT50: High | CU50: 39.4 | CV50: Demand 18.0/40 (units=9.0); Margin 0.3/30 (GM%=0.4); Channel 5.0/10 (AmazonNet%=NA); Sourcing 6.2/10 (mode=Local); Lead 10.0/10 (days=7.0); Fit 0.0/10; Penalty 0.0/10.
A51: CONN-FT232 | B51: Connectivity | C51: Module | D51: USB-UART FT232RL Module | E51: FTDI | F51: FT232RL | H51: USB to UART | I51: Reliable serial | J51: Pros | K51: Local | L51: Local | M51: 220 | N51: 400 | O51: =IF(AND(M51<>"",N51<>""),(N51-M51)/N51,"") -> 0.45 | Q51: =HYPERLINK("https://www.amazon.in/s?k="&SUBSTITUTE($D51," ","+"),"Amazon search") -> Amazon search | S51: =HYPERLINK("https://robu.in/?s="&SUBSTITUTE($D51," ","+")&"&post_type=product","Robu search") -> Robu search | U51: =HYPERLINK("https://www.alibaba.com/trade/search?SearchText="&SUBSTITUTE($D51," ","+"),"Alibaba search") -> Alibaba search | W51: =HYPERLINK("https://www.lcsc.com/search?q="&SUBSTITUTE($D51," ","+"),"LCSC search") -> LCSC search | Y51: =HYPERLINK("https://www.mouser.in/c/?q="&SUBSTITUTE($D51," ","+"),"Mouser search") -> Mouser search | AA51: =HYPERLINK("https://www.digikey.in/en/products/filter?keywords="&SUBSTITUTE($D51," ","+"),"DigiKey search") -> DigiKey search | AC51: =Inputs_Assumptions!$B$7 -> 150 | AD51: =Inputs_Assumptions!$B$7 -> 150 | AE51: =Inputs_Assumptions!$B$5 -> 0.1 | AF51: =Inputs_Assumptions!$B$6 -> 0.18 | AG51: =Inputs_Assumptions!$B$4 -> 83 | AJ51: =IF(AH51<>"",(AH51*AG51+AD51)*(1+AE51)*(1+AF51),(M51+AD51)*(1+AF51)) -> 436.6 | AK51: =Inputs_Assumptions!$B$9 -> 0.35 | AL51: =IF(AJ51<>"",AJ51/(1-AK51),"") -> 671.69231 | AM51: =Inputs_Assumptions!$B$8 -> 0.18 | AN51: =IF(AND(P51<>"",AJ51<>"",AM51<>""),(P51-AJ51-P51*AM51)/P51,"") | AO51: B | AP51: 10 | AQ51: 10 | AR51: 20 | AS51: 3 | AW51: 2025-12-20 | BV51: Works (healthy margin). Gross≈37%. Est Amazon net≈19% after ~18% fees. | BW51: Amazon (as verified kit) + Direct (B2B) + IndiaMART; also Website/WhatsApp + LinkedIn outreach. | BX51: Add: essentials kit (cables/adapters) + quick‑start card + basic support + 7‑day DOA replacement. | BY51: Title: USB-UART FT232RL Module | Verified/QA Tested | Quick‑Start + Support | GST Invoice Bullets: - Key specs: USB to UART - Use case: Reliable serial - Pre‑tested unit with packaging QC sticker + photo proof before dispatch. - Support: setup guide (QR) + WhatsApp troubleshooting; replacement DOA policy. - Ideal for startups/labs/training centers; bulk pricing available. | BZ51: electronics module, dev kit, maker kit, embedded components | CA51: Day1–2 sample+QC | Day3 assets+pack insert QR | Day4 IndiaMART+WhatsApp catalog | Week1 Amazon (kit) | Week1–2 LinkedIn/B2B outreach | Week2 small ads + optimize | Bi‑weekly price recheck | CB51: Pending (missing seller profile) | CC51: Reseller (needs confirmation) | CE51: Unknown | CH51: N | CI51: N | CJ51: 7 | CK51: Marketplace return policy; 7 days DOA replacement. | CL51: Domestic shipment (GST invoice preferred) | CM51: 30 days replacement for DOA. | CN51: 7–14 days (confirm with supplier) | CO51: N | CR51: 2026-01-06 | CS51: Works (healthy margin). Gross≈37%. Est Amazon net≈19% after ~18% fees. | Channels: Amazon (as verified kit) + Direct (B2B) + IndiaMART; also Website/WhatsApp + LinkedIn outreach. | Bundle: Add: essentials kit (cables/adapters) + quick‑start card + basic support + 7‑day DOA replacement. | CT51: Medium | CU51: 22.2 | CV51: Demand 6.0/40 (units=3.0); Margin 0.0/30 (GM%=-128787877877878784000.0); Channel 5.0/10 (AmazonNet%=NA); Sourcing 6.2/10 (mode=Local); Lead 10.0/10 (days=7.0); Fit 0.0/10; Penalty 5.0/10.
A52: CONN-FT4232H | B52: Connectivity | C52: Module | D52: USB-JTAG FT4232H | E52: FTDI | F52: FT4232H | H52: Multi-channel USB bridge (JTAG/UART) | I52: FPGA programming | J52: FPGA users | K52: Import | L52: Import | M52: 550 | N52: 900 | O52: =IF(AND(M52<>"",N52<>""),(N52-M52)/N52,"") -> 0.38888889 | Q52: =HYPERLINK("https://www.amazon.in/s?k="&SUBSTITUTE($D52," ","+"),"Amazon search") -> Amazon search | S52: =HYPERLINK("https://robu.in/?s="&SUBSTITUTE($D52," ","+")&"&post_type=product","Robu search") -> Robu search | U52: =HYPERLINK("https://www.alibaba.com/trade/search?SearchText="&SUBSTITUTE($D52," ","+"),"Alibaba search") -> Alibaba search | W52: =HYPERLINK("https://www.lcsc.com/search?q="&SUBSTITUTE($D52," ","+"),"LCSC search") -> LCSC search | Y52: =HYPERLINK("https://www.mouser.in/c/?q="&SUBSTITUTE($D52," ","+"),"Mouser search") -> Mouser search | AA52: =HYPERLINK("https://www.digikey.in/en/products/filter?keywords="&SUBSTITUTE($D52," ","+"),"DigiKey search") -> DigiKey search | AC52: =Inputs_Assumptions!$B$7 -> 150 | AD52: =Inputs_Assumptions!$B$7 -> 150 | AE52: =Inputs_Assumptions!$B$5 -> 0.1 | AF52: =Inputs_Assumptions!$B$6 -> 0.18 | AG52: =Inputs_Assumptions!$B$4 -> 83 | AJ52: =IF(AH52<>"",(AH52*AG52+AD52)*(1+AE52)*(1+AF52),(M52+AD52)*(1+AF52)) -> 826 | AK52: =Inputs_Assumptions!$B$9 -> 0.35 | AL52: =IF(AJ52<>"",AJ52/(1-AK52),"") -> 1270.7692 | AM52: =Inputs_Assumptions!$B$8 -> 0.18 | AN52: =IF(AND(P52<>"",AJ52<>"",AM52<>""),(P52-AJ52-P52*AM52)/P52,"") | AO52: C | AQ52: 6 | AR52: 12 | AS52: 2 | AW52: 2025-12-20 | BV52: Works (healthy margin). Gross≈31%. Est Amazon net≈13% after ~18% fees. | BW52: Amazon (as verified kit) + Direct (B2B) + IndiaMART; also Website/WhatsApp + LinkedIn outreach. | BX52: Add: ribbon cable/adapter set + USB extension + ESD pouch + printed quick‑start + driver QR + WhatsApp support + 6‑month replacement. | BY52: Title: USB-JTAG FT4232H | Verified/QA Tested | Quick‑Start + Support | GST Invoice Bullets: - Key specs: Multi-channel USB bridge (JTAG/UART) - Use case: FPGA programming - Pre‑tested unit with packaging QC sticker + photo proof before dispatch. - Support: setup guide (QR) + WhatsApp troubleshooting; replacement DOA policy. - Ideal for startups/labs/training centers; bulk pricing available. | BZ52: USB JTAG, xilinx jtag, altera jtag, quartus programmer, vivado programmer, fpga debugger, usb blaster, platform cable | CA52: Day1–2 sample+QC | Day3 assets+pack insert QR | Day4 IndiaMART+WhatsApp catalog | Week1 Amazon (kit) | Week1–2 LinkedIn/B2B outreach | Week2 small ads + optimize | Bi‑weekly price recheck | CB52: Pending (missing seller profile) | CC52: Reseller (needs confirmation) | CE52: Unknown | CH52: N | CI52: N | CJ52: 7 | CK52: Direct/IndiaMART: 7 days DOA replacement. Amazon: follow marketplace returns + your 7‑day DOA policy. | CL52: Domestic shipment (GST invoice preferred) | CM52: 6 months (replacement for DOA/functional failure; physical damage excluded). | CN52: 7–14 days (confirm with supplier) | CO52: N | CR52: 2026-01-06 | CS52: Works (healthy margin). Gross≈31%. Est Amazon net≈13% after ~18% fees. | Channels: Amazon (as verified kit) + Direct (B2B) + IndiaMART; also Website/WhatsApp + LinkedIn outreach. | Bundle: Add: ribbon cable/adapter set + USB extension + ESD pouch + printed quick‑start + driver QR + WhatsApp support + 6‑month replacement. | CT52: Low | CU52: 21 | CV52: Demand 4.0/40 (units=2.0); Margin 0.0/30 (GM%=-58361391280169467904.0); Channel 5.0/10 (AmazonNet%=NA); Sourcing 0.0/10 (mode=Import); Lead 10.0/10 (days=7.0); Fit 4.0/10; Penalty 2.0/10.
A53: CONN-LAN8720 | B53: Connectivity | C53: Module | D53: Ethernet PHY Module LAN8720 | E53: Microchip | F53: LAN8720 | H53: RMII PHY | I53: Ethernet in MCU/FPGA | J53: IoT devs | K53: Local | L53: Local | M53: 120 | N53: 250 | O53: =IF(AND(M53<>"",N53<>""),(N53-M53)/N53,"") -> 0.52 | Q53: =HYPERLINK("https://www.amazon.in/s?k="&SUBSTITUTE($D53," ","+"),"Amazon search") -> Amazon search | S53: =HYPERLINK("https://robu.in/?s="&SUBSTITUTE($D53," ","+")&"&post_type=product","Robu search") -> Robu search | U53: =HYPERLINK("https://www.alibaba.com/trade/search?SearchText="&SUBSTITUTE($D53," ","+"),"Alibaba search") -> Alibaba search | W53: =HYPERLINK("https://www.lcsc.com/search?q="&SUBSTITUTE($D53," ","+"),"LCSC search") -> LCSC search | Y53: =HYPERLINK("https://www.mouser.in/c/?q="&SUBSTITUTE($D53," ","+"),"Mouser search") -> Mouser search | AA53: =HYPERLINK("https://www.digikey.in/en/products/filter?keywords="&SUBSTITUTE($D53," ","+"),"DigiKey search") -> DigiKey search | AC53: =Inputs_Assumptions!$B$7 -> 150 | AD53: =Inputs_Assumptions!$B$7 -> 150 | AE53: =Inputs_Assumptions!$B$5 -> 0.1 | AF53: =Inputs_Assumptions!$B$6 -> 0.18 | AG53: =Inputs_Assumptions!$B$4 -> 83 | AJ53: =IF(AH53<>"",(AH53*AG53+AD53)*(1+AE53)*(1+AF53),(M53+AD53)*(1+AF53)) -> 318.6 | AK53: =Inputs_Assumptions!$B$9 -> 0.35 | AL53: =IF(AJ53<>"",AJ53/(1-AK53),"") -> 490.15385 | AM53: =Inputs_Assumptions!$B$8 -> 0.18 | AN53: =IF(AND(P53<>"",AJ53<>"",AM53<>""),(P53-AJ53-P53*AM53)/P53,"") | AO53: C | AW53: 2025-12-20 | BV53: Works (healthy margin). Gross≈43%. Est Amazon net≈25% after ~18% fees. | BW53: Amazon (as verified kit) + Direct (B2B) + IndiaMART; also Website/WhatsApp + LinkedIn outreach. | BX53: Add: essentials kit (cables/adapters) + quick‑start card + basic support + 7‑day DOA replacement. | BY53: Title: Ethernet PHY Module LAN8720 | Verified/QA Tested | Quick‑Start + Support | GST Invoice Bullets: - Key specs: RMII PHY - Use case: Ethernet in MCU/FPGA - Pre‑tested unit with packaging QC sticker + photo proof before dispatch. - Support: setup guide (QR) + WhatsApp troubleshooting; replacement DOA policy. - Ideal for startups/labs/training centers; bulk pricing available. | BZ53: electronics module, dev kit, maker kit, embedded components | CA53: Day1–2 sample+QC | Day3 assets+pack insert QR | Day4 IndiaMART+WhatsApp catalog | Week1 Amazon (kit) | Week1–2 LinkedIn/B2B outreach | Week2 small ads + optimize | Bi‑weekly price recheck | CB53: Pending (missing seller profile) | CC53: Reseller (needs confirmation) | CE53: Unknown | CH53: N | CI53: N | CJ53: 7 | CK53: Marketplace return policy; 7 days DOA replacement. | CL53: Domestic shipment (GST invoice preferred) | CM53: 30 days replacement for DOA. | CN53: 7–14 days (confirm with supplier) | CO53: N | CR53: 2026-01-06 | CS53: Works (healthy margin). Gross≈43%. Est Amazon net≈25% after ~18% fees. | Channels: Amazon (as verified kit) + Direct (B2B) + IndiaMART; also Website/WhatsApp + LinkedIn outreach. | Bundle: Add: essentials kit (cables/adapters) + quick‑start card + basic support + 7‑day DOA replacement. | CT53: Low | CU53: 16.2 | CV53: Demand 0.0/40 (units=0.0); Margin 0.0/30 (GM%=-214141412612614127616.0); Channel 5.0/10 (AmazonNet%=NA); Sourcing 6.2/10 (mode=Local); Lead 10.0/10 (days=7.0); Fit 0.0/10; Penalty 5.0/10.
